Workbook

Sheet README
B1: Project Budget Calculator
B3: PURPOSE | C3: Calculates the Budgeted balance of each project and phases it over the remaining months of the project.
B5: FORMULAS
B6: Budgeted | C6: Budgeted = Contracted Budget − WIP to date (the sum of WIP logged in months up to and including the Current Month).
B7: Phased Budgeted | C7: Budgeted is spread only over the project months AFTER the Current Month, using that project's phasing weights for those months, renormalised to 1.0.
C8: Phased Budgeted (month k) = Budgeted × weight(k) ÷ Σ weights of remaining months.
B9: Weights | C9: Enter raw weights (e.g. 1,2,2,2,2). They don't need to sum to 1. If a project has no weights at all, every month gets an equal weight.
B10: Example (from the slide) | C10: Contract 10,000. 5 months, weights 1:2:2:2:2. 1,000 of WIP logged in month I (the current month).
C11: → Budgeted = 9,000, phased over months II–V (weights 2:2:2:2 → 25% each) = 2,250 per month.
B13: SHEETS
B14: Projects | C14: Project ∑ table (page 1). Holds the global Current Month field. Add a project by filling in the next empty row. Use the header filter buttons to filter.
B15: Phasing | C15: Raw phasing weights per project, month 1–24 of the project. Also shows the weights normalised to 1.0 over the full duration.
B16: WIP Log | C16: Monthly WIP actuals per project on the calendar timeline. Only months ≤ Current Month count towards WIP to date.
B17: Project Page | C17: Page 2: pick a project from the dropdown to see its details, month-by-month phasing and chart (the "visualize" view).
B18: Timeline | C18: Page 3: Gantt-style view of every project. Each cell shows the WIP actual (≤ Current Month) or the Phased Budgeted (after it).
B19: Aggregator | C19: Page 4: Σ WIP + Σ Phased Budgeted per month against the manual TRM input, with a chart and calendar-year totals.
B20: Phased Budget | C20: Calculation grid (no inputs): Phased Budgeted per project per calendar month.
B22: HOW TO USE
B23: Yellow cells | C23: Key inputs: Current Month, Timeline Start, the TRM row and the project selector.
B24: Blue text | C24: Hard-coded inputs: project fields, weights, WIP amounts. Black text = formulas. Green text = links to another sheet.
B25: Light yellow grids | C25: Input grids on Phasing and WIP Log. Grey cells there are outside the project's duration or window.
B26: Monthly routine | C26: 1) Log the month's WIP on WIP Log. 2) Move Current Month forward one month on Projects. Everything recalculates.
B27: Status column | C27: Projects!N flags problems: WIP above contract, no remaining months left to phase the budget into, missing fields, etc.
B29: LIMITS & ASSUMPTIONS
B30: Capacity | C30: 50 projects, durations up to 24 months, calendar timeline of 36 months from Timeline Start (default Jan 2026 – Dec 2028).
B31: Timeline Start | C31: Change it only before logging WIP: the WIP Log columns are tied to calendar months, so moving the start shifts those columns.
B32: Months | C32: Starting Month and Current Month are compared by year and month only (the day is ignored).
B33: Units | C33: All amounts are in one currency unit (enter 10000 for 10k). No currency symbol is applied.
B34: TRM | C34: Monthly comparison target, entered manually on the Aggregator sheet (per user).
B35: Annual totals | C35: Calendar years (Jan–Dec), WIP actuals + Phased Budgeted.
B36: Source | C36: Logic from "Revenue_Forecast_Calculator.pptx", with the user's clarifications from 2026-10-06.

Sheet Projects
A1: Project ∑ Table
A2: Current Month | C2: 46296 | D2: Months up to and including this month are actuals (WIP). Later months are forecast (Phased Budgeted).
A3: Timeline Start | C3: 46023 | D3: First month of the 36-month calendar timeline. Change it only before logging WIP.
A5: # | B5: Project Name | C5: Engagement Manager | D5: Starting Month | E5: Duration (months) | F5: End Month | G5: Contracted Budget | H5: WIP to Date | I5: Budgeted (Contract − WIP) | J5: Remaining Months | K5: Phased Budgeted – Next Month | L5: Phased Budgeted – Rest of Current Year | M5: Current-Year Forecast (WIP + Phased) | N5: Status
A6: 1 | B6: Example Project (slide) | C6: J. Doe | D6: 46296 | E6: 5 | F6: =IF(OR(D6="",E6=""),"",EDATE(D6,E6-1)) -> 46419 | G6: 10000 | H6: =IF(B6="","",'WIP Log'!C6) -> 1000 | I6: =IF(B6="","",N(G6)-N(H6)) -> 9000 | J6: =IF(OR(B6="",E6=""),"",MAX(0,E6-Phasing!F6+1)) -> 4 | K6: =IF(B6="","",IF(AND(((YEAR(Projects!$C$2)-YEAR(Projects!$C$3))*12+MONTH(Projects!$C$2)-MONTH(Projects!$C$3)+1)+1>=1,((YEAR(Projects!$C$2)-YEAR(Projects!$C$3))*12+MONTH(Projects!$C$2)-MONTH(Projects!$C$3)+1)+1<=36),INDEX('Phased Budget'!$H6:$AQ6,((YEAR(Projects!$C$2)-YEAR(Projects!$C$3))*12+MONTH(Projects!$C$2)-MONTH(Projects!$C$3)+1)+1),0)) -> 2250 | L6: =IF(B6="","",SUMPRODUCT('Phased Budget'!$H6:$AQ6*(YEAR('Phased Budget'!$H$5:$AQ$5)=YEAR(Projects!$C$2)))) -> 4500 | M6: =IF(B6="","",SUMPRODUCT('WIP Log'!$D6:$AM6*('WIP Log'!$D$5:$AM$5<=Projects!$C$2)*(YEAR('WIP Log'!$D$5:$AM$5)=YEAR(Projects!$C$2)))+L6) -> 5500 | N6: =IF(B6="","",IF(OR(D6="",E6="",G6=""),"Missing start / duration / contract",IF(OR(E6<1,E6>24),"Duration must be 1–24",IF(I6<0,"WIP exceeds contract",IF(AND(J6=0,I6<>0),"Budget not phased: no remaining months",IF(AND(J6>0,Phasing!G6=0,I6<>0),"Budget not phased: remaining weights are 0",IF(OR(D6<Projects!$C$3,F6>EDATE(Projects!$C$3,35)),"Partly outside timeline",IF(Phasing!H6=0,"OK","Weights entered beyond duration (ignored)")))))))) -> OK
A7: 2 | F7: =IF(OR(D7="",E7=""),"",EDATE(D7,E7-1)) | H7: =IF(B7="","",'WIP Log'!C7) | I7: =IF(B7="","",N(G7)-N(H7)) | J7: =IF(OR(B7="",E7=""),"",MAX(0,E7-Phasing!F7+1)) | K7: =IF(B7="","",IF(AND(((YEAR(Projects!$C$2)-YEAR(Projects!$C$3))*12+MONTH(Projects!$C$2)-MONTH(Projects!$C$3)+1)+1>=1,((YEAR(Projects!$C$2)-YEAR(Projects!$C$3))*12+MONTH(Projects!$C$2)-MONTH(Projects!$C$3)+1)+1<=36),INDEX('Phased Budget'!$H7:$AQ7,((YEAR(Projects!$C$2)-YEAR(Projects!$C$3))*12+MONTH(Projects!$C$2)-MONTH(Projects!$C$3)+1)+1),0)) | L7: =IF(B7="","",SUMPRODUCT('Phased Budget'!$H7:$AQ7*(YEAR('Phased Budget'!$H$5:$AQ$5)=YEAR(Projects!$C$2)))) | M7: =IF(B7="","",SUMPRODUCT('WIP Log'!$D7:$AM7*('WIP Log'!$D$5:$AM$5<=Projects!$C$2)*(YEAR('WIP Log'!$D$5:$AM$5)=YEAR(Projects!$C$2)))+L7) | N7: =IF(B7="","",IF(OR(D7="",E7="",G7=""),"Missing start / duration / contract",IF(OR(E7<1,E7>24),"Duration must be 1–24",IF(I7<0,"WIP exceeds contract",IF(AND(J7=0,I7<>0),"Budget not phased: no remaining months",IF(AND(J7>0,Phasing!G7=0,I7<>0),"Budget not phased: remaining weights are 0",IF(OR(D7<Projects!$C$3,F7>EDATE(Projects!$C$3,35)),"Partly outside timeline",IF(Phasing!H7=0,"OK","Weights entered beyond duration (ignored)"))))))))
A8: 3 | F8: =IF(OR(D8="",E8=""),"",EDATE(D8,E8-1)) | H8: =IF(B8="","",'WIP Log'!C8) | I8: =IF(B8="","",N(G8)-N(H8)) | J8: =IF(OR(B8="",E8=""),"",MAX(0,E8-Phasing!F8+1)) | K8: =IF(B8="","",IF(AND(((YEAR(Projects!$C$2)-YEAR(Projects!$C$3))*12+MONTH(Projects!$C$2)-MONTH(Projects!$C$3)+1)+1>=1,((YEAR(Projects!$C$2)-YEAR(Projects!$C$3))*12+MONTH(Projects!$C$2)-MONTH(Projects!$C$3)+1)+1<=36),INDEX('Phased Budget'!$H8:$AQ8,((YEAR(Projects!$C$2)-YEAR(Projects!$C$3))*12+MONTH(Projects!$C$2)-MONTH(Projects!$C$3)+1)+1),0)) | L8: =IF(B8="","",SUMPRODUCT('Phased Budget'!$H8:$AQ8*(YEAR('Phased Budget'!$H$5:$AQ$5)=YEAR(Projects!$C$2)))) | M8: =IF(B8="","",SUMPRODUCT('WIP Log'!$D8:$AM8*('WIP Log'!$D$5:$AM$5<=Projects!$C$2)*(YEAR('WIP Log'!$D$5:$AM$5)=YEAR(Projects!$C$2)))+L8) | N8: =IF(B8="","",IF(OR(D8="",E8="",G8=""),"Missing start / duration / contract",IF(OR(E8<1,E8>24),"Duration must be 1–24",IF(I8<0,"WIP exceeds contract",IF(AND(J8=0,I8<>0),"Budget not phased: no remaining months",IF(AND(J8>0,Phasing!G8=0,I8<>0),"Budget not phased: remaining weights are 0",IF(OR(D8<Projects!$C$3,F8>EDATE(Projects!$C$3,35)),"Partly outside timeline",IF(Phasing!H8=0,"OK","Weights entered beyond duration (ignored)"))))))))
A9: 4 | F9: =IF(OR(D9="",E9=""),"",EDATE(D9,E9-1)) | H9: =IF(B9="","",'WIP Log'!C9) | I9: =IF(B9="","",N(G9)-N(H9)) | J9: =IF(OR(B9="",E9=""),"",MAX(0,E9-Phasing!F9+1)) | K9: =IF(B9="","",IF(AND(((YEAR(Projects!$C$2)-YEAR(Projects!$C$3))*12+MONTH(Projects!$C$2)-MONTH(Projects!$C$3)+1)+1>=1,((YEAR(Projects!$C$2)-YEAR(Projects!$C$3))*12+MONTH(Projects!$C$2)-MONTH(Projects!$C$3)+1)+1<=36),INDEX('Phased Budget'!$H9:$AQ9,((YEAR(Projects!$C$2)-YEAR(Projects!$C$3))*12+MONTH(Projects!$C$2)-MONTH(Projects!$C$3)+1)+1),0)) | L9: =IF(B9="","",SUMPRODUCT('Phased Budget'!$H9:$AQ9*(YEAR('Phased Budget'!$H$5:$AQ$5)=YEAR(Projects!$C$2)))) | M9: =IF(B9="","",SUMPRODUCT('WIP Log'!$D9:$AM9*('WIP Log'!$D$5:$AM$5<=Projects!$C$2)*(YEAR('WIP Log'!$D$5:$AM$5)=YEAR(Projects!$C$2)))+L9) | N9: =IF(B9="","",IF(OR(D9="",E9="",G9=""),"Missing start / duration / contract",IF(OR(E9<1,E9>24),"Duration must be 1–24",IF(I9<0,"WIP exceeds contract",IF(AND(J9=0,I9<>0),"Budget not phased: no remaining months",IF(AND(J9>0,Phasing!G9=0,I9<>0),"Budget not phased: remaining weights are 0",IF(OR(D9<Projects!$C$3,F9>EDATE(Projects!$C$3,35)),"Partly outside timeline",IF(Phasing!H9=0,"OK","Weights entered beyond duration (ignored)"))))))))
A10: 5 | F10: =IF(OR(D10="",E10=""),"",EDATE(D10,E10-1)) | H10: =IF(B10="","",'WIP Log'!C10) | I10: =IF(B10="","",N(G10)-N(H10)) | J10: =IF(OR(B10="",E10=""),"",MAX(0,E10-Phasing!F10+1)) | K10: =IF(B10="","",IF(AND(((YEAR(Projects!$C$2)-YEAR(Projects!$C$3))*12+MONTH(Projects!$C$2)-MONTH(Projects!$C$3)+1)+1>=1,((YEAR(Projects!$C$2)-YEAR(Projects!$C$3))*12+MONTH(Projects!$C$2)-MONTH(Projects!$C$3)+1)+1<=36),INDEX('Phased Budget'!$H10:$AQ10,((YEAR(Projects!$C$2)-YEAR(Projects!$C$3))*12+MONTH(Projects!$C$2)-MONTH(Projects!$C$3)+1)+1),0)) | L10: =IF(B10="","",SUMPRODUCT('Phased Budget'!$H10:$AQ10*(YEAR('Phased Budget'!$H$5:$AQ$5)=YEAR(Projects!$C$2)))) | M10: =IF(B10="","",SUMPRODUCT('WIP Log'!$D10:$AM10*('WIP Log'!$D$5:$AM$5<=Projects!$C$2)*(YEAR('WIP Log'!$D$5:$AM$5)=YEAR(Projects!$C$2)))+L10) | N10: =IF(B10="","",IF(OR(D10="",E10="",G10=""),"Missing start / duration / contract",IF(OR(E10<1,E10>24),"Duration must be 1–24",IF(I10<0,"WIP exceeds contract",IF(AND(J10=0,I10<>0),"Budget not phased: no remaining months",IF(AND(J10>0,Phasing!G10=0,I10<>0),"Budget not phased: remaining weights are 0",IF(OR(D10<Projects!$C$3,F10>EDATE(Projects!$C$3,35)),"Partly outside timeline",IF(Phasing!H10=0,"OK","Weights entered beyond duration (ignored)"))))))))
A11: 6 | F11: =IF(OR(D11="",E11=""),"",EDATE(D11,E11-1)) | H11: =IF(B11="","",'WIP Log'!C11) | I11: =IF(B11="","",N(G11)-N(H11)) | J11: =IF(OR(B11="",E11=""),"",MAX(0,E11-Phasing!F11+1)) | K11: =IF(B11="","",IF(AND(((YEAR(Projects!$C$2)-YEAR(Projects!$C$3))*12+MONTH(Projects!$C$2)-MONTH(Projects!$C$3)+1)+1>=1,((YEAR(Projects!$C$2)-YEAR(Projects!$C$3))*12+MONTH(Projects!$C$2)-MONTH(Projects!$C$3)+1)+1<=36),INDEX('Phased Budget'!$H11:$AQ11,((YEAR(Projects!$C$2)-YEAR(Projects!$C$3))*12+MONTH(Projects!$C$2)-MONTH(Projects!$C$3)+1)+1),0)) | L11: =IF(B11="","",SUMPRODUCT('Phased Budget'!$H11:$AQ11*(YEAR('Phased Budget'!$H$5:$AQ$5)=YEAR(Projects!$C$2)))) | M11: =IF(B11="","",SUMPRODUCT('WIP Log'!$D11:$AM11*('WIP Log'!$D$5:$AM$5<=Projects!$C$2)*(YEAR('WIP Log'!$D$5:$AM$5)=YEAR(Projects!$C$2)))+L11) | N11: =IF(B11="","",IF(OR(D11="",E11="",G11=""),"Missing start / duration / contract",IF(OR(E11<1,E11>24),"Duration must be 1–24",IF(I11<0,"WIP exceeds contract",IF(AND(J11=0,I11<>0),"Budget not phased: no remaining months",IF(AND(J11>0,Phasing!G11=0,I11<>0),"Budget not phased: remaining weights are 0",IF(OR(D11<Projects!$C$3,F11>EDATE(Projects!$C$3,35)),"Partly outside timeline",IF(Phasing!H11=0,"OK","Weights entered beyond duration (ignored)"))))))))
A12: 7 | F12: =IF(OR(D12="",E12=""),"",EDATE(D12,E12-1)) | H12: =IF(B12="","",'WIP Log'!C12) | I12: =IF(B12="","",N(G12)-N(H12)) | J12: =IF(OR(B12="",E12=""),"",MAX(0,E12-Phasing!F12+1)) | K12: =IF(B12="","",IF(AND(((YEAR(Projects!$C$2)-YEAR(Projects!$C$3))*12+MONTH(Projects!$C$2)-MONTH(Projects!$C$3)+1)+1>=1,((YEAR(Projects!$C$2)-YEAR(Projects!$C$3))*12+MONTH(Projects!$C$2)-MONTH(Projects!$C$3)+1)+1<=36),INDEX('Phased Budget'!$H12:$AQ12,((YEAR(Projects!$C$2)-YEAR(Projects!$C$3))*12+MONTH(Projects!$C$2)-MONTH(Projects!$C$3)+1)+1),0)) | L12: =IF(B12="","",SUMPRODUCT('Phased Budget'!$H12:$AQ12*(YEAR('Phased Budget'!$H$5:$AQ$5)=YEAR(Projects!$C$2)))) | M12: =IF(B12="","",SUMPRODUCT('WIP Log'!$D12:$AM12*('WIP Log'!$D$5:$AM$5<=Projects!$C$2)*(YEAR('WIP Log'!$D$5:$AM$5)=YEAR(Projects!$C$2)))+L12) | N12: =IF(B12="","",IF(OR(D12="",E12="",G12=""),"Missing start / duration / contract",IF(OR(E12<1,E12>24),"Duration must be 1–24",IF(I12<0,"WIP exceeds contract",IF(AND(J12=0,I12<>0),"Budget not phased: no remaining months",IF(AND(J12>0,Phasing!G12=0,I12<>0),"Budget not phased: remaining weights are 0",IF(OR(D12<Projects!$C$3,F12>EDATE(Projects!$C$3,35)),"Partly outside timeline",IF(Phasing!H12=0,"OK","Weights entered beyond duration (ignored)"))))))))
A13: 8 | F13: =IF(OR(D13="",E13=""),"",EDATE(D13,E13-1)) | H13: =IF(B13="","",'WIP Log'!C13) | I13: =IF(B13="","",N(G13)-N(H13)) | J13: =IF(OR(B13="",E13=""),"",MAX(0,E13-Phasing!F13+1)) | K13: =IF(B13="","",IF(AND(((YEAR(Projects!$C$2)-YEAR(Projects!$C$3))*12+MONTH(Projects!$C$2)-MONTH(Projects!$C$3)+1)+1>=1,((YEAR(Projects!$C$2)-YEAR(Projects!$C$3))*12+MONTH(Projects!$C$2)-MONTH(Projects!$C$3)+1)+1<=36),INDEX('Phased Budget'!$H13:$AQ13,((YEAR(Projects!$C$2)-YEAR(Projects!$C$3))*12+MONTH(Projects!$C$2)-MONTH(Projects!$C$3)+1)+1),0)) | L13: =IF(B13="","",SUMPRODUCT('Phased Budget'!$H13:$AQ13*(YEAR('Phased Budget'!$H$5:$AQ$5)=YEAR(Projects!$C$2)))) | M13: =IF(B13="","",SUMPRODUCT('WIP Log'!$D13:$AM13*('WIP Log'!$D$5:$AM$5<=Projects!$C$2)*(YEAR('WIP Log'!$D$5:$AM$5)=YEAR(Projects!$C$2)))+L13) | N13: =IF(B13="","",IF(OR(D13="",E13="",G13=""),"Missing start / duration / contract",IF(OR(E13<1,E13>24),"Duration must be 1–24",IF(I13<0,"WIP exceeds contract",IF(AND(J13=0,I13<>0),"Budget not phased: no remaining months",IF(AND(J13>0,Phasing!G13=0,I13<>0),"Budget not phased: remaining weights are 0",IF(OR(D13<Projects!$C$3,F13>EDATE(Projects!$C$3,35)),"Partly outside timeline",IF(Phasing!H13=0,"OK","Weights entered beyond duration (ignored)"))))))))
A14: 9 | F14: =IF(OR(D14="",E14=""),"",EDATE(D14,E14-1)) | H14: =IF(B14="","",'WIP Log'!C14) | I14: =IF(B14="","",N(G14)-N(H14)) | J14: =IF(OR(B14="",E14=""),"",MAX(0,E14-Phasing!F14+1)) | K14: =IF(B14="","",IF(AND(((YEAR(Projects!$C$2)-YEAR(Projects!$C$3))*12+MONTH(Projects!$C$2)-MONTH(Projects!$C$3)+1)+1>=1,((YEAR(Projects!$C$2)-YEAR(Projects!$C$3))*12+MONTH(Projects!$C$2)-MONTH(Projects!$C$3)+1)+1<=36),INDEX('Phased Budget'!$H14:$AQ14,((YEAR(Projects!$C$2)-YEAR(Projects!$C$3))*12+MONTH(Projects!$C$2)-MONTH(Projects!$C$3)+1)+1),0)) | L14: =IF(B14="","",SUMPRODUCT('Phased Budget'!$H14:$AQ14*(YEAR('Phased Budget'!$H$5:$AQ$5)=YEAR(Projects!$C$2)))) | M14: =IF(B14="","",SUMPRODUCT('WIP Log'!$D14:$AM14*('WIP Log'!$D$5:$AM$5<=Projects!$C$2)*(YEAR('WIP Log'!$D$5:$AM$5)=YEAR(Projects!$C$2)))+L14) | N14: =IF(B14="","",IF(OR(D14="",E14="",G14=""),"Missing start / duration / contract",IF(OR(E14<1,E14>24),"Duration must be 1–24",IF(I14<0,"WIP exceeds contract",IF(AND(J14=0,I14<>0),"Budget not phased: no remaining months",IF(AND(J14>0,Phasing!G14=0,I14<>0),"Budget not phased: remaining weights are 0",IF(OR(D14<Projects!$C$3,F14>EDATE(Projects!$C$3,35)),"Partly outside timeline",IF(Phasing!H14=0,"OK","Weights entered beyond duration (ignored)"))))))))
A15: 10 | F15: =IF(OR(D15="",E15=""),"",EDATE(D15,E15-1)) | H15: =IF(B15="","",'WIP Log'!C15) | I15: =IF(B15="","",N(G15)-N(H15)) | J15: =IF(OR(B15="",E15=""),"",MAX(0,E15-Phasing!F15+1)) | K15: =IF(B15="","",IF(AND(((YEAR(Projects!$C$2)-YEAR(Projects!$C$3))*12+MONTH(Projects!$C$2)-MONTH(Projects!$C$3)+1)+1>=1,((YEAR(Projects!$C$2)-YEAR(Projects!$C$3))*12+MONTH(Projects!$C$2)-MONTH(Projects!$C$3)+1)+1<=36),INDEX('Phased Budget'!$H15:$AQ15,((YEAR(Projects!$C$2)-YEAR(Projects!$C$3))*12+MONTH(Projects!$C$2)-MONTH(Projects!$C$3)+1)+1),0)) | L15: =IF(B15="","",SUMPRODUCT('Phased Budget'!$H15:$AQ15*(YEAR('Phased Budget'!$H$5:$AQ$5)=YEAR(Projects!$C$2)))) | M15: =IF(B15="","",SUMPRODUCT('WIP Log'!$D15:$AM15*('WIP Log'!$D$5:$AM$5<=Projects!$C$2)*(YEAR('WIP Log'!$D$5:$AM$5)=YEAR(Projects!$C$2)))+L15) | N15: =IF(B15="","",IF(OR(D15="",E15="",G15=""),"Missing start / duration / contract",IF(OR(E15<1,E15>24),"Duration must be 1–24",IF(I15<0,"WIP exceeds contract",IF(AND(J15=0,I15<>0),"Budget not phased: no remaining months",IF(AND(J15>0,Phasing!G15=0,I15<>0),"Budget not phased: remaining weights are 0",IF(OR(D15<Projects!$C$3,F15>EDATE(Projects!$C$3,35)),"Partly outside timeline",IF(Phasing!H15=0,"OK","Weights entered beyond duration (ignored)"))))))))
A16: 11 | F16: =IF(OR(D16="",E16=""),"",EDATE(D16,E16-1)) | H16: =IF(B16="","",'WIP Log'!C16) | I16: =IF(B16="","",N(G16)-N(H16)) | J16: =IF(OR(B16="",E16=""),"",MAX(0,E16-Phasing!F16+1)) | K16: =IF(B16="","",IF(AND(((YEAR(Projects!$C$2)-YEAR(Projects!$C$3))*12+MONTH(Projects!$C$2)-MONTH(Projects!$C$3)+1)+1>=1,((YEAR(Projects!$C$2)-YEAR(Projects!$C$3))*12+MONTH(Projects!$C$2)-MONTH(Projects!$C$3)+1)+1<=36),INDEX('Phased Budget'!$H16:$AQ16,((YEAR(Projects!$C$2)-YEAR(Projects!$C$3))*12+MONTH(Projects!$C$2)-MONTH(Projects!$C$3)+1)+1),0)) | L16: =IF(B16="","",SUMPRODUCT('Phased Budget'!$H16:$AQ16*(YEAR('Phased Budget'!$H$5:$AQ$5)=YEAR(Projects!$C$2)))) | M16: =IF(B16="","",SUMPRODUCT('WIP Log'!$D16:$AM16*('WIP Log'!$D$5:$AM$5<=Projects!$C$2)*(YEAR('WIP Log'!$D$5:$AM$5)=YEAR(Projects!$C$2)))+L16) | N16: =IF(B16="","",IF(OR(D16="",E16="",G16=""),"Missing start / duration / contract",IF(OR(E16<1,E16>24),"Duration must be 1–24",IF(I16<0,"WIP exceeds contract",IF(AND(J16=0,I16<>0),"Budget not phased: no remaining months",IF(AND(J16>0,Phasing!G16=0,I16<>0),"Budget not phased: remaining weights are 0",IF(OR(D16<Projects!$C$3,F16>EDATE(Projects!$C$3,35)),"Partly outside timeline",IF(Phasing!H16=0,"OK","Weights entered beyond duration (ignored)"))))))))
A17: 12 | F17: =IF(OR(D17="",E17=""),"",EDATE(D17,E17-1)) | H17: =IF(B17="","",'WIP Log'!C17) | I17: =IF(B17="","",N(G17)-N(H17)) | J17: =IF(OR(B17="",E17=""),"",MAX(0,E17-Phasing!F17+1)) | K17: =IF(B17="","",IF(AND(((YEAR(Projects!$C$2)-YEAR(Projects!$C$3))*12+MONTH(Projects!$C$2)-MONTH(Projects!$C$3)+1)+1>=1,((YEAR(Projects!$C$2)-YEAR(Projects!$C$3))*12+MONTH(Projects!$C$2)-MONTH(Projects!$C$3)+1)+1<=36),INDEX('Phased Budget'!$H17:$AQ17,((YEAR(Projects!$C$2)-YEAR(Projects!$C$3))*12+MONTH(Projects!$C$2)-MONTH(Projects!$C$3)+1)+1),0)) | L17: =IF(B17="","",SUMPRODUCT('Phased Budget'!$H17:$AQ17*(YEAR('Phased Budget'!$H$5:$AQ$5)=YEAR(Projects!$C$2)))) | M17: =IF(B17="","",SUMPRODUCT('WIP Log'!$D17:$AM17*('WIP Log'!$D$5:$AM$5<=Projects!$C$2)*(YEAR('WIP Log'!$D$5:$AM$5)=YEAR(Projects!$C$2)))+L17) | N17: =IF(B17="","",IF(OR(D17="",E17="",G17=""),"Missing start / duration / contract",IF(OR(E17<1,E17>24),"Duration must be 1–24",IF(I17<0,"WIP exceeds contract",IF(AND(J17=0,I17<>0),"Budget not phased: no remaining months",IF(AND(J17>0,Phasing!G17=0,I17<>0),"Budget not phased: remaining weights are 0",IF(OR(D17<Projects!$C$3,F17>EDATE(Projects!$C$3,35)),"Partly outside timeline",IF(Phasing!H17=0,"OK","Weights entered beyond duration (ignored)"))))))))
A18: 13 | F18: =IF(OR(D18="",E18=""),"",EDATE(D18,E18-1)) | H18: =IF(B18="","",'WIP Log'!C18) | I18: =IF(B18="","",N(G18)-N(H18)) | J18: =IF(OR(B18="",E18=""),"",MAX(0,E18-Phasing!F18+1)) | K18: =IF(B18="","",IF(AND(((YEAR(Projects!$C$2)-YEAR(Projects!$C$3))*12+MONTH(Projects!$C$2)-MONTH(Projects!$C$3)+1)+1>=1,((YEAR(Projects!$C$2)-YEAR(Projects!$C$3))*12+MONTH(Projects!$C$2)-MONTH(Projects!$C$3)+1)+1<=36),INDEX('Phased Budget'!$H18:$AQ18,((YEAR(Projects!$C$2)-YEAR(Projects!$C$3))*12+MONTH(Projects!$C$2)-MONTH(Projects!$C$3)+1)+1),0)) | L18: =IF(B18="","",SUMPRODUCT('Phased Budget'!$H18:$AQ18*(YEAR('Phased Budget'!$H$5:$AQ$5)=YEAR(Projects!$C$2)))) | M18: =IF(B18="","",SUMPRODUCT('WIP Log'!$D18:$AM18*('WIP Log'!$D$5:$AM$5<=Projects!$C$2)*(YEAR('WIP Log'!$D$5:$AM$5)=YEAR(Projects!$C$2)))+L18) | N18: =IF(B18="","",IF(OR(D18="",E18="",G18=""),"Missing start / duration / contract",IF(OR(E18<1,E18>24),"Duration must be 1–24",IF(I18<0,"WIP exceeds contract",IF(AND(J18=0,I18<>0),"Budget not phased: no remaining months",IF(AND(J18>0,Phasing!G18=0,I18<>0),"Budget not phased: remaining weights are 0",IF(OR(D18<Projects!$C$3,F18>EDATE(Projects!$C$3,35)),"Partly outside timeline",IF(Phasing!H18=0,"OK","Weights entered beyond duration (ignored)"))))))))
... A55: 50 | F55: =IF(OR(D55="",E55=""),"",EDATE(D55,E55-1)) | H55: =IF(B55="","",'WIP Log'!C55) | I55: =IF(B55="","",N(G55)-N(H55)) | J55: =IF(OR(B55="",E55=""),"",MAX(0,E55-Phasing!F55+1)) | K55: =IF(B55="","",IF(AND(((YEAR(Projects!$C$2)-YEAR(Projects!$C$3))*12+MONTH(Projects!$C$2)-MONTH(Projects!$C$3)+1)+1>=1,((YEAR(Projects!$C$2)-YEAR(Projects!$C$3))*12+MONTH(Projects!$C$2)-MONTH(Projects!$C$3)+1)+1<=36),INDEX('Phased Budget'!$H55:$AQ55,((YEAR(Projects!$C$2)-YEAR(Projects!$C$3))*12+MONTH(Projects!$C$2)-MONTH(Projects!$C$3)+1)+1),0)) | L55: =IF(B55="","",SUMPRODUCT('Phased Budget'!$H55:$AQ55*(YEAR('Phased Budget'!$H$5:$AQ$5)=YEAR(Projects!$C$2)))) | M55: =IF(B55="","",SUMPRODUCT('WIP Log'!$D55:$AM55*('WIP Log'!$D$5:$AM$5<=Projects!$C$2)*(YEAR('WIP Log'!$D$5:$AM$5)=YEAR(Projects!$C$2)))+L55) | N55: =IF(B55="","",IF(OR(D55="",E55="",G55=""),"Missing start / duration / contract",IF(OR(E55<1,E55>24),"Duration must be 1–24",IF(I55<0,"WIP exceeds contract",IF(AND(J55=0,I55<>0),"Budget not phased: no remaining months",IF(AND(J55>0,Phasing!G55=0,I55<>0),"Budget not phased: remaining weights are 0",IF(OR(D55<Projects!$C$3,F55>EDATE(Projects!$C$3,35)),"Partly outside timeline",IF(Phasing!H55=0,"OK","Weights entered beyond duration (ignored)"))))))))
B57: TOTAL | G57: =SUM(G6:G55) -> 10000 | H57: =SUM(H6:H55) -> 1000 | I57: =SUM(I6:I55) -> 9000 | K57: =SUM(K6:K55) -> 2250 | L57: =SUM(L6:L55) -> 4500 | M57: =SUM(M6:M55) -> 5500 | N57: =COUNTIFS(N6:N55,"<>OK",B6:B55,"<>")&" project(s) need attention" -> 0 project(s) need attention

Sheet Phasing
A1: Phasing Weights
H2: month index | I2: 1 | J2: 2 | K2: 3 | L2: 4 | M2: 5 | N2: 6 | O2: 7 | P2: 8 | Q2: 9 | R2: 10 | S2: 11 | T2: 12 | U2: 13 | V2: 14 | W2: 15 | X2: 16 | Y2: 17 | Z2: 18 | AA2: 19 | AB2: 20 | AC2: 21 | AD2: 22 | AE2: 23 | AF2: 24 | AH2: 1 | AI2: 2 | AJ2: 3 | AK2: 4 | AL2: 5 | AM2: 6 | AN2: 7 | AO2: 8 | AP2: 9 | AQ2: 10 | AR2: 11 | AS2: 12 | AT2: 13 | AU2: 14 | AV2: 15 | AW2: 16 | AX2: 17 | AY2: 18 | AZ2: 19 | BA2: 20 | BB2: 21 | BC2: 22 | BD2: 23 | BE2: 24
A3: Enter raw weights in the yellow cells (month 1 = Starting Month). They are renormalised to 1.0 automatically. Leave a row blank for equal weights.
I4: RAW WEIGHTS (input) → | AH4: NORMALISED WEIGHTS, FULL DURATION (Σ = 1.0) →
A5: # | B5: Project Name | C5: Duration | D5: Weights entered | E5: Σ weights (full duration) | F5: First remaining month # | G5: Σ weights (remaining months) | H5: Non-zero weights beyond duration | I5: M1 | J5: M2 | K5: M3 | L5: M4 | M5: M5 | N5: M6 | O5: M7 | P5: M8 | Q5: M9 | R5: M10 | S5: M11 | T5: M12 | U5: M13 | V5: M14 | W5: M15 | X5: M16 | Y5: M17 | Z5: M18 | AA5: M19 | AB5: M20 | AC5: M21 | AD5: M22 | AE5: M23 | AF5: M24 | AH5: M1 | AI5: M2 | AJ5: M3 | AK5: M4 | AL5: M5 | AM5: M6 | AN5: M7 | AO5: M8 | AP5: M9 | AQ5: M10 | AR5: M11 | AS5: M12 | AT5: M13 | AU5: M14 | AV5: M15 | AW5: M16 | AX5: M17 | AY5: M18 | AZ5: M19 | BA5: M20 | BB5: M21 | BC5: M22 | BD5: M23 | BE5: M24 | BF5: Check Σ
A6: 1 | B6: =IF(Projects!B6="","",Projects!B6) -> Example Project (slide) | C6: =IF(Projects!E6="","",Projects!E6) -> 5 | D6: =COUNT($I6:$AF6) -> 5 | E6: =IF(C6="",0,IF(D6=0,C6,SUMPRODUCT($I6:$AF6*($I$2:$AF$2<=C6)))) -> 9 | F6: =IF(OR(C6="",Projects!D6=""),1,MAX(1,((YEAR(Projects!$C$2)-YEAR(Projects!D6))*12+MONTH(Projects!$C$2)-MONTH(Projects!D6)+1)+1)) -> 2 | G6: =IF(C6="",0,IF(D6=0,MAX(0,C6-F6+1),SUMPRODUCT($I6:$AF6*($I$2:$AF$2>=F6)*($I$2:$AF$2<=C6)))) -> 8 | H6: =IF(C6="",0,SUMPRODUCT(($I6:$AF6<>0)*($I$2:$AF$2>C6))) -> 0 | I6: 1 | J6: 2 | K6: 2 | L6: 2 | M6: 2 | AH6: =IF(OR(C6="",AH$2>C6,E6=0),"",IF(D6=0,1/C6,N(I6)/E6)) -> 0.11111111 | AI6: =IF(OR(C6="",AI$2>C6,E6=0),"",IF(D6=0,1/C6,N(J6)/E6)) -> 0.22222222 | AJ6: =IF(OR(C6="",AJ$2>C6,E6=0),"",IF(D6=0,1/C6,N(K6)/E6)) -> 0.22222222 | AK6: =IF(OR(C6="",AK$2>C6,E6=0),"",IF(D6=0,1/C6,N(L6)/E6)) -> 0.22222222 | AL6: =IF(OR(C6="",AL$2>C6,E6=0),"",IF(D6=0,1/C6,N(M6)/E6)) -> 0.22222222 | AM6: =IF(OR(C6="",AM$2>C6,E6=0),"",IF(D6=0,1/C6,N(N6)/E6)) | AN6: =IF(OR(C6="",AN$2>C6,E6=0),"",IF(D6=0,1/C6,N(O6)/E6)) | AO6: =IF(OR(C6="",AO$2>C6,E6=0),"",IF(D6=0,1/C6,N(P6)/E6)) | AP6: =IF(OR(C6="",AP$2>C6,E6=0),"",IF(D6=0,1/C6,N(Q6)/E6)) | AQ6: =IF(OR(C6="",AQ$2>C6,E6=0),"",IF(D6=0,1/C6,N(R6)/E6)) | AR6: =IF(OR(C6="",AR$2>C6,E6=0),"",IF(D6=0,1/C6,N(S6)/E6)) | AS6: =IF(OR(C6="",AS$2>C6,E6=0),"",IF(D6=0,1/C6,N(T6)/E6)) | AT6: =IF(OR(C6="",AT$2>C6,E6=0),"",IF(D6=0,1/C6,N(U6)/E6)) | AU6: =IF(OR(C6="",AU$2>C6,E6=0),"",IF(D6=0,1/C6,N(V6)/E6)) | AV6: =IF(OR(C6="",AV$2>C6,E6=0),"",IF(D6=0,1/C6,N(W6)/E6)) | AW6: =IF(OR(C6="",AW$2>C6,E6=0),"",IF(D6=0,1/C6,N(X6)/E6)) | AX6: =IF(OR(C6="",AX$2>C6,E6=0),"",IF(D6=0,1/C6,N(Y6)/E6)) | AY6: =IF(OR(C6="",AY$2>C6,E6=0),"",IF(D6=0,1/C6,N(Z6)/E6)) | AZ6: =IF(OR(C6="",AZ$2>C6,E6=0),"",IF(D6=0,1/C6,N(AA6)/E6)) | BA6: =IF(OR(C6="",BA$2>C6,E6=0),"",IF(D6=0,1/C6,N(AB6)/E6)) | BB6: =IF(OR(C6="",BB$2>C6,E6=0),"",IF(D6=0,1/C6,N(AC6)/E6)) | BC6: =IF(OR(C6="",BC$2>C6,E6=0),"",IF(D6=0,1/C6,N(AD6)/E6)) | BD6: =IF(OR(C6="",BD$2>C6,E6=0),"",IF(D6=0,1/C6,N(AE6)/E6)) | BE6: =IF(OR(C6="",BE$2>C6,E6=0),"",IF(D6=0,1/C6,N(AF6)/E6)) | BF6: =IF(C6="","",SUM(AH6:BE6)) -> 1
A7: 2 | B7: =IF(Projects!B7="","",Projects!B7) | C7: =IF(Projects!E7="","",Projects!E7) | D7: =COUNT($I7:$AF7) -> 0 | E7: =IF(C7="",0,IF(D7=0,C7,SUMPRODUCT($I7:$AF7*($I$2:$AF$2<=C7)))) -> 0 | F7: =IF(OR(C7="",Projects!D7=""),1,MAX(1,((YEAR(Projects!$C$2)-YEAR(Projects!D7))*12+MONTH(Projects!$C$2)-MONTH(Projects!D7)+1)+1)) -> 1 | G7: =IF(C7="",0,IF(D7=0,MAX(0,C7-F7+1),SUMPRODUCT($I7:$AF7*($I$2:$AF$2>=F7)*($I$2:$AF$2<=C7)))) -> 0 | H7: =IF(C7="",0,SUMPRODUCT(($I7:$AF7<>0)*($I$2:$AF$2>C7))) -> 0 | AH7: =IF(OR(C7="",AH$2>C7,E7=0),"",IF(D7=0,1/C7,N(I7)/E7)) | AI7: =IF(OR(C7="",AI$2>C7,E7=0),"",IF(D7=0,1/C7,N(J7)/E7)) | AJ7: =IF(OR(C7="",AJ$2>C7,E7=0),"",IF(D7=0,1/C7,N(K7)/E7)) | AK7: =IF(OR(C7="",AK$2>C7,E7=0),"",IF(D7=0,1/C7,N(L7)/E7)) | AL7: =IF(OR(C7="",AL$2>C7,E7=0),"",IF(D7=0,1/C7,N(M7)/E7)) | AM7: =IF(OR(C7="",AM$2>C7,E7=0),"",IF(D7=0,1/C7,N(N7)/E7)) | AN7: =IF(OR(C7="",AN$2>C7,E7=0),"",IF(D7=0,1/C7,N(O7)/E7)) | AO7: =IF(OR(C7="",AO$2>C7,E7=0),"",IF(D7=0,1/C7,N(P7)/E7)) | AP7: =IF(OR(C7="",AP$2>C7,E7=0),"",IF(D7=0,1/C7,N(Q7)/E7)) | AQ7: =IF(OR(C7="",AQ$2>C7,E7=0),"",IF(D7=0,1/C7,N(R7)/E7)) | AR7: =IF(OR(C7="",AR$2>C7,E7=0),"",IF(D7=0,1/C7,N(S7)/E7)) | AS7: =IF(OR(C7="",AS$2>C7,E7=0),"",IF(D7=0,1/C7,N(T7)/E7)) | AT7: =IF(OR(C7="",AT$2>C7,E7=0),"",IF(D7=0,1/C7,N(U7)/E7)) | AU7: =IF(OR(C7="",AU$2>C7,E7=0),"",IF(D7=0,1/C7,N(V7)/E7)) | AV7: =IF(OR(C7="",AV$2>C7,E7=0),"",IF(D7=0,1/C7,N(W7)/E7)) | AW7: =IF(OR(C7="",AW$2>C7,E7=0),"",IF(D7=0,1/C7,N(X7)/E7)) | AX7: =IF(OR(C7="",AX$2>C7,E7=0),"",IF(D7=0,1/C7,N(Y7)/E7)) | AY7: =IF(OR(C7="",AY$2>C7,E7=0),"",IF(D7=0,1/C7,N(Z7)/E7)) | AZ7: =IF(OR(C7="",AZ$2>C7,E7=0),"",IF(D7=0,1/C7,N(AA7)/E7)) | BA7: =IF(OR(C7="",BA$2>C7,E7=0),"",IF(D7=0,1/C7,N(AB7)/E7)) | BB7: =IF(OR(C7="",BB$2>C7,E7=0),"",IF(D7=0,1/C7,N(AC7)/E7)) | BC7: =IF(OR(C7="",BC$2>C7,E7=0),"",IF(D7=0,1/C7,N(AD7)/E7)) | BD7: =IF(OR(C7="",BD$2>C7,E7=0),"",IF(D7=0,1/C7,N(AE7)/E7)) | BE7: =IF(OR(C7="",BE$2>C7,E7=0),"",IF(D7=0,1/C7,N(AF7)/E7)) | BF7: =IF(C7="","",SUM(AH7:BE7))
A8: 3 | B8: =IF(Projects!B8="","",Projects!B8) | C8: =IF(Projects!E8="","",Projects!E8) | D8: =COUNT($I8:$AF8) -> 0 | E8: =IF(C8="",0,IF(D8=0,C8,SUMPRODUCT($I8:$AF8*($I$2:$AF$2<=C8)))) -> 0 | F8: =IF(OR(C8="",Projects!D8=""),1,MAX(1,((YEAR(Projects!$C$2)-YEAR(Projects!D8))*12+MONTH(Projects!$C$2)-MONTH(Projects!D8)+1)+1)) -> 1 | G8: =IF(C8="",0,IF(D8=0,MAX(0,C8-F8+1),SUMPRODUCT($I8:$AF8*($I$2:$AF$2>=F8)*($I$2:$AF$2<=C8)))) -> 0 | H8: =IF(C8="",0,SUMPRODUCT(($I8:$AF8<>0)*($I$2:$AF$2>C8))) -> 0 | AH8: =IF(OR(C8="",AH$2>C8,E8=0),"",IF(D8=0,1/C8,N(I8)/E8)) | AI8: =IF(OR(C8="",AI$2>C8,E8=0),"",IF(D8=0,1/C8,N(J8)/E8)) | AJ8: =IF(OR(C8="",AJ$2>C8,E8=0),"",IF(D8=0,1/C8,N(K8)/E8)) | AK8: =IF(OR(C8="",AK$2>C8,E8=0),"",IF(D8=0,1/C8,N(L8)/E8)) | AL8: =IF(OR(C8="",AL$2>C8,E8=0),"",IF(D8=0,1/C8,N(M8)/E8)) | AM8: =IF(OR(C8="",AM$2>C8,E8=0),"",IF(D8=0,1/C8,N(N8)/E8)) | AN8: =IF(OR(C8="",AN$2>C8,E8=0),"",IF(D8=0,1/C8,N(O8)/E8)) | AO8: =IF(OR(C8="",AO$2>C8,E8=0),"",IF(D8=0,1/C8,N(P8)/E8)) | AP8: =IF(OR(C8="",AP$2>C8,E8=0),"",IF(D8=0,1/C8,N(Q8)/E8)) | AQ8: =IF(OR(C8="",AQ$2>C8,E8=0),"",IF(D8=0,1/C8,N(R8)/E8)) | AR8: =IF(OR(C8="",AR$2>C8,E8=0),"",IF(D8=0,1/C8,N(S8)/E8)) | AS8: =IF(OR(C8="",AS$2>C8,E8=0),"",IF(D8=0,1/C8,N(T8)/E8)) | AT8: =IF(OR(C8="",AT$2>C8,E8=0),"",IF(D8=0,1/C8,N(U8)/E8)) | AU8: =IF(OR(C8="",AU$2>C8,E8=0),"",IF(D8=0,1/C8,N(V8)/E8)) | AV8: =IF(OR(C8="",AV$2>C8,E8=0),"",IF(D8=0,1/C8,N(W8)/E8)) | AW8: =IF(OR(C8="",AW$2>C8,E8=0),"",IF(D8=0,1/C8,N(X8)/E8)) | AX8: =IF(OR(C8="",AX$2>C8,E8=0),"",IF(D8=0,1/C8,N(Y8)/E8)) | AY8: =IF(OR(C8="",AY$2>C8,E8=0),"",IF(D8=0,1/C8,N(Z8)/E8)) | AZ8: =IF(OR(C8="",AZ$2>C8,E8=0),"",IF(D8=0,1/C8,N(AA8)/E8)) | BA8: =IF(OR(C8="",BA$2>C8,E8=0),"",IF(D8=0,1/C8,N(AB8)/E8)) | BB8: =IF(OR(C8="",BB$2>C8,E8=0),"",IF(D8=0,1/C8,N(AC8)/E8)) | BC8: =IF(OR(C8="",BC$2>C8,E8=0),"",IF(D8=0,1/C8,N(AD8)/E8)) | BD8: =IF(OR(C8="",BD$2>C8,E8=0),"",IF(D8=0,1/C8,N(AE8)/E8)) | BE8: =IF(OR(C8="",BE$2>C8,E8=0),"",IF(D8=0,1/C8,N(AF8)/E8)) | BF8: =IF(C8="","",SUM(AH8:BE8))
A9: 4 | B9: =IF(Projects!B9="","",Projects!B9) | C9: =IF(Projects!E9="","",Projects!E9) | D9: =COUNT($I9:$AF9) -> 0 | E9: =IF(C9="",0,IF(D9=0,C9,SUMPRODUCT($I9:$AF9*($I$2:$AF$2<=C9)))) -> 0 | F9: =IF(OR(C9="",Projects!D9=""),1,MAX(1,((YEAR(Projects!$C$2)-YEAR(Projects!D9))*12+MONTH(Projects!$C$2)-MONTH(Projects!D9)+1)+1)) -> 1 | G9: =IF(C9="",0,IF(D9=0,MAX(0,C9-F9+1),SUMPRODUCT($I9:$AF9*($I$2:$AF$2>=F9)*($I$2:$AF$2<=C9)))) -> 0 | H9: =IF(C9="",0,SUMPRODUCT(($I9:$AF9<>0)*($I$2:$AF$2>C9))) -> 0 | AH9: =IF(OR(C9="",AH$2>C9,E9=0),"",IF(D9=0,1/C9,N(I9)/E9)) | AI9: =IF(OR(C9="",AI$2>C9,E9=0),"",IF(D9=0,1/C9,N(J9)/E9)) | AJ9: =IF(OR(C9="",AJ$2>C9,E9=0),"",IF(D9=0,1/C9,N(K9)/E9)) | AK9: =IF(OR(C9="",AK$2>C9,E9=0),"",IF(D9=0,1/C9,N(L9)/E9)) | AL9: =IF(OR(C9="",AL$2>C9,E9=0),"",IF(D9=0,1/C9,N(M9)/E9)) | AM9: =IF(OR(C9="",AM$2>C9,E9=0),"",IF(D9=0,1/C9,N(N9)/E9)) | AN9: =IF(OR(C9="",AN$2>C9,E9=0),"",IF(D9=0,1/C9,N(O9)/E9)) | AO9: =IF(OR(C9="",AO$2>C9,E9=0),"",IF(D9=0,1/C9,N(P9)/E9)) | AP9: =IF(OR(C9="",AP$2>C9,E9=0),"",IF(D9=0,1/C9,N(Q9)/E9)) | AQ9: =IF(OR(C9="",AQ$2>C9,E9=0),"",IF(D9=0,1/C9,N(R9)/E9)) | AR9: =IF(OR(C9="",AR$2>C9,E9=0),"",IF(D9=0,1/C9,N(S9)/E9)) | AS9: =IF(OR(C9="",AS$2>C9,E9=0),"",IF(D9=0,1/C9,N(T9)/E9)) | AT9: =IF(OR(C9="",AT$2>C9,E9=0),"",IF(D9=0,1/C9,N(U9)/E9)) | AU9: =IF(OR(C9="",AU$2>C9,E9=0),"",IF(D9=0,1/C9,N(V9)/E9)) | AV9: =IF(OR(C9="",AV$2>C9,E9=0),"",IF(D9=0,1/C9,N(W9)/E9)) | AW9: =IF(OR(C9="",AW$2>C9,E9=0),"",IF(D9=0,1/C9,N(X9)/E9)) | AX9: =IF(OR(C9="",AX$2>C9,E9=0),"",IF(D9=0,1/C9,N(Y9)/E9)) | AY9: =IF(OR(C9="",AY$2>C9,E9=0),"",IF(D9=0,1/C9,N(Z9)/E9)) | AZ9: =IF(OR(C9="",AZ$2>C9,E9=0),"",IF(D9=0,1/C9,N(AA9)/E9)) | BA9: =IF(OR(C9="",BA$2>C9,E9=0),"",IF(D9=0,1/C9,N(AB9)/E9)) | BB9: =IF(OR(C9="",BB$2>C9,E9=0),"",IF(D9=0,1/C9,N(AC9)/E9)) | BC9: =IF(OR(C9="",BC$2>C9,E9=0),"",IF(D9=0,1/C9,N(AD9)/E9)) | BD9: =IF(OR(C9="",BD$2>C9,E9=0),"",IF(D9=0,1/C9,N(AE9)/E9)) | BE9: =IF(OR(C9="",BE$2>C9,E9=0),"",IF(D9=0,1/C9,N(AF9)/E9)) | BF9: =IF(C9="","",SUM(AH9:BE9))
A10: 5 | B10: =IF(Projects!B10="","",Projects!B10) | C10: =IF(Projects!E10="","",Projects!E10) | D10: =COUNT($I10:$AF10) -> 0 | E10: =IF(C10="",0,IF(D10=0,C10,SUMPRODUCT($I10:$AF10*($I$2:$AF$2<=C10)))) -> 0 | F10: =IF(OR(C10="",Projects!D10=""),1,MAX(1,((YEAR(Projects!$C$2)-YEAR(Projects!D10))*12+MONTH(Projects!$C$2)-MONTH(Projects!D10)+1)+1)) -> 1 | G10: =IF(C10="",0,IF(D10=0,MAX(0,C10-F10+1),SUMPRODUCT($I10:$AF10*($I$2:$AF$2>=F10)*($I$2:$AF$2<=C10)))) -> 0 | H10: =IF(C10="",0,SUMPRODUCT(($I10:$AF10<>0)*($I$2:$AF$2>C10))) -> 0 | AH10: =IF(OR(C10="",AH$2>C10,E10=0),"",IF(D10=0,1/C10,N(I10)/E10)) | AI10: =IF(OR(C10="",AI$2>C10,E10=0),"",IF(D10=0,1/C10,N(J10)/E10)) | AJ10: =IF(OR(C10="",AJ$2>C10,E10=0),"",IF(D10=0,1/C10,N(K10)/E10)) | AK10: =IF(OR(C10="",AK$2>C10,E10=0),"",IF(D10=0,1/C10,N(L10)/E10)) | AL10: =IF(OR(C10="",AL$2>C10,E10=0),"",IF(D10=0,1/C10,N(M10)/E10)) | AM10: =IF(OR(C10="",AM$2>C10,E10=0),"",IF(D10=0,1/C10,N(N10)/E10)) | AN10: =IF(OR(C10="",AN$2>C10,E10=0),"",IF(D10=0,1/C10,N(O10)/E10)) | AO10: =IF(OR(C10="",AO$2>C10,E10=0),"",IF(D10=0,1/C10,N(P10)/E10)) | AP10: =IF(OR(C10="",AP$2>C10,E10=0),"",IF(D10=0,1/C10,N(Q10)/E10)) | AQ10: =IF(OR(C10="",AQ$2>C10,E10=0),"",IF(D10=0,1/C10,N(R10)/E10)) | AR10: =IF(OR(C10="",AR$2>C10,E10=0),"",IF(D10=0,1/C10,N(S10)/E10)) | AS10: =IF(OR(C10="",AS$2>C10,E10=0),"",IF(D10=0,1/C10,N(T10)/E10)) | AT10: =IF(OR(C10="",AT$2>C10,E10=0),"",IF(D10=0,1/C10,N(U10)/E10)) | AU10: =IF(OR(C10="",AU$2>C10,E10=0),"",IF(D10=0,1/C10,N(V10)/E10)) | AV10: =IF(OR(C10="",AV$2>C10,E10=0),"",IF(D10=0,1/C10,N(W10)/E10)) | AW10: =IF(OR(C10="",AW$2>C10,E10=0),"",IF(D10=0,1/C10,N(X10)/E10)) | AX10: =IF(OR(C10="",AX$2>C10,E10=0),"",IF(D10=0,1/C10,N(Y10)/E10)) | AY10: =IF(OR(C10="",AY$2>C10,E10=0),"",IF(D10=0,1/C10,N(Z10)/E10)) | AZ10: =IF(OR(C10="",AZ$2>C10,E10=0),"",IF(D10=0,1/C10,N(AA10)/E10)) | BA10: =IF(OR(C10="",BA$2>C10,E10=0),"",IF(D10=0,1/C10,N(AB10)/E10)) | BB10: =IF(OR(C10="",BB$2>C10,E10=0),"",IF(D10=0,1/C10,N(AC10)/E10)) | BC10: =IF(OR(C10="",BC$2>C10,E10=0),"",IF(D10=0,1/C10,N(AD10)/E10)) | BD10: =IF(OR(C10="",BD$2>C10,E10=0),"",IF(D10=0,1/C10,N(AE10)/E10)) | BE10: =IF(OR(C10="",BE$2>C10,E10=0),"",IF(D10=0,1/C10,N(AF10)/E10)) | BF10: =IF(C10="","",SUM(AH10:BE10))
A11: 6 | B11: =IF(Projects!B11="","",Projects!B11) | C11: =IF(Projects!E11="","",Projects!E11) | D11: =COUNT($I11:$AF11) -> 0 | E11: =IF(C11="",0,IF(D11=0,C11,SUMPRODUCT($I11:$AF11*($I$2:$AF$2<=C11)))) -> 0 | F11: =IF(OR(C11="",Projects!D11=""),1,MAX(1,((YEAR(Projects!$C$2)-YEAR(Projects!D11))*12+MONTH(Projects!$C$2)-MONTH(Projects!D11)+1)+1)) -> 1 | G11: =IF(C11="",0,IF(D11=0,MAX(0,C11-F11+1),SUMPRODUCT($I11:$AF11*($I$2:$AF$2>=F11)*($I$2:$AF$2<=C11)))) -> 0 | H11: =IF(C11="",0,SUMPRODUCT(($I11:$AF11<>0)*($I$2:$AF$2>C11))) -> 0 | AH11: =IF(OR(C11="",AH$2>C11,E11=0),"",IF(D11=0,1/C11,N(I11)/E11)) | AI11: =IF(OR(C11="",AI$2>C11,E11=0),"",IF(D11=0,1/C11,N(J11)/E11)) | AJ11: =IF(OR(C11="",AJ$2>C11,E11=0),"",IF(D11=0,1/C11,N(K11)/E11)) | AK11: =IF(OR(C11="",AK$2>C11,E11=0),"",IF(D11=0,1/C11,N(L11)/E11)) | AL11: =IF(OR(C11="",AL$2>C11,E11=0),"",IF(D11=0,1/C11,N(M11)/E11)) | AM11: =IF(OR(C11="",AM$2>C11,E11=0),"",IF(D11=0,1/C11,N(N11)/E11)) | AN11: =IF(OR(C11="",AN$2>C11,E11=0),"",IF(D11=0,1/C11,N(O11)/E11)) | AO11: =IF(OR(C11="",AO$2>C11,E11=0),"",IF(D11=0,1/C11,N(P11)/E11)) | AP11: =IF(OR(C11="",AP$2>C11,E11=0),"",IF(D11=0,1/C11,N(Q11)/E11)) | AQ11: =IF(OR(C11="",AQ$2>C11,E11=0),"",IF(D11=0,1/C11,N(R11)/E11)) | AR11: =IF(OR(C11="",AR$2>C11,E11=0),"",IF(D11=0,1/C11,N(S11)/E11)) | AS11: =IF(OR(C11="",AS$2>C11,E11=0),"",IF(D11=0,1/C11,N(T11)/E11)) | AT11: =IF(OR(C11="",AT$2>C11,E11=0),"",IF(D11=0,1/C11,N(U11)/E11)) | AU11: =IF(OR(C11="",AU$2>C11,E11=0),"",IF(D11=0,1/C11,N(V11)/E11)) | AV11: =IF(OR(C11="",AV$2>C11,E11=0),"",IF(D11=0,1/C11,N(W11)/E11)) | AW11: =IF(OR(C11="",AW$2>C11,E11=0),"",IF(D11=0,1/C11,N(X11)/E11)) | AX11: =IF(OR(C11="",AX$2>C11,E11=0),"",IF(D11=0,1/C11,N(Y11)/E11)) | AY11: =IF(OR(C11="",AY$2>C11,E11=0),"",IF(D11=0,1/C11,N(Z11)/E11)) | AZ11: =IF(OR(C11="",AZ$2>C11,E11=0),"",IF(D11=0,1/C11,N(AA11)/E11)) | BA11: =IF(OR(C11="",BA$2>C11,E11=0),"",IF(D11=0,1/C11,N(AB11)/E11)) | BB11: =IF(OR(C11="",BB$2>C11,E11=0),"",IF(D11=0,1/C11,N(AC11)/E11)) | BC11: =IF(OR(C11="",BC$2>C11,E11=0),"",IF(D11=0,1/C11,N(AD11)/E11)) | BD11: =IF(OR(C11="",BD$2>C11,E11=0),"",IF(D11=0,1/C11,N(AE11)/E11)) | BE11: =IF(OR(C11="",BE$2>C11,E11=0),"",IF(D11=0,1/C11,N(AF11)/E11)) | BF11: =IF(C11="","",SUM(AH11:BE11))
A12: 7 | B12: =IF(Projects!B12="","",Projects!B12) | C12: =IF(Projects!E12="","",Projects!E12) | D12: =COUNT($I12:$AF12) -> 0 | E12: =IF(C12="",0,IF(D12=0,C12,SUMPRODUCT($I12:$AF12*($I$2:$AF$2<=C12)))) -> 0 | F12: =IF(OR(C12="",Projects!D12=""),1,MAX(1,((YEAR(Projects!$C$2)-YEAR(Projects!D12))*12+MONTH(Projects!$C$2)-MONTH(Projects!D12)+1)+1)) -> 1 | G12: =IF(C12="",0,IF(D12=0,MAX(0,C12-F12+1),SUMPRODUCT($I12:$AF12*($I$2:$AF$2>=F12)*($I$2:$AF$2<=C12)))) -> 0 | H12: =IF(C12="",0,SUMPRODUCT(($I12:$AF12<>0)*($I$2:$AF$2>C12))) -> 0 | AH12: =IF(OR(C12="",AH$2>C12,E12=0),"",IF(D12=0,1/C12,N(I12)/E12)) | AI12: =IF(OR(C12="",AI$2>C12,E12=0),"",IF(D12=0,1/C12,N(J12)/E12)) | AJ12: =IF(OR(C12="",AJ$2>C12,E12=0),"",IF(D12=0,1/C12,N(K12)/E12)) | AK12: =IF(OR(C12="",AK$2>C12,E12=0),"",IF(D12=0,1/C12,N(L12)/E12)) | AL12: =IF(OR(C12="",AL$2>C12,E12=0),"",IF(D12=0,1/C12,N(M12)/E12)) | AM12: =IF(OR(C12="",AM$2>C12,E12=0),"",IF(D12=0,1/C12,N(N12)/E12)) | AN12: =IF(OR(C12="",AN$2>C12,E12=0),"",IF(D12=0,1/C12,N(O12)/E12)) | AO12: =IF(OR(C12="",AO$2>C12,E12=0),"",IF(D12=0,1/C12,N(P12)/E12)) | AP12: =IF(OR(C12="",AP$2>C12,E12=0),"",IF(D12=0,1/C12,N(Q12)/E12)) | AQ12: =IF(OR(C12="",AQ$2>C12,E12=0),"",IF(D12=0,1/C12,N(R12)/E12)) | AR12: =IF(OR(C12="",AR$2>C12,E12=0),"",IF(D12=0,1/C12,N(S12)/E12)) | AS12: =IF(OR(C12="",AS$2>C12,E12=0),"",IF(D12=0,1/C12,N(T12)/E12)) | AT12: =IF(OR(C12="",AT$2>C12,E12=0),"",IF(D12=0,1/C12,N(U12)/E12)) | AU12: =IF(OR(C12="",AU$2>C12,E12=0),"",IF(D12=0,1/C12,N(V12)/E12)) | AV12: =IF(OR(C12="",AV$2>C12,E12=0),"",IF(D12=0,1/C12,N(W12)/E12)) | AW12: =IF(OR(C12="",AW$2>C12,E12=0),"",IF(D12=0,1/C12,N(X12)/E12)) | AX12: =IF(OR(C12="",AX$2>C12,E12=0),"",IF(D12=0,1/C12,N(Y12)/E12)) | AY12: =IF(OR(C12="",AY$2>C12,E12=0),"",IF(D12=0,1/C12,N(Z12)/E12)) | AZ12: =IF(OR(C12="",AZ$2>C12,E12=0),"",IF(D12=0,1/C12,N(AA12)/E12)) | BA12: =IF(OR(C12="",BA$2>C12,E12=0),"",IF(D12=0,1/C12,N(AB12)/E12)) | BB12: =IF(OR(C12="",BB$2>C12,E12=0),"",IF(D12=0,1/C12,N(AC12)/E12)) | BC12: =IF(OR(C12="",BC$2>C12,E12=0),"",IF(D12=0,1/C12,N(AD12)/E12)) | BD12: =IF(OR(C12="",BD$2>C12,E12=0),"",IF(D12=0,1/C12,N(AE12)/E12)) | BE12: =IF(OR(C12="",BE$2>C12,E12=0),"",IF(D12=0,1/C12,N(AF12)/E12)) | BF12: =IF(C12="","",SUM(AH12:BE12))
A13: 8 | B13: =IF(Projects!B13="","",Projects!B13) | C13: =IF(Projects!E13="","",Projects!E13) | D13: =COUNT($I13:$AF13) -> 0 | E13: =IF(C13="",0,IF(D13=0,C13,SUMPRODUCT($I13:$AF13*($I$2:$AF$2<=C13)))) -> 0 | F13: =IF(OR(C13="",Projects!D13=""),1,MAX(1,((YEAR(Projects!$C$2)-YEAR(Projects!D13))*12+MONTH(Projects!$C$2)-MONTH(Projects!D13)+1)+1)) -> 1 | G13: =IF(C13="",0,IF(D13=0,MAX(0,C13-F13+1),SUMPRODUCT($I13:$AF13*($I$2:$AF$2>=F13)*($I$2:$AF$2<=C13)))) -> 0 | H13: =IF(C13="",0,SUMPRODUCT(($I13:$AF13<>0)*($I$2:$AF$2>C13))) -> 0 | AH13: =IF(OR(C13="",AH$2>C13,E13=0),"",IF(D13=0,1/C13,N(I13)/E13)) | AI13: =IF(OR(C13="",AI$2>C13,E13=0),"",IF(D13=0,1/C13,N(J13)/E13)) | AJ13: =IF(OR(C13="",AJ$2>C13,E13=0),"",IF(D13=0,1/C13,N(K13)/E13)) | AK13: =IF(OR(C13="",AK$2>C13,E13=0),"",IF(D13=0,1/C13,N(L13)/E13)) | AL13: =IF(OR(C13="",AL$2>C13,E13=0),"",IF(D13=0,1/C13,N(M13)/E13)) | AM13: =IF(OR(C13="",AM$2>C13,E13=0),"",IF(D13=0,1/C13,N(N13)/E13)) | AN13: =IF(OR(C13="",AN$2>C13,E13=0),"",IF(D13=0,1/C13,N(O13)/E13)) | AO13: =IF(OR(C13="",AO$2>C13,E13=0),"",IF(D13=0,1/C13,N(P13)/E13)) | AP13: =IF(OR(C13="",AP$2>C13,E13=0),"",IF(D13=0,1/C13,N(Q13)/E13)) | AQ13: =IF(OR(C13="",AQ$2>C13,E13=0),"",IF(D13=0,1/C13,N(R13)/E13)) | AR13: =IF(OR(C13="",AR$2>C13,E13=0),"",IF(D13=0,1/C13,N(S13)/E13)) | AS13: =IF(OR(C13="",AS$2>C13,E13=0),"",IF(D13=0,1/C13,N(T13)/E13)) | AT13: =IF(OR(C13="",AT$2>C13,E13=0),"",IF(D13=0,1/C13,N(U13)/E13)) | AU13: =IF(OR(C13="",AU$2>C13,E13=0),"",IF(D13=0,1/C13,N(V13)/E13)) | AV13: =IF(OR(C13="",AV$2>C13,E13=0),"",IF(D13=0,1/C13,N(W13)/E13)) | AW13: =IF(OR(C13="",AW$2>C13,E13=0),"",IF(D13=0,1/C13,N(X13)/E13)) | AX13: =IF(OR(C13="",AX$2>C13,E13=0),"",IF(D13=0,1/C13,N(Y13)/E13)) | AY13: =IF(OR(C13="",AY$2>C13,E13=0),"",IF(D13=0,1/C13,N(Z13)/E13)) | AZ13: =IF(OR(C13="",AZ$2>C13,E13=0),"",IF(D13=0,1/C13,N(AA13)/E13)) | BA13: =IF(OR(C13="",BA$2>C13,E13=0),"",IF(D13=0,1/C13,N(AB13)/E13)) | BB13: =IF(OR(C13="",BB$2>C13,E13=0),"",IF(D13=0,1/C13,N(AC13)/E13)) | BC13: =IF(OR(C13="",BC$2>C13,E13=0),"",IF(D13=0,1/C13,N(AD13)/E13)) | BD13: =IF(OR(C13="",BD$2>C13,E13=0),"",IF(D13=0,1/C13,N(AE13)/E13)) | BE13: =IF(OR(C13="",BE$2>C13,E13=0),"",IF(D13=0,1/C13,N(AF13)/E13)) | BF13: =IF(C13="","",SUM(AH13:BE13))
A14: 9 | B14: =IF(Projects!B14="","",Projects!B14) | C14: =IF(Projects!E14="","",Projects!E14) | D14: =COUNT($I14:$AF14) -> 0 | E14: =IF(C14="",0,IF(D14=0,C14,SUMPRODUCT($I14:$AF14*($I$2:$AF$2<=C14)))) -> 0 | F14: =IF(OR(C14="",Projects!D14=""),1,MAX(1,((YEAR(Projects!$C$2)-YEAR(Projects!D14))*12+MONTH(Projects!$C$2)-MONTH(Projects!D14)+1)+1)) -> 1 | G14: =IF(C14="",0,IF(D14=0,MAX(0,C14-F14+1),SUMPRODUCT($I14:$AF14*($I$2:$AF$2>=F14)*($I$2:$AF$2<=C14)))) -> 0 | H14: =IF(C14="",0,SUMPRODUCT(($I14:$AF14<>0)*($I$2:$AF$2>C14))) -> 0 | AH14: =IF(OR(C14="",AH$2>C14,E14=0),"",IF(D14=0,1/C14,N(I14)/E14)) | AI14: =IF(OR(C14="",AI$2>C14,E14=0),"",IF(D14=0,1/C14,N(J14)/E14)) | AJ14: =IF(OR(C14="",AJ$2>C14,E14=0),"",IF(D14=0,1/C14,N(K14)/E14)) | AK14: =IF(OR(C14="",AK$2>C14,E14=0),"",IF(D14=0,1/C14,N(L14)/E14)) | AL14: =IF(OR(C14="",AL$2>C14,E14=0),"",IF(D14=0,1/C14,N(M14)/E14)) | AM14: =IF(OR(C14="",AM$2>C14,E14=0),"",IF(D14=0,1/C14,N(N14)/E14)) | AN14: =IF(OR(C14="",AN$2>C14,E14=0),"",IF(D14=0,1/C14,N(O14)/E14)) | AO14: =IF(OR(C14="",AO$2>C14,E14=0),"",IF(D14=0,1/C14,N(P14)/E14)) | AP14: =IF(OR(C14="",AP$2>C14,E14=0),"",IF(D14=0,1/C14,N(Q14)/E14)) | AQ14: =IF(OR(C14="",AQ$2>C14,E14=0),"",IF(D14=0,1/C14,N(R14)/E14)) | AR14: =IF(OR(C14="",AR$2>C14,E14=0),"",IF(D14=0,1/C14,N(S14)/E14)) | AS14: =IF(OR(C14="",AS$2>C14,E14=0),"",IF(D14=0,1/C14,N(T14)/E14)) | AT14: =IF(OR(C14="",AT$2>C14,E14=0),"",IF(D14=0,1/C14,N(U14)/E14)) | AU14: =IF(OR(C14="",AU$2>C14,E14=0),"",IF(D14=0,1/C14,N(V14)/E14)) | AV14: =IF(OR(C14="",AV$2>C14,E14=0),"",IF(D14=0,1/C14,N(W14)/E14)) | AW14: =IF(OR(C14="",AW$2>C14,E14=0),"",IF(D14=0,1/C14,N(X14)/E14)) | AX14: =IF(OR(C14="",AX$2>C14,E14=0),"",IF(D14=0,1/C14,N(Y14)/E14)) | AY14: =IF(OR(C14="",AY$2>C14,E14=0),"",IF(D14=0,1/C14,N(Z14)/E14)) | AZ14: =IF(OR(C14="",AZ$2>C14,E14=0),"",IF(D14=0,1/C14,N(AA14)/E14)) | BA14: =IF(OR(C14="",BA$2>C14,E14=0),"",IF(D14=0,1/C14,N(AB14)/E14)) | BB14: =IF(OR(C14="",BB$2>C14,E14=0),"",IF(D14=0,1/C14,N(AC14)/E14)) | BC14: =IF(OR(C14="",BC$2>C14,E14=0),"",IF(D14=0,1/C14,N(AD14)/E14)) | BD14: =IF(OR(C14="",BD$2>C14,E14=0),"",IF(D14=0,1/C14,N(AE14)/E14)) | BE14: =IF(OR(C14="",BE$2>C14,E14=0),"",IF(D14=0,1/C14,N(AF14)/E14)) | BF14: =IF(C14="","",SUM(AH14:BE14))
A15: 10 | B15: =IF(Projects!B15="","",Projects!B15) | C15: =IF(Projects!E15="","",Projects!E15) | D15: =COUNT($I15:$AF15) -> 0 | E15: =IF(C15="",0,IF(D15=0,C15,SUMPRODUCT($I15:$AF15*($I$2:$AF$2<=C15)))) -> 0 | F15: =IF(OR(C15="",Projects!D15=""),1,MAX(1,((YEAR(Projects!$C$2)-YEAR(Projects!D15))*12+MONTH(Projects!$C$2)-MONTH(Projects!D15)+1)+1)) -> 1 | G15: =IF(C15="",0,IF(D15=0,MAX(0,C15-F15+1),SUMPRODUCT($I15:$AF15*($I$2:$AF$2>=F15)*($I$2:$AF$2<=C15)))) -> 0 | H15: =IF(C15="",0,SUMPRODUCT(($I15:$AF15<>0)*($I$2:$AF$2>C15))) -> 0 | AH15: =IF(OR(C15="",AH$2>C15,E15=0),"",IF(D15=0,1/C15,N(I15)/E15)) | AI15: =IF(OR(C15="",AI$2>C15,E15=0),"",IF(D15=0,1/C15,N(J15)/E15)) | AJ15: =IF(OR(C15="",AJ$2>C15,E15=0),"",IF(D15=0,1/C15,N(K15)/E15)) | AK15: =IF(OR(C15="",AK$2>C15,E15=0),"",IF(D15=0,1/C15,N(L15)/E15)) | AL15: =IF(OR(C15="",AL$2>C15,E15=0),"",IF(D15=0,1/C15,N(M15)/E15)) | AM15: =IF(OR(C15="",AM$2>C15,E15=0),"",IF(D15=0,1/C15,N(N15)/E15)) | AN15: =IF(OR(C15="",AN$2>C15,E15=0),"",IF(D15=0,1/C15,N(O15)/E15)) | AO15: =IF(OR(C15="",AO$2>C15,E15=0),"",IF(D15=0,1/C15,N(P15)/E15)) | AP15: =IF(OR(C15="",AP$2>C15,E15=0),"",IF(D15=0,1/C15,N(Q15)/E15)) | AQ15: =IF(OR(C15="",AQ$2>C15,E15=0),"",IF(D15=0,1/C15,N(R15)/E15)) | AR15: =IF(OR(C15="",AR$2>C15,E15=0),"",IF(D15=0,1/C15,N(S15)/E15)) | AS15: =IF(OR(C15="",AS$2>C15,E15=0),"",IF(D15=0,1/C15,N(T15)/E15)) | AT15: =IF(OR(C15="",AT$2>C15,E15=0),"",IF(D15=0,1/C15,N(U15)/E15)) | AU15: =IF(OR(C15="",AU$2>C15,E15=0),"",IF(D15=0,1/C15,N(V15)/E15)) | AV15: =IF(OR(C15="",AV$2>C15,E15=0),"",IF(D15=0,1/C15,N(W15)/E15)) | AW15: =IF(OR(C15="",AW$2>C15,E15=0),"",IF(D15=0,1/C15,N(X15)/E15)) | AX15: =IF(OR(C15="",AX$2>C15,E15=0),"",IF(D15=0,1/C15,N(Y15)/E15)) | AY15: =IF(OR(C15="",AY$2>C15,E15=0),"",IF(D15=0,1/C15,N(Z15)/E15)) | AZ15: =IF(OR(C15="",AZ$2>C15,E15=0),"",IF(D15=0,1/C15,N(AA15)/E15)) | BA15: =IF(OR(C15="",BA$2>C15,E15=0),"",IF(D15=0,1/C15,N(AB15)/E15)) | BB15: =IF(OR(C15="",BB$2>C15,E15=0),"",IF(D15=0,1/C15,N(AC15)/E15)) | BC15: =IF(OR(C15="",BC$2>C15,E15=0),"",IF(D15=0,1/C15,N(AD15)/E15)) | BD15: =IF(OR(C15="",BD$2>C15,E15=0),"",IF(D15=0,1/C15,N(AE15)/E15)) | BE15: =IF(OR(C15="",BE$2>C15,E15=0),"",IF(D15=0,1/C15,N(AF15)/E15)) | BF15: =IF(C15="","",SUM(AH15:BE15))
A16: 11 | B16: =IF(Projects!B16="","",Projects!B16) | C16: =IF(Projects!E16="","",Projects!E16) | D16: =COUNT($I16:$AF16) -> 0 | E16: =IF(C16="",0,IF(D16=0,C16,SUMPRODUCT($I16:$AF16*($I$2:$AF$2<=C16)))) -> 0 | F16: =IF(OR(C16="",Projects!D16=""),1,MAX(1,((YEAR(Projects!$C$2)-YEAR(Projects!D16))*12+MONTH(Projects!$C$2)-MONTH(Projects!D16)+1)+1)) -> 1 | G16: =IF(C16="",0,IF(D16=0,MAX(0,C16-F16+1),SUMPRODUCT($I16:$AF16*($I$2:$AF$2>=F16)*($I$2:$AF$2<=C16)))) -> 0 | H16: =IF(C16="",0,SUMPRODUCT(($I16:$AF16<>0)*($I$2:$AF$2>C16))) -> 0 | AH16: =IF(OR(C16="",AH$2>C16,E16=0),"",IF(D16=0,1/C16,N(I16)/E16)) | AI16: =IF(OR(C16="",AI$2>C16,E16=0),"",IF(D16=0,1/C16,N(J16)/E16)) | AJ16: =IF(OR(C16="",AJ$2>C16,E16=0),"",IF(D16=0,1/C16,N(K16)/E16)) | AK16: =IF(OR(C16="",AK$2>C16,E16=0),"",IF(D16=0,1/C16,N(L16)/E16)) | AL16: =IF(OR(C16="",AL$2>C16,E16=0),"",IF(D16=0,1/C16,N(M16)/E16)) | AM16: =IF(OR(C16="",AM$2>C16,E16=0),"",IF(D16=0,1/C16,N(N16)/E16)) | AN16: =IF(OR(C16="",AN$2>C16,E16=0),"",IF(D16=0,1/C16,N(O16)/E16)) | AO16: =IF(OR(C16="",AO$2>C16,E16=0),"",IF(D16=0,1/C16,N(P16)/E16)) | AP16: =IF(OR(C16="",AP$2>C16,E16=0),"",IF(D16=0,1/C16,N(Q16)/E16)) | AQ16: =IF(OR(C16="",AQ$2>C16,E16=0),"",IF(D16=0,1/C16,N(R16)/E16)) | AR16: =IF(OR(C16="",AR$2>C16,E16=0),"",IF(D16=0,1/C16,N(S16)/E16)) | AS16: =IF(OR(C16="",AS$2>C16,E16=0),"",IF(D16=0,1/C16,N(T16)/E16)) | AT16: =IF(OR(C16="",AT$2>C16,E16=0),"",IF(D16=0,1/C16,N(U16)/E16)) | AU16: =IF(OR(C16="",AU$2>C16,E16=0),"",IF(D16=0,1/C16,N(V16)/E16)) | AV16: =IF(OR(C16="",AV$2>C16,E16=0),"",IF(D16=0,1/C16,N(W16)/E16)) | AW16: =IF(OR(C16="",AW$2>C16,E16=0),"",IF(D16=0,1/C16,N(X16)/E16)) | AX16: =IF(OR(C16="",AX$2>C16,E16=0),"",IF(D16=0,1/C16,N(Y16)/E16)) | AY16: =IF(OR(C16="",AY$2>C16,E16=0),"",IF(D16=0,1/C16,N(Z16)/E16)) | AZ16: =IF(OR(C16="",AZ$2>C16,E16=0),"",IF(D16=0,1/C16,N(AA16)/E16)) | BA16: =IF(OR(C16="",BA$2>C16,E16=0),"",IF(D16=0,1/C16,N(AB16)/E16)) | BB16: =IF(OR(C16="",BB$2>C16,E16=0),"",IF(D16=0,1/C16,N(AC16)/E16)) | BC16: =IF(OR(C16="",BC$2>C16,E16=0),"",IF(D16=0,1/C16,N(AD16)/E16)) | BD16: =IF(OR(C16="",BD$2>C16,E16=0),"",IF(D16=0,1/C16,N(AE16)/E16)) | BE16: =IF(OR(C16="",BE$2>C16,E16=0),"",IF(D16=0,1/C16,N(AF16)/E16)) | BF16: =IF(C16="","",SUM(AH16:BE16))
A17: 12 | B17: =IF(Projects!B17="","",Projects!B17) | C17: =IF(Projects!E17="","",Projects!E17) | D17: =COUNT($I17:$AF17) -> 0 | E17: =IF(C17="",0,IF(D17=0,C17,SUMPRODUCT($I17:$AF17*($I$2:$AF$2<=C17)))) -> 0 | F17: =IF(OR(C17="",Projects!D17=""),1,MAX(1,((YEAR(Projects!$C$2)-YEAR(Projects!D17))*12+MONTH(Projects!$C$2)-MONTH(Projects!D17)+1)+1)) -> 1 | G17: =IF(C17="",0,IF(D17=0,MAX(0,C17-F17+1),SUMPRODUCT($I17:$AF17*($I$2:$AF$2>=F17)*($I$2:$AF$2<=C17)))) -> 0 | H17: =IF(C17="",0,SUMPRODUCT(($I17:$AF17<>0)*($I$2:$AF$2>C17))) -> 0 | AH17: =IF(OR(C17="",AH$2>C17,E17=0),"",IF(D17=0,1/C17,N(I17)/E17)) | AI17: =IF(OR(C17="",AI$2>C17,E17=0),"",IF(D17=0,1/C17,N(J17)/E17)) | AJ17: =IF(OR(C17="",AJ$2>C17,E17=0),"",IF(D17=0,1/C17,N(K17)/E17)) | AK17: =IF(OR(C17="",AK$2>C17,E17=0),"",IF(D17=0,1/C17,N(L17)/E17)) | AL17: =IF(OR(C17="",AL$2>C17,E17=0),"",IF(D17=0,1/C17,N(M17)/E17)) | AM17: =IF(OR(C17="",AM$2>C17,E17=0),"",IF(D17=0,1/C17,N(N17)/E17)) | AN17: =IF(OR(C17="",AN$2>C17,E17=0),"",IF(D17=0,1/C17,N(O17)/E17)) | AO17: =IF(OR(C17="",AO$2>C17,E17=0),"",IF(D17=0,1/C17,N(P17)/E17)) | AP17: =IF(OR(C17="",AP$2>C17,E17=0),"",IF(D17=0,1/C17,N(Q17)/E17)) | AQ17: =IF(OR(C17="",AQ$2>C17,E17=0),"",IF(D17=0,1/C17,N(R17)/E17)) | AR17: =IF(OR(C17="",AR$2>C17,E17=0),"",IF(D17=0,1/C17,N(S17)/E17)) | AS17: =IF(OR(C17="",AS$2>C17,E17=0),"",IF(D17=0,1/C17,N(T17)/E17)) | AT17: =IF(OR(C17="",AT$2>C17,E17=0),"",IF(D17=0,1/C17,N(U17)/E17)) | AU17: =IF(OR(C17="",AU$2>C17,E17=0),"",IF(D17=0,1/C17,N(V17)/E17)) | AV17: =IF(OR(C17="",AV$2>C17,E17=0),"",IF(D17=0,1/C17,N(W17)/E17)) | AW17: =IF(OR(C17="",AW$2>C17,E17=0),"",IF(D17=0,1/C17,N(X17)/E17)) | AX17: =IF(OR(C17="",AX$2>C17,E17=0),"",IF(D17=0,1/C17,N(Y17)/E17)) | AY17: =IF(OR(C17="",AY$2>C17,E17=0),"",IF(D17=0,1/C17,N(Z17)/E17)) | AZ17: =IF(OR(C17="",AZ$2>C17,E17=0),"",IF(D17=0,1/C17,N(AA17)/E17)) | BA17: =IF(OR(C17="",BA$2>C17,E17=0),"",IF(D17=0,1/C17,N(AB17)/E17)) | BB17: =IF(OR(C17="",BB$2>C17,E17=0),"",IF(D17=0,1/C17,N(AC17)/E17)) | BC17: =IF(OR(C17="",BC$2>C17,E17=0),"",IF(D17=0,1/C17,N(AD17)/E17)) | BD17: =IF(OR(C17="",BD$2>C17,E17=0),"",IF(D17=0,1/C17,N(AE17)/E17)) | BE17: =IF(OR(C17="",BE$2>C17,E17=0),"",IF(D17=0,1/C17,N(AF17)/E17)) | BF17: =IF(C17="","",SUM(AH17:BE17))
A18: 13 | B18: =IF(Projects!B18="","",Projects!B18) | C18: =IF(Projects!E18="","",Projects!E18) | D18: =COUNT($I18:$AF18) -> 0 | E18: =IF(C18="",0,IF(D18=0,C18,SUMPRODUCT($I18:$AF18*($I$2:$AF$2<=C18)))) -> 0 | F18: =IF(OR(C18="",Projects!D18=""),1,MAX(1,((YEAR(Projects!$C$2)-YEAR(Projects!D18))*12+MONTH(Projects!$C$2)-MONTH(Projects!D18)+1)+1)) -> 1 | G18: =IF(C18="",0,IF(D18=0,MAX(0,C18-F18+1),SUMPRODUCT($I18:$AF18*($I$2:$AF$2>=F18)*($I$2:$AF$2<=C18)))) -> 0 | H18: =IF(C18="",0,SUMPRODUCT(($I18:$AF18<>0)*($I$2:$AF$2>C18))) -> 0 | AH18: =IF(OR(C18="",AH$2>C18,E18=0),"",IF(D18=0,1/C18,N(I18)/E18)) | AI18: =IF(OR(C18="",AI$2>C18,E18=0),"",IF(D18=0,1/C18,N(J18)/E18)) | AJ18: =IF(OR(C18="",AJ$2>C18,E18=0),"",IF(D18=0,1/C18,N(K18)/E18)) | AK18: =IF(OR(C18="",AK$2>C18,E18=0),"",IF(D18=0,1/C18,N(L18)/E18)) | AL18: =IF(OR(C18="",AL$2>C18,E18=0),"",IF(D18=0,1/C18,N(M18)/E18)) | AM18: =IF(OR(C18="",AM$2>C18,E18=0),"",IF(D18=0,1/C18,N(N18)/E18)) | AN18: =IF(OR(C18="",AN$2>C18,E18=0),"",IF(D18=0,1/C18,N(O18)/E18)) | AO18: =IF(OR(C18="",AO$2>C18,E18=0),"",IF(D18=0,1/C18,N(P18)/E18)) | AP18: =IF(OR(C18="",AP$2>C18,E18=0),"",IF(D18=0,1/C18,N(Q18)/E18)) | AQ18: =IF(OR(C18="",AQ$2>C18,E18=0),"",IF(D18=0,1/C18,N(R18)/E18)) | AR18: =IF(OR(C18="",AR$2>C18,E18=0),"",IF(D18=0,1/C18,N(S18)/E18)) | AS18: =IF(OR(C18="",AS$2>C18,E18=0),"",IF(D18=0,1/C18,N(T18)/E18)) | AT18: =IF(OR(C18="",AT$2>C18,E18=0),"",IF(D18=0,1/C18,N(U18)/E18)) | AU18: =IF(OR(C18="",AU$2>C18,E18=0),"",IF(D18=0,1/C18,N(V18)/E18)) | AV18: =IF(OR(C18="",AV$2>C18,E18=0),"",IF(D18=0,1/C18,N(W18)/E18)) | AW18: =IF(OR(C18="",AW$2>C18,E18=0),"",IF(D18=0,1/C18,N(X18)/E18)) | AX18: =IF(OR(C18="",AX$2>C18,E18=0),"",IF(D18=0,1/C18,N(Y18)/E18)) | AY18: =IF(OR(C18="",AY$2>C18,E18=0),"",IF(D18=0,1/C18,N(Z18)/E18)) | AZ18: =IF(OR(C18="",AZ$2>C18,E18=0),"",IF(D18=0,1/C18,N(AA18)/E18)) | BA18: =IF(OR(C18="",BA$2>C18,E18=0),"",IF(D18=0,1/C18,N(AB18)/E18)) | BB18: =IF(OR(C18="",BB$2>C18,E18=0),"",IF(D18=0,1/C18,N(AC18)/E18)) | BC18: =IF(OR(C18="",BC$2>C18,E18=0),"",IF(D18=0,1/C18,N(AD18)/E18)) | BD18: =IF(OR(C18="",BD$2>C18,E18=0),"",IF(D18=0,1/C18,N(AE18)/E18)) | BE18: =IF(OR(C18="",BE$2>C18,E18=0),"",IF(D18=0,1/C18,N(AF18)/E18)) | BF18: =IF(C18="","",SUM(AH18:BE18))
... A55: 50 | B55: =IF(Projects!B55="","",Projects!B55) | C55: =IF(Projects!E55="","",Projects!E55) | D55: =COUNT($I55:$AF55) -> 0 | E55: =IF(C55="",0,IF(D55=0,C55,SUMPRODUCT($I55:$AF55*($I$2:$AF$2<=C55)))) -> 0 | F55: =IF(OR(C55="",Projects!D55=""),1,MAX(1,((YEAR(Projects!$C$2)-YEAR(Projects!D55))*12+MONTH(Projects!$C$2)-MONTH(Projects!D55)+1)+1)) -> 1 | G55: =IF(C55="",0,IF(D55=0,MAX(0,C55-F55+1),SUMPRODUCT($I55:$AF55*($I$2:$AF$2>=F55)*($I$2:$AF$2<=C55)))) -> 0 | H55: =IF(C55="",0,SUMPRODUCT(($I55:$AF55<>0)*($I$2:$AF$2>C55))) -> 0 | AH55: =IF(OR(C55="",AH$2>C55,E55=0),"",IF(D55=0,1/C55,N(I55)/E55)) | AI55: =IF(OR(C55="",AI$2>C55,E55=0),"",IF(D55=0,1/C55,N(J55)/E55)) | AJ55: =IF(OR(C55="",AJ$2>C55,E55=0),"",IF(D55=0,1/C55,N(K55)/E55)) | AK55: =IF(OR(C55="",AK$2>C55,E55=0),"",IF(D55=0,1/C55,N(L55)/E55)) | AL55: =IF(OR(C55="",AL$2>C55,E55=0),"",IF(D55=0,1/C55,N(M55)/E55)) | AM55: =IF(OR(C55="",AM$2>C55,E55=0),"",IF(D55=0,1/C55,N(N55)/E55)) | AN55: =IF(OR(C55="",AN$2>C55,E55=0),"",IF(D55=0,1/C55,N(O55)/E55)) | AO55: =IF(OR(C55="",AO$2>C55,E55=0),"",IF(D55=0,1/C55,N(P55)/E55)) | AP55: =IF(OR(C55="",AP$2>C55,E55=0),"",IF(D55=0,1/C55,N(Q55)/E55)) | AQ55: =IF(OR(C55="",AQ$2>C55,E55=0),"",IF(D55=0,1/C55,N(R55)/E55)) | AR55: =IF(OR(C55="",AR$2>C55,E55=0),"",IF(D55=0,1/C55,N(S55)/E55)) | AS55: =IF(OR(C55="",AS$2>C55,E55=0),"",IF(D55=0,1/C55,N(T55)/E55)) | AT55: =IF(OR(C55="",AT$2>C55,E55=0),"",IF(D55=0,1/C55,N(U55)/E55)) | AU55: =IF(OR(C55="",AU$2>C55,E55=0),"",IF(D55=0,1/C55,N(V55)/E55)) | AV55: =IF(OR(C55="",AV$2>C55,E55=0),"",IF(D55=0,1/C55,N(W55)/E55)) | AW55: =IF(OR(C55="",AW$2>C55,E55=0),"",IF(D55=0,1/C55,N(X55)/E55)) | AX55: =IF(OR(C55="",AX$2>C55,E55=0),"",IF(D55=0,1/C55,N(Y55)/E55)) | AY55: =IF(OR(C55="",AY$2>C55,E55=0),"",IF(D55=0,1/C55,N(Z55)/E55)) | AZ55: =IF(OR(C55="",AZ$2>C55,E55=0),"",IF(D55=0,1/C55,N(AA55)/E55)) | BA55: =IF(OR(C55="",BA$2>C55,E55=0),"",IF(D55=0,1/C55,N(AB55)/E55)) | BB55: =IF(OR(C55="",BB$2>C55,E55=0),"",IF(D55=0,1/C55,N(AC55)/E55)) | BC55: =IF(OR(C55="",BC$2>C55,E55=0),"",IF(D55=0,1/C55,N(AD55)/E55)) | BD55: =IF(OR(C55="",BD$2>C55,E55=0),"",IF(D55=0,1/C55,N(AE55)/E55)) | BE55: =IF(OR(C55="",BE$2>C55,E55=0),"",IF(D55=0,1/C55,N(AF55)/E55)) | BF55: =IF(C55="","",SUM(AH55:BE55))

Sheet WIP Log
A1: WIP Log (monthly actuals)
A3: Enter the WIP actual for each project and month. Only months up to and including the Current Month count; later months are ignored.
D4: =IF(D5<=Projects!$C$2,"actual","future") -> actual | E4: =IF(E5<=Projects!$C$2,"actual","future") -> actual | F4: =IF(F5<=Projects!$C$2,"actual","future") -> actual | G4: =IF(G5<=Projects!$C$2,"actual","future") -> actual | H4: =IF(H5<=Projects!$C$2,"actual","future") -> actual | I4: =IF(I5<=Projects!$C$2,"actual","future") -> actual | J4: =IF(J5<=Projects!$C$2,"actual","future") -> actual | K4: =IF(K5<=Projects!$C$2,"actual","future") -> actual | ... AM4: =IF(AM5<=Projects!$C$2,"actual","future") -> future
A5: # | B5: Project Name | C5: WIP to Date (≤ Current Month) | D5: =Projects!$C$3 -> 46023 | E5: =EDATE(D5,1) -> 46054 | F5: =EDATE(E5,1) -> 46082 | G5: =EDATE(F5,1) -> 46113 | H5: =EDATE(G5,1) -> 46143 | I5: =EDATE(H5,1) -> 46174 | J5: =EDATE(I5,1) -> 46204 | K5: =EDATE(J5,1) -> 46235 | L5: =EDATE(K5,1) -> 46266 | ... AM5: =EDATE(AL5,1) -> 47088
A6: 1 | B6: =IF(Projects!B6="","",Projects!B6) -> Example Project (slide) | C6: =SUMPRODUCT($D6:$AM6*($D$5:$AM$5<=Projects!$C$2)) -> 1000 | M6: 1000
A7: 2 | B7: =IF(Projects!B7="","",Projects!B7) | C7: =SUMPRODUCT($D7:$AM7*($D$5:$AM$5<=Projects!$C$2)) -> 0
A8: 3 | B8: =IF(Projects!B8="","",Projects!B8) | C8: =SUMPRODUCT($D8:$AM8*($D$5:$AM$5<=Projects!$C$2)) -> 0
A9: 4 | B9: =IF(Projects!B9="","",Projects!B9) | C9: =SUMPRODUCT($D9:$AM9*($D$5:$AM$5<=Projects!$C$2)) -> 0
A10: 5 | B10: =IF(Projects!B10="","",Projects!B10) | C10: =SUMPRODUCT($D10:$AM10*($D$5:$AM$5<=Projects!$C$2)) -> 0
A11: 6 | B11: =IF(Projects!B11="","",Projects!B11) | C11: =SUMPRODUCT($D11:$AM11*($D$5:$AM$5<=Projects!$C$2)) -> 0
A12: 7 | B12: =IF(Projects!B12="","",Projects!B12) | C12: =SUMPRODUCT($D12:$AM12*($D$5:$AM$5<=Projects!$C$2)) -> 0
A13: 8 | B13: =IF(Projects!B13="","",Projects!B13) | C13: =SUMPRODUCT($D13:$AM13*($D$5:$AM$5<=Projects!$C$2)) -> 0
A14: 9 | B14: =IF(Projects!B14="","",Projects!B14) | C14: =SUMPRODUCT($D14:$AM14*($D$5:$AM$5<=Projects!$C$2)) -> 0
A15: 10 | B15: =IF(Projects!B15="","",Projects!B15) | C15: =SUMPRODUCT($D15:$AM15*($D$5:$AM$5<=Projects!$C$2)) -> 0
A16: 11 | B16: =IF(Projects!B16="","",Projects!B16) | C16: =SUMPRODUCT($D16:$AM16*($D$5:$AM$5<=Projects!$C$2)) -> 0
A17: 12 | B17: =IF(Projects!B17="","",Projects!B17) | C17: =SUMPRODUCT($D17:$AM17*($D$5:$AM$5<=Projects!$C$2)) -> 0
A18: 13 | B18: =IF(Projects!B18="","",Projects!B18) | C18: =SUMPRODUCT($D18:$AM18*($D$5:$AM$5<=Projects!$C$2)) -> 0
... A55: 50 | B55: =IF(Projects!B55="","",Projects!B55) | C55: =SUMPRODUCT($D55:$AM55*($D$5:$AM$5<=Projects!$C$2)) -> 0
B57: TOTAL | C57: =SUM(C6:C55) -> 1000 | D57: =SUM(D6:D55) -> 0 | E57: =SUM(E6:E55) -> 0 | F57: =SUM(F6:F55) -> 0 | G57: =SUM(G6:G55) -> 0 | H57: =SUM(H6:H55) -> 0 | I57: =SUM(I6:I55) -> 0 | J57: =SUM(J6:J55) -> 0 | ... AM57: =SUM(AM6:AM55) -> 0

Sheet Project Page
A1: Project Page | J1: row | K1: =IFERROR(MATCH(B3,Projects!$B$6:$B$55,0),0) -> 1
A3: Select project ▸ | B3: Example Project (slide) | F3: =IF(ISNA(MATCH(B3,Projects!$B$6:$B$55,0)),"◂ Pick a project from the dropdown","")
A5: Engagement Manager | B5: =IF($K$1=0,"",INDEX(Projects!$C$6:$C$55,$K$1)&"") -> J. Doe
A6: Starting Month | B6: =IF($K$1=0,"",INDEX(Projects!$D$6:$D$55,$K$1)) -> 46296
A7: Duration (months) | B7: =IF($K$1=0,"",INDEX(Projects!$E$6:$E$55,$K$1)) -> 5
A8: End Month | B8: =IF($K$1=0,"",INDEX(Projects!$F$6:$F$55,$K$1)) -> 46419
A9: Contracted Budget | B9: =IF($K$1=0,"",INDEX(Projects!$G$6:$G$55,$K$1)) -> 10000
A10: WIP to Date | B10: =IF($K$1=0,"",INDEX(Projects!$H$6:$H$55,$K$1)) -> 1000
A11: Budgeted (Contract − WIP) | B11: =IF($K$1=0,"",INDEX(Projects!$I$6:$I$55,$K$1)) -> 9000
A12: Remaining Months | B12: =IF($K$1=0,"",INDEX(Projects!$J$6:$J$55,$K$1)) -> 4
A13: Status | B13: =IF($K$1=0,"",INDEX(Projects!$N$6:$N$55,$K$1)&"") -> OK
A16: Project Month | B16: Calendar Month | C16: Raw Weight | D16: Plan Weight (Σ=1) | E16: Original Plan (Contract × weight) | F16: WIP Actual | G16: Phased Budgeted | H16: Total (WIP + Phased) | I16: Actual / Forecast
A17: =IF(AND($K$1>0,1<=N($B$7)),1,"") -> 1 | B17: =IF(A17="","",EDATE($B$6,A17-1)) -> 46296 | C17: =IF(A17="","",IF(INDEX(Phasing!$D$6:$D$55,$K$1)=0,1,N(INDEX(Phasing!$I$6:$AF$55,$K$1,A17)))) -> 1 | D17: =IF(A17="","",N(INDEX(Phasing!$AH$6:$BE$55,$K$1,A17))) -> 0.11111111 | E17: =IF(A17="","",D17*N($B$9)) -> 1111.1111 | F17: =IF(A17="","",IF(AND(AND(((YEAR(B17)-YEAR(Projects!$C$3))*12+MONTH(B17)-MONTH(Projects!$C$3)+1)>=1,((YEAR(B17)-YEAR(Projects!$C$3))*12+MONTH(B17)-MONTH(Projects!$C$3)+1)<=36),B17<=Projects!$C$2),INDEX('WIP Log'!$D$6:$AM$55,$K$1,((YEAR(B17)-YEAR(Projects!$C$3))*12+MONTH(B17)-MONTH(Projects!$C$3)+1)),0)) -> 1000 | G17: =IF(A17="","",IF(AND(((YEAR(B17)-YEAR(Projects!$C$3))*12+MONTH(B17)-MONTH(Projects!$C$3)+1)>=1,((YEAR(B17)-YEAR(Projects!$C$3))*12+MONTH(B17)-MONTH(Projects!$C$3)+1)<=36),INDEX('Phased Budget'!$H$6:$AQ$55,$K$1,((YEAR(B17)-YEAR(Projects!$C$3))*12+MONTH(B17)-MONTH(Projects!$C$3)+1)),0)) -> 0 | H17: =IF(A17="","",F17+G17) -> 1000 | I17: =IF(A17="","",IF(B17<=Projects!$C$2,"Actual","Forecast")) -> Actual
A18: =IF(AND($K$1>0,2<=N($B$7)),2,"") -> 2 | B18: =IF(A18="","",EDATE($B$6,A18-1)) -> 46327 | C18: =IF(A18="","",IF(INDEX(Phasing!$D$6:$D$55,$K$1)=0,1,N(INDEX(Phasing!$I$6:$AF$55,$K$1,A18)))) -> 2 | D18: =IF(A18="","",N(INDEX(Phasing!$AH$6:$BE$55,$K$1,A18))) -> 0.22222222 | E18: =IF(A18="","",D18*N($B$9)) -> 2222.2222 | F18: =IF(A18="","",IF(AND(AND(((YEAR(B18)-YEAR(Projects!$C$3))*12+MONTH(B18)-MONTH(Projects!$C$3)+1)>=1,((YEAR(B18)-YEAR(Projects!$C$3))*12+MONTH(B18)-MONTH(Projects!$C$3)+1)<=36),B18<=Projects!$C$2),INDEX('WIP Log'!$D$6:$AM$55,$K$1,((YEAR(B18)-YEAR(Projects!$C$3))*12+MONTH(B18)-MONTH(Projects!$C$3)+1)),0)) -> 0 | G18: =IF(A18="","",IF(AND(((YEAR(B18)-YEAR(Projects!$C$3))*12+MONTH(B18)-MONTH(Projects!$C$3)+1)>=1,((YEAR(B18)-YEAR(Projects!$C$3))*12+MONTH(B18)-MONTH(Projects!$C$3)+1)<=36),INDEX('Phased Budget'!$H$6:$AQ$55,$K$1,((YEAR(B18)-YEAR(Projects!$C$3))*12+MONTH(B18)-MONTH(Projects!$C$3)+1)),0)) -> 2250 | H18: =IF(A18="","",F18+G18) -> 2250 | I18: =IF(A18="","",IF(B18<=Projects!$C$2,"Actual","Forecast")) -> Forecast
A19: =IF(AND($K$1>0,3<=N($B$7)),3,"") -> 3 | B19: =IF(A19="","",EDATE($B$6,A19-1)) -> 46357 | C19: =IF(A19="","",IF(INDEX(Phasing!$D$6:$D$55,$K$1)=0,1,N(INDEX(Phasing!$I$6:$AF$55,$K$1,A19)))) -> 2 | D19: =IF(A19="","",N(INDEX(Phasing!$AH$6:$BE$55,$K$1,A19))) -> 0.22222222 | E19: =IF(A19="","",D19*N($B$9)) -> 2222.2222 | F19: =IF(A19="","",IF(AND(AND(((YEAR(B19)-YEAR(Projects!$C$3))*12+MONTH(B19)-MONTH(Projects!$C$3)+1)>=1,((YEAR(B19)-YEAR(Projects!$C$3))*12+MONTH(B19)-MONTH(Projects!$C$3)+1)<=36),B19<=Projects!$C$2),INDEX('WIP Log'!$D$6:$AM$55,$K$1,((YEAR(B19)-YEAR(Projects!$C$3))*12+MONTH(B19)-MONTH(Projects!$C$3)+1)),0)) -> 0 | G19: =IF(A19="","",IF(AND(((YEAR(B19)-YEAR(Projects!$C$3))*12+MONTH(B19)-MONTH(Projects!$C$3)+1)>=1,((YEAR(B19)-YEAR(Projects!$C$3))*12+MONTH(B19)-MONTH(Projects!$C$3)+1)<=36),INDEX('Phased Budget'!$H$6:$AQ$55,$K$1,((YEAR(B19)-YEAR(Projects!$C$3))*12+MONTH(B19)-MONTH(Projects!$C$3)+1)),0)) -> 2250 | H19: =IF(A19="","",F19+G19) -> 2250 | I19: =IF(A19="","",IF(B19<=Projects!$C$2,"Actual","Forecast")) -> Forecast
A20: =IF(AND($K$1>0,4<=N($B$7)),4,"") -> 4 | B20: =IF(A20="","",EDATE($B$6,A20-1)) -> 46388 | C20: =IF(A20="","",IF(INDEX(Phasing!$D$6:$D$55,$K$1)=0,1,N(INDEX(Phasing!$I$6:$AF$55,$K$1,A20)))) -> 2 | D20: =IF(A20="","",N(INDEX(Phasing!$AH$6:$BE$55,$K$1,A20))) -> 0.22222222 | E20: =IF(A20="","",D20*N($B$9)) -> 2222.2222 | F20: =IF(A20="","",IF(AND(AND(((YEAR(B20)-YEAR(Projects!$C$3))*12+MONTH(B20)-MONTH(Projects!$C$3)+1)>=1,((YEAR(B20)-YEAR(Projects!$C$3))*12+MONTH(B20)-MONTH(Projects!$C$3)+1)<=36),B20<=Projects!$C$2),INDEX('WIP Log'!$D$6:$AM$55,$K$1,((YEAR(B20)-YEAR(Projects!$C$3))*12+MONTH(B20)-MONTH(Projects!$C$3)+1)),0)) -> 0 | G20: =IF(A20="","",IF(AND(((YEAR(B20)-YEAR(Projects!$C$3))*12+MONTH(B20)-MONTH(Projects!$C$3)+1)>=1,((YEAR(B20)-YEAR(Projects!$C$3))*12+MONTH(B20)-MONTH(Projects!$C$3)+1)<=36),INDEX('Phased Budget'!$H$6:$AQ$55,$K$1,((YEAR(B20)-YEAR(Projects!$C$3))*12+MONTH(B20)-MONTH(Projects!$C$3)+1)),0)) -> 2250 | H20: =IF(A20="","",F20+G20) -> 2250 | I20: =IF(A20="","",IF(B20<=Projects!$C$2,"Actual","Forecast")) -> Forecast
A21: =IF(AND($K$1>0,5<=N($B$7)),5,"") -> 5 | B21: =IF(A21="","",EDATE($B$6,A21-1)) -> 46419 | C21: =IF(A21="","",IF(INDEX(Phasing!$D$6:$D$55,$K$1)=0,1,N(INDEX(Phasing!$I$6:$AF$55,$K$1,A21)))) -> 2 | D21: =IF(A21="","",N(INDEX(Phasing!$AH$6:$BE$55,$K$1,A21))) -> 0.22222222 | E21: =IF(A21="","",D21*N($B$9)) -> 2222.2222 | F21: =IF(A21="","",IF(AND(AND(((YEAR(B21)-YEAR(Projects!$C$3))*12+MONTH(B21)-MONTH(Projects!$C$3)+1)>=1,((YEAR(B21)-YEAR(Projects!$C$3))*12+MONTH(B21)-MONTH(Projects!$C$3)+1)<=36),B21<=Projects!$C$2),INDEX('WIP Log'!$D$6:$AM$55,$K$1,((YEAR(B21)-YEAR(Projects!$C$3))*12+MONTH(B21)-MONTH(Projects!$C$3)+1)),0)) -> 0 | G21: =IF(A21="","",IF(AND(((YEAR(B21)-YEAR(Projects!$C$3))*12+MONTH(B21)-MONTH(Projects!$C$3)+1)>=1,((YEAR(B21)-YEAR(Projects!$C$3))*12+MONTH(B21)-MONTH(Projects!$C$3)+1)<=36),INDEX('Phased Budget'!$H$6:$AQ$55,$K$1,((YEAR(B21)-YEAR(Projects!$C$3))*12+MONTH(B21)-MONTH(Projects!$C$3)+1)),0)) -> 2250 | H21: =IF(A21="","",F21+G21) -> 2250 | I21: =IF(A21="","",IF(B21<=Projects!$C$2,"Actual","Forecast")) -> Forecast
A22: =IF(AND($K$1>0,6<=N($B$7)),6,"") | B22: =IF(A22="","",EDATE($B$6,A22-1)) | C22: =IF(A22="","",IF(INDEX(Phasing!$D$6:$D$55,$K$1)=0,1,N(INDEX(Phasing!$I$6:$AF$55,$K$1,A22)))) | D22: =IF(A22="","",N(INDEX(Phasing!$AH$6:$BE$55,$K$1,A22))) | E22: =IF(A22="","",D22*N($B$9)) | F22: =IF(A22="","",IF(AND(AND(((YEAR(B22)-YEAR(Projects!$C$3))*12+MONTH(B22)-MONTH(Projects!$C$3)+1)>=1,((YEAR(B22)-YEAR(Projects!$C$3))*12+MONTH(B22)-MONTH(Projects!$C$3)+1)<=36),B22<=Projects!$C$2),INDEX('WIP Log'!$D$6:$AM$55,$K$1,((YEAR(B22)-YEAR(Projects!$C$3))*12+MONTH(B22)-MONTH(Projects!$C$3)+1)),0)) | G22: =IF(A22="","",IF(AND(((YEAR(B22)-YEAR(Projects!$C$3))*12+MONTH(B22)-MONTH(Projects!$C$3)+1)>=1,((YEAR(B22)-YEAR(Projects!$C$3))*12+MONTH(B22)-MONTH(Projects!$C$3)+1)<=36),INDEX('Phased Budget'!$H$6:$AQ$55,$K$1,((YEAR(B22)-YEAR(Projects!$C$3))*12+MONTH(B22)-MONTH(Projects!$C$3)+1)),0)) | H22: =IF(A22="","",F22+G22) | I22: =IF(A22="","",IF(B22<=Projects!$C$2,"Actual","Forecast"))
A23: =IF(AND($K$1>0,7<=N($B$7)),7,"") | B23: =IF(A23="","",EDATE($B$6,A23-1)) | C23: =IF(A23="","",IF(INDEX(Phasing!$D$6:$D$55,$K$1)=0,1,N(INDEX(Phasing!$I$6:$AF$55,$K$1,A23)))) | D23: =IF(A23="","",N(INDEX(Phasing!$AH$6:$BE$55,$K$1,A23))) | E23: =IF(A23="","",D23*N($B$9)) | F23: =IF(A23="","",IF(AND(AND(((YEAR(B23)-YEAR(Projects!$C$3))*12+MONTH(B23)-MONTH(Projects!$C$3)+1)>=1,((YEAR(B23)-YEAR(Projects!$C$3))*12+MONTH(B23)-MONTH(Projects!$C$3)+1)<=36),B23<=Projects!$C$2),INDEX('WIP Log'!$D$6:$AM$55,$K$1,((YEAR(B23)-YEAR(Projects!$C$3))*12+MONTH(B23)-MONTH(Projects!$C$3)+1)),0)) | G23: =IF(A23="","",IF(AND(((YEAR(B23)-YEAR(Projects!$C$3))*12+MONTH(B23)-MONTH(Projects!$C$3)+1)>=1,((YEAR(B23)-YEAR(Projects!$C$3))*12+MONTH(B23)-MONTH(Projects!$C$3)+1)<=36),INDEX('Phased Budget'!$H$6:$AQ$55,$K$1,((YEAR(B23)-YEAR(Projects!$C$3))*12+MONTH(B23)-MONTH(Projects!$C$3)+1)),0)) | H23: =IF(A23="","",F23+G23) | I23: =IF(A23="","",IF(B23<=Projects!$C$2,"Actual","Forecast"))
A24: =IF(AND($K$1>0,8<=N($B$7)),8,"") | B24: =IF(A24="","",EDATE($B$6,A24-1)) | C24: =IF(A24="","",IF(INDEX(Phasing!$D$6:$D$55,$K$1)=0,1,N(INDEX(Phasing!$I$6:$AF$55,$K$1,A24)))) | D24: =IF(A24="","",N(INDEX(Phasing!$AH$6:$BE$55,$K$1,A24))) | E24: =IF(A24="","",D24*N($B$9)) | F24: =IF(A24="","",IF(AND(AND(((YEAR(B24)-YEAR(Projects!$C$3))*12+MONTH(B24)-MONTH(Projects!$C$3)+1)>=1,((YEAR(B24)-YEAR(Projects!$C$3))*12+MONTH(B24)-MONTH(Projects!$C$3)+1)<=36),B24<=Projects!$C$2),INDEX('WIP Log'!$D$6:$AM$55,$K$1,((YEAR(B24)-YEAR(Projects!$C$3))*12+MONTH(B24)-MONTH(Projects!$C$3)+1)),0)) | G24: =IF(A24="","",IF(AND(((YEAR(B24)-YEAR(Projects!$C$3))*12+MONTH(B24)-MONTH(Projects!$C$3)+1)>=1,((YEAR(B24)-YEAR(Projects!$C$3))*12+MONTH(B24)-MONTH(Projects!$C$3)+1)<=36),INDEX('Phased Budget'!$H$6:$AQ$55,$K$1,((YEAR(B24)-YEAR(Projects!$C$3))*12+MONTH(B24)-MONTH(Projects!$C$3)+1)),0)) | H24: =IF(A24="","",F24+G24) | I24: =IF(A24="","",IF(B24<=Projects!$C$2,"Actual","Forecast"))
A25: =IF(AND($K$1>0,9<=N($B$7)),9,"") | B25: =IF(A25="","",EDATE($B$6,A25-1)) | C25: =IF(A25="","",IF(INDEX(Phasing!$D$6:$D$55,$K$1)=0,1,N(INDEX(Phasing!$I$6:$AF$55,$K$1,A25)))) | D25: =IF(A25="","",N(INDEX(Phasing!$AH$6:$BE$55,$K$1,A25))) | E25: =IF(A25="","",D25*N($B$9)) | F25: =IF(A25="","",IF(AND(AND(((YEAR(B25)-YEAR(Projects!$C$3))*12+MONTH(B25)-MONTH(Projects!$C$3)+1)>=1,((YEAR(B25)-YEAR(Projects!$C$3))*12+MONTH(B25)-MONTH(Projects!$C$3)+1)<=36),B25<=Projects!$C$2),INDEX('WIP Log'!$D$6:$AM$55,$K$1,((YEAR(B25)-YEAR(Projects!$C$3))*12+MONTH(B25)-MONTH(Projects!$C$3)+1)),0)) | G25: =IF(A25="","",IF(AND(((YEAR(B25)-YEAR(Projects!$C$3))*12+MONTH(B25)-MONTH(Projects!$C$3)+1)>=1,((YEAR(B25)-YEAR(Projects!$C$3))*12+MONTH(B25)-MONTH(Projects!$C$3)+1)<=36),INDEX('Phased Budget'!$H$6:$AQ$55,$K$1,((YEAR(B25)-YEAR(Projects!$C$3))*12+MONTH(B25)-MONTH(Projects!$C$3)+1)),0)) | H25: =IF(A25="","",F25+G25) | I25: =IF(A25="","",IF(B25<=Projects!$C$2,"Actual","Forecast"))
A26: =IF(AND($K$1>0,10<=N($B$7)),10,"") | B26: =IF(A26="","",EDATE($B$6,A26-1)) | C26: =IF(A26="","",IF(INDEX(Phasing!$D$6:$D$55,$K$1)=0,1,N(INDEX(Phasing!$I$6:$AF$55,$K$1,A26)))) | D26: =IF(A26="","",N(INDEX(Phasing!$AH$6:$BE$55,$K$1,A26))) | E26: =IF(A26="","",D26*N($B$9)) | F26: =IF(A26="","",IF(AND(AND(((YEAR(B26)-YEAR(Projects!$C$3))*12+MONTH(B26)-MONTH(Projects!$C$3)+1)>=1,((YEAR(B26)-YEAR(Projects!$C$3))*12+MONTH(B26)-MONTH(Projects!$C$3)+1)<=36),B26<=Projects!$C$2),INDEX('WIP Log'!$D$6:$AM$55,$K$1,((YEAR(B26)-YEAR(Projects!$C$3))*12+MONTH(B26)-MONTH(Projects!$C$3)+1)),0)) | G26: =IF(A26="","",IF(AND(((YEAR(B26)-YEAR(Projects!$C$3))*12+MONTH(B26)-MONTH(Projects!$C$3)+1)>=1,((YEAR(B26)-YEAR(Projects!$C$3))*12+MONTH(B26)-MONTH(Projects!$C$3)+1)<=36),INDEX('Phased Budget'!$H$6:$AQ$55,$K$1,((YEAR(B26)-YEAR(Projects!$C$3))*12+MONTH(B26)-MONTH(Projects!$C$3)+1)),0)) | H26: =IF(A26="","",F26+G26) | I26: =IF(A26="","",IF(B26<=Projects!$C$2,"Actual","Forecast"))
A27: =IF(AND($K$1>0,11<=N($B$7)),11,"") | B27: =IF(A27="","",EDATE($B$6,A27-1)) | C27: =IF(A27="","",IF(INDEX(Phasing!$D$6:$D$55,$K$1)=0,1,N(INDEX(Phasing!$I$6:$AF$55,$K$1,A27)))) | D27: =IF(A27="","",N(INDEX(Phasing!$AH$6:$BE$55,$K$1,A27))) | E27: =IF(A27="","",D27*N($B$9)) | F27: =IF(A27="","",IF(AND(AND(((YEAR(B27)-YEAR(Projects!$C$3))*12+MONTH(B27)-MONTH(Projects!$C$3)+1)>=1,((YEAR(B27)-YEAR(Projects!$C$3))*12+MONTH(B27)-MONTH(Projects!$C$3)+1)<=36),B27<=Projects!$C$2),INDEX('WIP Log'!$D$6:$AM$55,$K$1,((YEAR(B27)-YEAR(Projects!$C$3))*12+MONTH(B27)-MONTH(Projects!$C$3)+1)),0)) | G27: =IF(A27="","",IF(AND(((YEAR(B27)-YEAR(Projects!$C$3))*12+MONTH(B27)-MONTH(Projects!$C$3)+1)>=1,((YEAR(B27)-YEAR(Projects!$C$3))*12+MONTH(B27)-MONTH(Projects!$C$3)+1)<=36),INDEX('Phased Budget'!$H$6:$AQ$55,$K$1,((YEAR(B27)-YEAR(Projects!$C$3))*12+MONTH(B27)-MONTH(Projects!$C$3)+1)),0)) | H27: =IF(A27="","",F27+G27) | I27: =IF(A27="","",IF(B27<=Projects!$C$2,"Actual","Forecast"))
A28: =IF(AND($K$1>0,12<=N($B$7)),12,"") | B28: =IF(A28="","",EDATE($B$6,A28-1)) | C28: =IF(A28="","",IF(INDEX(Phasing!$D$6:$D$55,$K$1)=0,1,N(INDEX(Phasing!$I$6:$AF$55,$K$1,A28)))) | D28: =IF(A28="","",N(INDEX(Phasing!$AH$6:$BE$55,$K$1,A28))) | E28: =IF(A28="","",D28*N($B$9)) | F28: =IF(A28="","",IF(AND(AND(((YEAR(B28)-YEAR(Projects!$C$3))*12+MONTH(B28)-MONTH(Projects!$C$3)+1)>=1,((YEAR(B28)-YEAR(Projects!$C$3))*12+MONTH(B28)-MONTH(Projects!$C$3)+1)<=36),B28<=Projects!$C$2),INDEX('WIP Log'!$D$6:$AM$55,$K$1,((YEAR(B28)-YEAR(Projects!$C$3))*12+MONTH(B28)-MONTH(Projects!$C$3)+1)),0)) | G28: =IF(A28="","",IF(AND(((YEAR(B28)-YEAR(Projects!$C$3))*12+MONTH(B28)-MONTH(Projects!$C$3)+1)>=1,((YEAR(B28)-YEAR(Projects!$C$3))*12+MONTH(B28)-MONTH(Projects!$C$3)+1)<=36),INDEX('Phased Budget'!$H$6:$AQ$55,$K$1,((YEAR(B28)-YEAR(Projects!$C$3))*12+MONTH(B28)-MONTH(Projects!$C$3)+1)),0)) | H28: =IF(A28="","",F28+G28) | I28: =IF(A28="","",IF(B28<=Projects!$C$2,"Actual","Forecast"))
A29: =IF(AND($K$1>0,13<=N($B$7)),13,"") | B29: =IF(A29="","",EDATE($B$6,A29-1)) | C29: =IF(A29="","",IF(INDEX(Phasing!$D$6:$D$55,$K$1)=0,1,N(INDEX(Phasing!$I$6:$AF$55,$K$1,A29)))) | D29: =IF(A29="","",N(INDEX(Phasing!$AH$6:$BE$55,$K$1,A29))) | E29: =IF(A29="","",D29*N($B$9)) | F29: =IF(A29="","",IF(AND(AND(((YEAR(B29)-YEAR(Projects!$C$3))*12+MONTH(B29)-MONTH(Projects!$C$3)+1)>=1,((YEAR(B29)-YEAR(Projects!$C$3))*12+MONTH(B29)-MONTH(Projects!$C$3)+1)<=36),B29<=Projects!$C$2),INDEX('WIP Log'!$D$6:$AM$55,$K$1,((YEAR(B29)-YEAR(Projects!$C$3))*12+MONTH(B29)-MONTH(Projects!$C$3)+1)),0)) | G29: =IF(A29="","",IF(AND(((YEAR(B29)-YEAR(Projects!$C$3))*12+MONTH(B29)-MONTH(Projects!$C$3)+1)>=1,((YEAR(B29)-YEAR(Projects!$C$3))*12+MONTH(B29)-MONTH(Projects!$C$3)+1)<=36),INDEX('Phased Budget'!$H$6:$AQ$55,$K$1,((YEAR(B29)-YEAR(Projects!$C$3))*12+MONTH(B29)-MONTH(Projects!$C$3)+1)),0)) | H29: =IF(A29="","",F29+G29) | I29: =IF(A29="","",IF(B29<=Projects!$C$2,"Actual","Forecast"))
A30: =IF(AND($K$1>0,14<=N($B$7)),14,"") | B30: =IF(A30="","",EDATE($B$6,A30-1)) | C30: =IF(A30="","",IF(INDEX(Phasing!$D$6:$D$55,$K$1)=0,1,N(INDEX(Phasing!$I$6:$AF$55,$K$1,A30)))) | D30: =IF(A30="","",N(INDEX(Phasing!$AH$6:$BE$55,$K$1,A30))) | E30: =IF(A30="","",D30*N($B$9)) | F30: =IF(A30="","",IF(AND(AND(((YEAR(B30)-YEAR(Projects!$C$3))*12+MONTH(B30)-MONTH(Projects!$C$3)+1)>=1,((YEAR(B30)-YEAR(Projects!$C$3))*12+MONTH(B30)-MONTH(Projects!$C$3)+1)<=36),B30<=Projects!$C$2),INDEX('WIP Log'!$D$6:$AM$55,$K$1,((YEAR(B30)-YEAR(Projects!$C$3))*12+MONTH(B30)-MONTH(Projects!$C$3)+1)),0)) | G30: =IF(A30="","",IF(AND(((YEAR(B30)-YEAR(Projects!$C$3))*12+MONTH(B30)-MONTH(Projects!$C$3)+1)>=1,((YEAR(B30)-YEAR(Projects!$C$3))*12+MONTH(B30)-MONTH(Projects!$C$3)+1)<=36),INDEX('Phased Budget'!$H$6:$AQ$55,$K$1,((YEAR(B30)-YEAR(Projects!$C$3))*12+MONTH(B30)-MONTH(Projects!$C$3)+1)),0)) | H30: =IF(A30="","",F30+G30) | I30: =IF(A30="","",IF(B30<=Projects!$C$2,"Actual","Forecast"))
A31: =IF(AND($K$1>0,15<=N($B$7)),15,"") | B31: =IF(A31="","",EDATE($B$6,A31-1)) | C31: =IF(A31="","",IF(INDEX(Phasing!$D$6:$D$55,$K$1)=0,1,N(INDEX(Phasing!$I$6:$AF$55,$K$1,A31)))) | D31: =IF(A31="","",N(INDEX(Phasing!$AH$6:$BE$55,$K$1,A31))) | E31: =IF(A31="","",D31*N($B$9)) | F31: =IF(A31="","",IF(AND(AND(((YEAR(B31)-YEAR(Projects!$C$3))*12+MONTH(B31)-MONTH(Projects!$C$3)+1)>=1,((YEAR(B31)-YEAR(Projects!$C$3))*12+MONTH(B31)-MONTH(Projects!$C$3)+1)<=36),B31<=Projects!$C$2),INDEX('WIP Log'!$D$6:$AM$55,$K$1,((YEAR(B31)-YEAR(Projects!$C$3))*12+MONTH(B31)-MONTH(Projects!$C$3)+1)),0)) | G31: =IF(A31="","",IF(AND(((YEAR(B31)-YEAR(Projects!$C$3))*12+MONTH(B31)-MONTH(Projects!$C$3)+1)>=1,((YEAR(B31)-YEAR(Projects!$C$3))*12+MONTH(B31)-MONTH(Projects!$C$3)+1)<=36),INDEX('Phased Budget'!$H$6:$AQ$55,$K$1,((YEAR(B31)-YEAR(Projects!$C$3))*12+MONTH(B31)-MONTH(Projects!$C$3)+1)),0)) | H31: =IF(A31="","",F31+G31) | I31: =IF(A31="","",IF(B31<=Projects!$C$2,"Actual","Forecast"))
A32: =IF(AND($K$1>0,16<=N($B$7)),16,"") | B32: =IF(A32="","",EDATE($B$6,A32-1)) | C32: =IF(A32="","",IF(INDEX(Phasing!$D$6:$D$55,$K$1)=0,1,N(INDEX(Phasing!$I$6:$AF$55,$K$1,A32)))) | D32: =IF(A32="","",N(INDEX(Phasing!$AH$6:$BE$55,$K$1,A32))) | E32: =IF(A32="","",D32*N($B$9)) | F32: =IF(A32="","",IF(AND(AND(((YEAR(B32)-YEAR(Projects!$C$3))*12+MONTH(B32)-MONTH(Projects!$C$3)+1)>=1,((YEAR(B32)-YEAR(Projects!$C$3))*12+MONTH(B32)-MONTH(Projects!$C$3)+1)<=36),B32<=Projects!$C$2),INDEX('WIP Log'!$D$6:$AM$55,$K$1,((YEAR(B32)-YEAR(Projects!$C$3))*12+MONTH(B32)-MONTH(Projects!$C$3)+1)),0)) | G32: =IF(A32="","",IF(AND(((YEAR(B32)-YEAR(Projects!$C$3))*12+MONTH(B32)-MONTH(Projects!$C$3)+1)>=1,((YEAR(B32)-YEAR(Projects!$C$3))*12+MONTH(B32)-MONTH(Projects!$C$3)+1)<=36),INDEX('Phased Budget'!$H$6:$AQ$55,$K$1,((YEAR(B32)-YEAR(Projects!$C$3))*12+MONTH(B32)-MONTH(Projects!$C$3)+1)),0)) | H32: =IF(A32="","",F32+G32) | I32: =IF(A32="","",IF(B32<=Projects!$C$2,"Actual","Forecast"))
A33: =IF(AND($K$1>0,17<=N($B$7)),17,"") | B33: =IF(A33="","",EDATE($B$6,A33-1)) | C33: =IF(A33="","",IF(INDEX(Phasing!$D$6:$D$55,$K$1)=0,1,N(INDEX(Phasing!$I$6:$AF$55,$K$1,A33)))) | D33: =IF(A33="","",N(INDEX(Phasing!$AH$6:$BE$55,$K$1,A33))) | E33: =IF(A33="","",D33*N($B$9)) | F33: =IF(A33="","",IF(AND(AND(((YEAR(B33)-YEAR(Projects!$C$3))*12+MONTH(B33)-MONTH(Projects!$C$3)+1)>=1,((YEAR(B33)-YEAR(Projects!$C$3))*12+MONTH(B33)-MONTH(Projects!$C$3)+1)<=36),B33<=Projects!$C$2),INDEX('WIP Log'!$D$6:$AM$55,$K$1,((YEAR(B33)-YEAR(Projects!$C$3))*12+MONTH(B33)-MONTH(Projects!$C$3)+1)),0)) | G33: =IF(A33="","",IF(AND(((YEAR(B33)-YEAR(Projects!$C$3))*12+MONTH(B33)-MONTH(Projects!$C$3)+1)>=1,((YEAR(B33)-YEAR(Projects!$C$3))*12+MONTH(B33)-MONTH(Projects!$C$3)+1)<=36),INDEX('Phased Budget'!$H$6:$AQ$55,$K$1,((YEAR(B33)-YEAR(Projects!$C$3))*12+MONTH(B33)-MONTH(Projects!$C$3)+1)),0)) | H33: =IF(A33="","",F33+G33) | I33: =IF(A33="","",IF(B33<=Projects!$C$2,"Actual","Forecast"))
A34: =IF(AND($K$1>0,18<=N($B$7)),18,"") | B34: =IF(A34="","",EDATE($B$6,A34-1)) | C34: =IF(A34="","",IF(INDEX(Phasing!$D$6:$D$55,$K$1)=0,1,N(INDEX(Phasing!$I$6:$AF$55,$K$1,A34)))) | D34: =IF(A34="","",N(INDEX(Phasing!$AH$6:$BE$55,$K$1,A34))) | E34: =IF(A34="","",D34*N($B$9)) | F34: =IF(A34="","",IF(AND(AND(((YEAR(B34)-YEAR(Projects!$C$3))*12+MONTH(B34)-MONTH(Projects!$C$3)+1)>=1,((YEAR(B34)-YEAR(Projects!$C$3))*12+MONTH(B34)-MONTH(Projects!$C$3)+1)<=36),B34<=Projects!$C$2),INDEX('WIP Log'!$D$6:$AM$55,$K$1,((YEAR(B34)-YEAR(Projects!$C$3))*12+MONTH(B34)-MONTH(Projects!$C$3)+1)),0)) | G34: =IF(A34="","",IF(AND(((YEAR(B34)-YEAR(Projects!$C$3))*12+MONTH(B34)-MONTH(Projects!$C$3)+1)>=1,((YEAR(B34)-YEAR(Projects!$C$3))*12+MONTH(B34)-MONTH(Projects!$C$3)+1)<=36),INDEX('Phased Budget'!$H$6:$AQ$55,$K$1,((YEAR(B34)-YEAR(Projects!$C$3))*12+MONTH(B34)-MONTH(Projects!$C$3)+1)),0)) | H34: =IF(A34="","",F34+G34) | I34: =IF(A34="","",IF(B34<=Projects!$C$2,"Actual","Forecast"))
A35: =IF(AND($K$1>0,19<=N($B$7)),19,"") | B35: =IF(A35="","",EDATE($B$6,A35-1)) | C35: =IF(A35="","",IF(INDEX(Phasing!$D$6:$D$55,$K$1)=0,1,N(INDEX(Phasing!$I$6:$AF$55,$K$1,A35)))) | D35: =IF(A35="","",N(INDEX(Phasing!$AH$6:$BE$55,$K$1,A35))) | E35: =IF(A35="","",D35*N($B$9)) | F35: =IF(A35="","",IF(AND(AND(((YEAR(B35)-YEAR(Projects!$C$3))*12+MONTH(B35)-MONTH(Projects!$C$3)+1)>=1,((YEAR(B35)-YEAR(Projects!$C$3))*12+MONTH(B35)-MONTH(Projects!$C$3)+1)<=36),B35<=Projects!$C$2),INDEX('WIP Log'!$D$6:$AM$55,$K$1,((YEAR(B35)-YEAR(Projects!$C$3))*12+MONTH(B35)-MONTH(Projects!$C$3)+1)),0)) | G35: =IF(A35="","",IF(AND(((YEAR(B35)-YEAR(Projects!$C$3))*12+MONTH(B35)-MONTH(Projects!$C$3)+1)>=1,((YEAR(B35)-YEAR(Projects!$C$3))*12+MONTH(B35)-MONTH(Projects!$C$3)+1)<=36),INDEX('Phased Budget'!$H$6:$AQ$55,$K$1,((YEAR(B35)-YEAR(Projects!$C$3))*12+MONTH(B35)-MONTH(Projects!$C$3)+1)),0)) | H35: =IF(A35="","",F35+G35) | I35: =IF(A35="","",IF(B35<=Projects!$C$2,"Actual","Forecast"))
A36: =IF(AND($K$1>0,20<=N($B$7)),20,"") | B36: =IF(A36="","",EDATE($B$6,A36-1)) | C36: =IF(A36="","",IF(INDEX(Phasing!$D$6:$D$55,$K$1)=0,1,N(INDEX(Phasing!$I$6:$AF$55,$K$1,A36)))) | D36: =IF(A36="","",N(INDEX(Phasing!$AH$6:$BE$55,$K$1,A36))) | E36: =IF(A36="","",D36*N($B$9)) | F36: =IF(A36="","",IF(AND(AND(((YEAR(B36)-YEAR(Projects!$C$3))*12+MONTH(B36)-MONTH(Projects!$C$3)+1)>=1,((YEAR(B36)-YEAR(Projects!$C$3))*12+MONTH(B36)-MONTH(Projects!$C$3)+1)<=36),B36<=Projects!$C$2),INDEX('WIP Log'!$D$6:$AM$55,$K$1,((YEAR(B36)-YEAR(Projects!$C$3))*12+MONTH(B36)-MONTH(Projects!$C$3)+1)),0)) | G36: =IF(A36="","",IF(AND(((YEAR(B36)-YEAR(Projects!$C$3))*12+MONTH(B36)-MONTH(Projects!$C$3)+1)>=1,((YEAR(B36)-YEAR(Projects!$C$3))*12+MONTH(B36)-MONTH(Projects!$C$3)+1)<=36),INDEX('Phased Budget'!$H$6:$AQ$55,$K$1,((YEAR(B36)-YEAR(Projects!$C$3))*12+MONTH(B36)-MONTH(Projects!$C$3)+1)),0)) | H36: =IF(A36="","",F36+G36) | I36: =IF(A36="","",IF(B36<=Projects!$C$2,"Actual","Forecast"))
A37: =IF(AND($K$1>0,21<=N($B$7)),21,"") | B37: =IF(A37="","",EDATE($B$6,A37-1)) | C37: =IF(A37="","",IF(INDEX(Phasing!$D$6:$D$55,$K$1)=0,1,N(INDEX(Phasing!$I$6:$AF$55,$K$1,A37)))) | D37: =IF(A37="","",N(INDEX(Phasing!$AH$6:$BE$55,$K$1,A37))) | E37: =IF(A37="","",D37*N($B$9)) | F37: =IF(A37="","",IF(AND(AND(((YEAR(B37)-YEAR(Projects!$C$3))*12+MONTH(B37)-MONTH(Projects!$C$3)+1)>=1,((YEAR(B37)-YEAR(Projects!$C$3))*12+MONTH(B37)-MONTH(Projects!$C$3)+1)<=36),B37<=Projects!$C$2),INDEX('WIP Log'!$D$6:$AM$55,$K$1,((YEAR(B37)-YEAR(Projects!$C$3))*12+MONTH(B37)-MONTH(Projects!$C$3)+1)),0)) | G37: =IF(A37="","",IF(AND(((YEAR(B37)-YEAR(Projects!$C$3))*12+MONTH(B37)-MONTH(Projects!$C$3)+1)>=1,((YEAR(B37)-YEAR(Projects!$C$3))*12+MONTH(B37)-MONTH(Projects!$C$3)+1)<=36),INDEX('Phased Budget'!$H$6:$AQ$55,$K$1,((YEAR(B37)-YEAR(Projects!$C$3))*12+MONTH(B37)-MONTH(Projects!$C$3)+1)),0)) | H37: =IF(A37="","",F37+G37) | I37: =IF(A37="","",IF(B37<=Projects!$C$2,"Actual","Forecast"))
A38: =IF(AND($K$1>0,22<=N($B$7)),22,"") | B38: =IF(A38="","",EDATE($B$6,A38-1)) | C38: =IF(A38="","",IF(INDEX(Phasing!$D$6:$D$55,$K$1)=0,1,N(INDEX(Phasing!$I$6:$AF$55,$K$1,A38)))) | D38: =IF(A38="","",N(INDEX(Phasing!$AH$6:$BE$55,$K$1,A38))) | E38: =IF(A38="","",D38*N($B$9)) | F38: =IF(A38="","",IF(AND(AND(((YEAR(B38)-YEAR(Projects!$C$3))*12+MONTH(B38)-MONTH(Projects!$C$3)+1)>=1,((YEAR(B38)-YEAR(Projects!$C$3))*12+MONTH(B38)-MONTH(Projects!$C$3)+1)<=36),B38<=Projects!$C$2),INDEX('WIP Log'!$D$6:$AM$55,$K$1,((YEAR(B38)-YEAR(Projects!$C$3))*12+MONTH(B38)-MONTH(Projects!$C$3)+1)),0)) | G38: =IF(A38="","",IF(AND(((YEAR(B38)-YEAR(Projects!$C$3))*12+MONTH(B38)-MONTH(Projects!$C$3)+1)>=1,((YEAR(B38)-YEAR(Projects!$C$3))*12+MONTH(B38)-MONTH(Projects!$C$3)+1)<=36),INDEX('Phased Budget'!$H$6:$AQ$55,$K$1,((YEAR(B38)-YEAR(Projects!$C$3))*12+MONTH(B38)-MONTH(Projects!$C$3)+1)),0)) | H38: =IF(A38="","",F38+G38) | I38: =IF(A38="","",IF(B38<=Projects!$C$2,"Actual","Forecast"))
A39: =IF(AND($K$1>0,23<=N($B$7)),23,"") | B39: =IF(A39="","",EDATE($B$6,A39-1)) | C39: =IF(A39="","",IF(INDEX(Phasing!$D$6:$D$55,$K$1)=0,1,N(INDEX(Phasing!$I$6:$AF$55,$K$1,A39)))) | D39: =IF(A39="","",N(INDEX(Phasing!$AH$6:$BE$55,$K$1,A39))) | E39: =IF(A39="","",D39*N($B$9)) | F39: =IF(A39="","",IF(AND(AND(((YEAR(B39)-YEAR(Projects!$C$3))*12+MONTH(B39)-MONTH(Projects!$C$3)+1)>=1,((YEAR(B39)-YEAR(Projects!$C$3))*12+MONTH(B39)-MONTH(Projects!$C$3)+1)<=36),B39<=Projects!$C$2),INDEX('WIP Log'!$D$6:$AM$55,$K$1,((YEAR(B39)-YEAR(Projects!$C$3))*12+MONTH(B39)-MONTH(Projects!$C$3)+1)),0)) | G39: =IF(A39="","",IF(AND(((YEAR(B39)-YEAR(Projects!$C$3))*12+MONTH(B39)-MONTH(Projects!$C$3)+1)>=1,((YEAR(B39)-YEAR(Projects!$C$3))*12+MONTH(B39)-MONTH(Projects!$C$3)+1)<=36),INDEX('Phased Budget'!$H$6:$AQ$55,$K$1,((YEAR(B39)-YEAR(Projects!$C$3))*12+MONTH(B39)-MONTH(Projects!$C$3)+1)),0)) | H39: =IF(A39="","",F39+G39) | I39: =IF(A39="","",IF(B39<=Projects!$C$2,"Actual","Forecast"))
A40: =IF(AND($K$1>0,24<=N($B$7)),24,"") | B40: =IF(A40="","",EDATE($B$6,A40-1)) | C40: =IF(A40="","",IF(INDEX(Phasing!$D$6:$D$55,$K$1)=0,1,N(INDEX(Phasing!$I$6:$AF$55,$K$1,A40)))) | D40: =IF(A40="","",N(INDEX(Phasing!$AH$6:$BE$55,$K$1,A40))) | E40: =IF(A40="","",D40*N($B$9)) | F40: =IF(A40="","",IF(AND(AND(((YEAR(B40)-YEAR(Projects!$C$3))*12+MONTH(B40)-MONTH(Projects!$C$3)+1)>=1,((YEAR(B40)-YEAR(Projects!$C$3))*12+MONTH(B40)-MONTH(Projects!$C$3)+1)<=36),B40<=Projects!$C$2),INDEX('WIP Log'!$D$6:$AM$55,$K$1,((YEAR(B40)-YEAR(Projects!$C$3))*12+MONTH(B40)-MONTH(Projects!$C$3)+1)),0)) | G40: =IF(A40="","",IF(AND(((YEAR(B40)-YEAR(Projects!$C$3))*12+MONTH(B40)-MONTH(Projects!$C$3)+1)>=1,((YEAR(B40)-YEAR(Projects!$C$3))*12+MONTH(B40)-MONTH(Projects!$C$3)+1)<=36),INDEX('Phased Budget'!$H$6:$AQ$55,$K$1,((YEAR(B40)-YEAR(Projects!$C$3))*12+MONTH(B40)-MONTH(Projects!$C$3)+1)),0)) | H40: =IF(A40="","",F40+G40) | I40: =IF(A40="","",IF(B40<=Projects!$C$2,"Actual","Forecast"))
A41: TOTAL | D41: =SUM(D17:D40) -> 1 | E41: =SUM(E17:E40) -> 10000 | F41: =SUM(F17:F40) -> 1000 | G41: =SUM(G17:G40) -> 9000 | H41: =SUM(H17:H40) -> 10000
A42: Check: Total = Contract | H42: =IF($K$1=0,"",IF(ABS(H41-N(B9))<0.005,"✓ ties","✗ diff "&TEXT(H41-N(B9),"#,##0"))) -> ✓ ties

Sheet Timeline
A1: Project Timeline
A3: Dark orange = WIP actual (≤ Current Month). Light orange = Phased Budgeted. The bordered column is the Current Month.
A5: # | B5: Project Name | C5: Engagement Manager | D5: Start | E5: End | F5: ='WIP Log'!D5 -> 46023 | G5: ='WIP Log'!E5 -> 46054 | H5: ='WIP Log'!F5 -> 46082 | I5: ='WIP Log'!G5 -> 46113 | J5: ='WIP Log'!H5 -> 46143 | K5: ='WIP Log'!I5 -> 46174 | L5: ='WIP Log'!J5 -> 46204 | M5: ='WIP Log'!K5 -> 46235 | ... AO5: ='WIP Log'!AM5 -> 47088
A6: 1 | B6: =IF(Projects!B6="","",Projects!B6) -> Example Project (slide) | C6: =IF(Projects!C6="","",Projects!C6) -> J. Doe | D6: =IF(Projects!D6="","",Projects!D6) -> 46296 | E6: =IF(Projects!F6="","",Projects!F6) -> 46419 | F6: =IF($B6="","",IF(F$5<=Projects!$C$2,IF(OR(IF($D6="",FALSE(),AND(F$5>=DATE(YEAR($D6),MONTH($D6),1),F$5<=$E6)),N('WIP Log'!D6)<>0),N('WIP Log'!D6),""),IF(IF($D6="",FALSE(),AND(F$5>=DATE(YEAR($D6),MONTH($D6),1),F$5<=$E6)),'Phased Budget'!H6,""))) | G6: =IF($B6="","",IF(G$5<=Projects!$C$2,IF(OR(IF($D6="",FALSE(),AND(G$5>=DATE(YEAR($D6),MONTH($D6),1),G$5<=$E6)),N('WIP Log'!E6)<>0),N('WIP Log'!E6),""),IF(IF($D6="",FALSE(),AND(G$5>=DATE(YEAR($D6),MONTH($D6),1),G$5<=$E6)),'Phased Budget'!I6,""))) | H6: =IF($B6="","",IF(H$5<=Projects!$C$2,IF(OR(IF($D6="",FALSE(),AND(H$5>=DATE(YEAR($D6),MONTH($D6),1),H$5<=$E6)),N('WIP Log'!F6)<>0),N('WIP Log'!F6),""),IF(IF($D6="",FALSE(),AND(H$5>=DATE(YEAR($D6),MONTH($D6),1),H$5<=$E6)),'Phased Budget'!J6,""))) | I6: =IF($B6="","",IF(I$5<=Projects!$C$2,IF(OR(IF($D6="",FALSE(),AND(I$5>=DATE(YEAR($D6),MONTH($D6),1),I$5<=$E6)),N('WIP Log'!G6)<>0),N('WIP Log'!G6),""),IF(IF($D6="",FALSE(),AND(I$5>=DATE(YEAR($D6),MONTH($D6),1),I$5<=$E6)),'Phased Budget'!K6,""))) | J6: =IF($B6="","",IF(J$5<=Projects!$C$2,IF(OR(IF($D6="",FALSE(),AND(J$5>=DATE(YEAR($D6),MONTH($D6),1),J$5<=$E6)),N('WIP Log'!H6)<>0),N('WIP Log'!H6),""),IF(IF($D6="",FALSE(),AND(J$5>=DATE(YEAR($D6),MONTH($D6),1),J$5<=$E6)),'Phased Budget'!L6,""))) | K6: =IF($B6="","",IF(K$5<=Projects!$C$2,IF(OR(IF($D6="",FALSE(),AND(K$5>=DATE(YEAR($D6),MONTH($D6),1),K$5<=$E6)),N('WIP Log'!I6)<>0),N('WIP Log'!I6),""),IF(IF($D6="",FALSE(),AND(K$5>=DATE(YEAR($D6),MONTH($D6),1),K$5<=$E6)),'Phased Budget'!M6,""))) | L6: =IF($B6="","",IF(L$5<=Projects!$C$2,IF(OR(IF($D6="",FALSE(),AND(L$5>=DATE(YEAR($D6),MONTH($D6),1),L$5<=$E6)),N('WIP Log'!J6)<>0),N('WIP Log'!J6),""),IF(IF($D6="",FALSE(),AND(L$5>=DATE(YEAR($D6),MONTH($D6),1),L$5<=$E6)),'Phased Budget'!N6,""))) | M6: =IF($B6="","",IF(M$5<=Projects!$C$2,IF(OR(IF($D6="",FALSE(),AND(M$5>=DATE(YEAR($D6),MONTH($D6),1),M$5<=$E6)),N('WIP Log'!K6)<>0),N('WIP Log'!K6),""),IF(IF($D6="",FALSE(),AND(M$5>=DATE(YEAR($D6),MONTH($D6),1),M$5<=$E6)),'Phased Budget'!O6,""))) | ... AO6: =IF($B6="","",IF(AO$5<=Projects!$C$2,IF(OR(IF($D6="",FALSE(),AND(AO$5>=DATE(YEAR($D6),MONTH($D6),1),AO$5<=$E6)),N('WIP Log'!AM6)<>0),N('WIP Log'!AM6),""),IF(IF($D6="",FALSE(),AND(AO$5>=DATE(YEAR($D6),MONTH($D6),1),AO$5<=$E6)),'Phased Budget'!AQ6,"")))
A7: 2 | B7: =IF(Projects!B7="","",Projects!B7) | C7: =IF(Projects!C7="","",Projects!C7) | D7: =IF(Projects!D7="","",Projects!D7) | E7: =IF(Projects!F7="","",Projects!F7) | F7: =IF($B7="","",IF(F$5<=Projects!$C$2,IF(OR(IF($D7="",FALSE(),AND(F$5>=DATE(YEAR($D7),MONTH($D7),1),F$5<=$E7)),N('WIP Log'!D7)<>0),N('WIP Log'!D7),""),IF(IF($D7="",FALSE(),AND(F$5>=DATE(YEAR($D7),MONTH($D7),1),F$5<=$E7)),'Phased Budget'!H7,""))) | G7: =IF($B7="","",IF(G$5<=Projects!$C$2,IF(OR(IF($D7="",FALSE(),AND(G$5>=DATE(YEAR($D7),MONTH($D7),1),G$5<=$E7)),N('WIP Log'!E7)<>0),N('WIP Log'!E7),""),IF(IF($D7="",FALSE(),AND(G$5>=DATE(YEAR($D7),MONTH($D7),1),G$5<=$E7)),'Phased Budget'!I7,""))) | H7: =IF($B7="","",IF(H$5<=Projects!$C$2,IF(OR(IF($D7="",FALSE(),AND(H$5>=DATE(YEAR($D7),MONTH($D7),1),H$5<=$E7)),N('WIP Log'!F7)<>0),N('WIP Log'!F7),""),IF(IF($D7="",FALSE(),AND(H$5>=DATE(YEAR($D7),MONTH($D7),1),H$5<=$E7)),'Phased Budget'!J7,""))) | I7: =IF($B7="","",IF(I$5<=Projects!$C$2,IF(OR(IF($D7="",FALSE(),AND(I$5>=DATE(YEAR($D7),MONTH($D7),1),I$5<=$E7)),N('WIP Log'!G7)<>0),N('WIP Log'!G7),""),IF(IF($D7="",FALSE(),AND(I$5>=DATE(YEAR($D7),MONTH($D7),1),I$5<=$E7)),'Phased Budget'!K7,""))) | J7: =IF($B7="","",IF(J$5<=Projects!$C$2,IF(OR(IF($D7="",FALSE(),AND(J$5>=DATE(YEAR($D7),MONTH($D7),1),J$5<=$E7)),N('WIP Log'!H7)<>0),N('WIP Log'!H7),""),IF(IF($D7="",FALSE(),AND(J$5>=DATE(YEAR($D7),MONTH($D7),1),J$5<=$E7)),'Phased Budget'!L7,""))) | K7: =IF($B7="","",IF(K$5<=Projects!$C$2,IF(OR(IF($D7="",FALSE(),AND(K$5>=DATE(YEAR($D7),MONTH($D7),1),K$5<=$E7)),N('WIP Log'!I7)<>0),N('WIP Log'!I7),""),IF(IF($D7="",FALSE(),AND(K$5>=DATE(YEAR($D7),MONTH($D7),1),K$5<=$E7)),'Phased Budget'!M7,""))) | L7: =IF($B7="","",IF(L$5<=Projects!$C$2,IF(OR(IF($D7="",FALSE(),AND(L$5>=DATE(YEAR($D7),MONTH($D7),1),L$5<=$E7)),N('WIP Log'!J7)<>0),N('WIP Log'!J7),""),IF(IF($D7="",FALSE(),AND(L$5>=DATE(YEAR($D7),MONTH($D7),1),L$5<=$E7)),'Phased Budget'!N7,""))) | M7: =IF($B7="","",IF(M$5<=Projects!$C$2,IF(OR(IF($D7="",FALSE(),AND(M$5>=DATE(YEAR($D7),MONTH($D7),1),M$5<=$E7)),N('WIP Log'!K7)<>0),N('WIP Log'!K7),""),IF(IF($D7="",FALSE(),AND(M$5>=DATE(YEAR($D7),MONTH($D7),1),M$5<=$E7)),'Phased Budget'!O7,""))) | ... AO7: =IF($B7="","",IF(AO$5<=Projects!$C$2,IF(OR(IF($D7="",FALSE(),AND(AO$5>=DATE(YEAR($D7),MONTH($D7),1),AO$5<=$E7)),N('WIP Log'!AM7)<>0),N('WIP Log'!AM7),""),IF(IF($D7="",FALSE(),AND(AO$5>=DATE(YEAR($D7),MONTH($D7),1),AO$5<=$E7)),'Phased Budget'!AQ7,"")))
A8: 3 | B8: =IF(Projects!B8="","",Projects!B8) | C8: =IF(Projects!C8="","",Projects!C8) | D8: =IF(Projects!D8="","",Projects!D8) | E8: =IF(Projects!F8="","",Projects!F8) | F8: =IF($B8="","",IF(F$5<=Projects!$C$2,IF(OR(IF($D8="",FALSE(),AND(F$5>=DATE(YEAR($D8),MONTH($D8),1),F$5<=$E8)),N('WIP Log'!D8)<>0),N('WIP Log'!D8),""),IF(IF($D8="",FALSE(),AND(F$5>=DATE(YEAR($D8),MONTH($D8),1),F$5<=$E8)),'Phased Budget'!H8,""))) | G8: =IF($B8="","",IF(G$5<=Projects!$C$2,IF(OR(IF($D8="",FALSE(),AND(G$5>=DATE(YEAR($D8),MONTH($D8),1),G$5<=$E8)),N('WIP Log'!E8)<>0),N('WIP Log'!E8),""),IF(IF($D8="",FALSE(),AND(G$5>=DATE(YEAR($D8),MONTH($D8),1),G$5<=$E8)),'Phased Budget'!I8,""))) | H8: =IF($B8="","",IF(H$5<=Projects!$C$2,IF(OR(IF($D8="",FALSE(),AND(H$5>=DATE(YEAR($D8),MONTH($D8),1),H$5<=$E8)),N('WIP Log'!F8)<>0),N('WIP Log'!F8),""),IF(IF($D8="",FALSE(),AND(H$5>=DATE(YEAR($D8),MONTH($D8),1),H$5<=$E8)),'Phased Budget'!J8,""))) | I8: =IF($B8="","",IF(I$5<=Projects!$C$2,IF(OR(IF($D8="",FALSE(),AND(I$5>=DATE(YEAR($D8),MONTH($D8),1),I$5<=$E8)),N('WIP Log'!G8)<>0),N('WIP Log'!G8),""),IF(IF($D8="",FALSE(),AND(I$5>=DATE(YEAR($D8),MONTH($D8),1),I$5<=$E8)),'Phased Budget'!K8,""))) | J8: =IF($B8="","",IF(J$5<=Projects!$C$2,IF(OR(IF($D8="",FALSE(),AND(J$5>=DATE(YEAR($D8),MONTH($D8),1),J$5<=$E8)),N('WIP Log'!H8)<>0),N('WIP Log'!H8),""),IF(IF($D8="",FALSE(),AND(J$5>=DATE(YEAR($D8),MONTH($D8),1),J$5<=$E8)),'Phased Budget'!L8,""))) | K8: =IF($B8="","",IF(K$5<=Projects!$C$2,IF(OR(IF($D8="",FALSE(),AND(K$5>=DATE(YEAR($D8),MONTH($D8),1),K$5<=$E8)),N('WIP Log'!I8)<>0),N('WIP Log'!I8),""),IF(IF($D8="",FALSE(),AND(K$5>=DATE(YEAR($D8),MONTH($D8),1),K$5<=$E8)),'Phased Budget'!M8,""))) | L8: =IF($B8="","",IF(L$5<=Projects!$C$2,IF(OR(IF($D8="",FALSE(),AND(L$5>=DATE(YEAR($D8),MONTH($D8),1),L$5<=$E8)),N('WIP Log'!J8)<>0),N('WIP Log'!J8),""),IF(IF($D8="",FALSE(),AND(L$5>=DATE(YEAR($D8),MONTH($D8),1),L$5<=$E8)),'Phased Budget'!N8,""))) | M8: =IF($B8="","",IF(M$5<=Projects!$C$2,IF(OR(IF($D8="",FALSE(),AND(M$5>=DATE(YEAR($D8),MONTH($D8),1),M$5<=$E8)),N('WIP Log'!K8)<>0),N('WIP Log'!K8),""),IF(IF($D8="",FALSE(),AND(M$5>=DATE(YEAR($D8),MONTH($D8),1),M$5<=$E8)),'Phased Budget'!O8,""))) | ... AO8: =IF($B8="","",IF(AO$5<=Projects!$C$2,IF(OR(IF($D8="",FALSE(),AND(AO$5>=DATE(YEAR($D8),MONTH($D8),1),AO$5<=$E8)),N('WIP Log'!AM8)<>0),N('WIP Log'!AM8),""),IF(IF($D8="",FALSE(),AND(AO$5>=DATE(YEAR($D8),MONTH($D8),1),AO$5<=$E8)),'Phased Budget'!AQ8,"")))
A9: 4 | B9: =IF(Projects!B9="","",Projects!B9) | C9: =IF(Projects!C9="","",Projects!C9) | D9: =IF(Projects!D9="","",Projects!D9) | E9: =IF(Projects!F9="","",Projects!F9) | F9: =IF($B9="","",IF(F$5<=Projects!$C$2,IF(OR(IF($D9="",FALSE(),AND(F$5>=DATE(YEAR($D9),MONTH($D9),1),F$5<=$E9)),N('WIP Log'!D9)<>0),N('WIP Log'!D9),""),IF(IF($D9="",FALSE(),AND(F$5>=DATE(YEAR($D9),MONTH($D9),1),F$5<=$E9)),'Phased Budget'!H9,""))) | G9: =IF($B9="","",IF(G$5<=Projects!$C$2,IF(OR(IF($D9="",FALSE(),AND(G$5>=DATE(YEAR($D9),MONTH($D9),1),G$5<=$E9)),N('WIP Log'!E9)<>0),N('WIP Log'!E9),""),IF(IF($D9="",FALSE(),AND(G$5>=DATE(YEAR($D9),MONTH($D9),1),G$5<=$E9)),'Phased Budget'!I9,""))) | H9: =IF($B9="","",IF(H$5<=Projects!$C$2,IF(OR(IF($D9="",FALSE(),AND(H$5>=DATE(YEAR($D9),MONTH($D9),1),H$5<=$E9)),N('WIP Log'!F9)<>0),N('WIP Log'!F9),""),IF(IF($D9="",FALSE(),AND(H$5>=DATE(YEAR($D9),MONTH($D9),1),H$5<=$E9)),'Phased Budget'!J9,""))) | I9: =IF($B9="","",IF(I$5<=Projects!$C$2,IF(OR(IF($D9="",FALSE(),AND(I$5>=DATE(YEAR($D9),MONTH($D9),1),I$5<=$E9)),N('WIP Log'!G9)<>0),N('WIP Log'!G9),""),IF(IF($D9="",FALSE(),AND(I$5>=DATE(YEAR($D9),MONTH($D9),1),I$5<=$E9)),'Phased Budget'!K9,""))) | J9: =IF($B9="","",IF(J$5<=Projects!$C$2,IF(OR(IF($D9="",FALSE(),AND(J$5>=DATE(YEAR($D9),MONTH($D9),1),J$5<=$E9)),N('WIP Log'!H9)<>0),N('WIP Log'!H9),""),IF(IF($D9="",FALSE(),AND(J$5>=DATE(YEAR($D9),MONTH($D9),1),J$5<=$E9)),'Phased Budget'!L9,""))) | K9: =IF($B9="","",IF(K$5<=Projects!$C$2,IF(OR(IF($D9="",FALSE(),AND(K$5>=DATE(YEAR($D9),MONTH($D9),1),K$5<=$E9)),N('WIP Log'!I9)<>0),N('WIP Log'!I9),""),IF(IF($D9="",FALSE(),AND(K$5>=DATE(YEAR($D9),MONTH($D9),1),K$5<=$E9)),'Phased Budget'!M9,""))) | L9: =IF($B9="","",IF(L$5<=Projects!$C$2,IF(OR(IF($D9="",FALSE(),AND(L$5>=DATE(YEAR($D9),MONTH($D9),1),L$5<=$E9)),N('WIP Log'!J9)<>0),N('WIP Log'!J9),""),IF(IF($D9="",FALSE(),AND(L$5>=DATE(YEAR($D9),MONTH($D9),1),L$5<=$E9)),'Phased Budget'!N9,""))) | M9: =IF($B9="","",IF(M$5<=Projects!$C$2,IF(OR(IF($D9="",FALSE(),AND(M$5>=DATE(YEAR($D9),MONTH($D9),1),M$5<=$E9)),N('WIP Log'!K9)<>0),N('WIP Log'!K9),""),IF(IF($D9="",FALSE(),AND(M$5>=DATE(YEAR($D9),MONTH($D9),1),M$5<=$E9)),'Phased Budget'!O9,""))) | ... AO9: =IF($B9="","",IF(AO$5<=Projects!$C$2,IF(OR(IF($D9="",FALSE(),AND(AO$5>=DATE(YEAR($D9),MONTH($D9),1),AO$5<=$E9)),N('WIP Log'!AM9)<>0),N('WIP Log'!AM9),""),IF(IF($D9="",FALSE(),AND(AO$5>=DATE(YEAR($D9),MONTH($D9),1),AO$5<=$E9)),'Phased Budget'!AQ9,"")))
A10: 5 | B10: =IF(Projects!B10="","",Projects!B10) | C10: =IF(Projects!C10="","",Projects!C10) | D10: =IF(Projects!D10="","",Projects!D10) | E10: =IF(Projects!F10="","",Projects!F10) | F10: =IF($B10="","",IF(F$5<=Projects!$C$2,IF(OR(IF($D10="",FALSE(),AND(F$5>=DATE(YEAR($D10),MONTH($D10),1),F$5<=$E10)),N('WIP Log'!D10)<>0),N('WIP Log'!D10),""),IF(IF($D10="",FALSE(),AND(F$5>=DATE(YEAR($D10),MONTH($D10),1),F$5<=$E10)),'Phased Budget'!H10,""))) | G10: =IF($B10="","",IF(G$5<=Projects!$C$2,IF(OR(IF($D10="",FALSE(),AND(G$5>=DATE(YEAR($D10),MONTH($D10),1),G$5<=$E10)),N('WIP Log'!E10)<>0),N('WIP Log'!E10),""),IF(IF($D10="",FALSE(),AND(G$5>=DATE(YEAR($D10),MONTH($D10),1),G$5<=$E10)),'Phased Budget'!I10,""))) | H10: =IF($B10="","",IF(H$5<=Projects!$C$2,IF(OR(IF($D10="",FALSE(),AND(H$5>=DATE(YEAR($D10),MONTH($D10),1),H$5<=$E10)),N('WIP Log'!F10)<>0),N('WIP Log'!F10),""),IF(IF($D10="",FALSE(),AND(H$5>=DATE(YEAR($D10),MONTH($D10),1),H$5<=$E10)),'Phased Budget'!J10,""))) | I10: =IF($B10="","",IF(I$5<=Projects!$C$2,IF(OR(IF($D10="",FALSE(),AND(I$5>=DATE(YEAR($D10),MONTH($D10),1),I$5<=$E10)),N('WIP Log'!G10)<>0),N('WIP Log'!G10),""),IF(IF($D10="",FALSE(),AND(I$5>=DATE(YEAR($D10),MONTH($D10),1),I$5<=$E10)),'Phased Budget'!K10,""))) | J10: =IF($B10="","",IF(J$5<=Projects!$C$2,IF(OR(IF($D10="",FALSE(),AND(J$5>=DATE(YEAR($D10),MONTH($D10),1),J$5<=$E10)),N('WIP Log'!H10)<>0),N('WIP Log'!H10),""),IF(IF($D10="",FALSE(),AND(J$5>=DATE(YEAR($D10),MONTH($D10),1),J$5<=$E10)),'Phased Budget'!L10,""))) | K10: =IF($B10="","",IF(K$5<=Projects!$C$2,IF(OR(IF($D10="",FALSE(),AND(K$5>=DATE(YEAR($D10),MONTH($D10),1),K$5<=$E10)),N('WIP Log'!I10)<>0),N('WIP Log'!I10),""),IF(IF($D10="",FALSE(),AND(K$5>=DATE(YEAR($D10),MONTH($D10),1),K$5<=$E10)),'Phased Budget'!M10,""))) | L10: =IF($B10="","",IF(L$5<=Projects!$C$2,IF(OR(IF($D10="",FALSE(),AND(L$5>=DATE(YEAR($D10),MONTH($D10),1),L$5<=$E10)),N('WIP Log'!J10)<>0),N('WIP Log'!J10),""),IF(IF($D10="",FALSE(),AND(L$5>=DATE(YEAR($D10),MONTH($D10),1),L$5<=$E10)),'Phased Budget'!N10,""))) | M10: =IF($B10="","",IF(M$5<=Projects!$C$2,IF(OR(IF($D10="",FALSE(),AND(M$5>=DATE(YEAR($D10),MONTH($D10),1),M$5<=$E10)),N('WIP Log'!K10)<>0),N('WIP Log'!K10),""),IF(IF($D10="",FALSE(),AND(M$5>=DATE(YEAR($D10),MONTH($D10),1),M$5<=$E10)),'Phased Budget'!O10,""))) | ... AO10: =IF($B10="","",IF(AO$5<=Projects!$C$2,IF(OR(IF($D10="",FALSE(),AND(AO$5>=DATE(YEAR($D10),MONTH($D10),1),AO$5<=$E10)),N('WIP Log'!AM10)<>0),N('WIP Log'!AM10),""),IF(IF($D10="",FALSE(),AND(AO$5>=DATE(YEAR($D10),MONTH($D10),1),AO$5<=$E10)),'Phased Budget'!AQ10,"")))
A11: 6 | B11: =IF(Projects!B11="","",Projects!B11) | C11: =IF(Projects!C11="","",Projects!C11) | D11: =IF(Projects!D11="","",Projects!D11) | E11: =IF(Projects!F11="","",Projects!F11) | F11: =IF($B11="","",IF(F$5<=Projects!$C$2,IF(OR(IF($D11="",FALSE(),AND(F$5>=DATE(YEAR($D11),MONTH($D11),1),F$5<=$E11)),N('WIP Log'!D11)<>0),N('WIP Log'!D11),""),IF(IF($D11="",FALSE(),AND(F$5>=DATE(YEAR($D11),MONTH($D11),1),F$5<=$E11)),'Phased Budget'!H11,""))) | G11: =IF($B11="","",IF(G$5<=Projects!$C$2,IF(OR(IF($D11="",FALSE(),AND(G$5>=DATE(YEAR($D11),MONTH($D11),1),G$5<=$E11)),N('WIP Log'!E11)<>0),N('WIP Log'!E11),""),IF(IF($D11="",FALSE(),AND(G$5>=DATE(YEAR($D11),MONTH($D11),1),G$5<=$E11)),'Phased Budget'!I11,""))) | H11: =IF($B11="","",IF(H$5<=Projects!$C$2,IF(OR(IF($D11="",FALSE(),AND(H$5>=DATE(YEAR($D11),MONTH($D11),1),H$5<=$E11)),N('WIP Log'!F11)<>0),N('WIP Log'!F11),""),IF(IF($D11="",FALSE(),AND(H$5>=DATE(YEAR($D11),MONTH($D11),1),H$5<=$E11)),'Phased Budget'!J11,""))) | I11: =IF($B11="","",IF(I$5<=Projects!$C$2,IF(OR(IF($D11="",FALSE(),AND(I$5>=DATE(YEAR($D11),MONTH($D11),1),I$5<=$E11)),N('WIP Log'!G11)<>0),N('WIP Log'!G11),""),IF(IF($D11="",FALSE(),AND(I$5>=DATE(YEAR($D11),MONTH($D11),1),I$5<=$E11)),'Phased Budget'!K11,""))) | J11: =IF($B11="","",IF(J$5<=Projects!$C$2,IF(OR(IF($D11="",FALSE(),AND(J$5>=DATE(YEAR($D11),MONTH($D11),1),J$5<=$E11)),N('WIP Log'!H11)<>0),N('WIP Log'!H11),""),IF(IF($D11="",FALSE(),AND(J$5>=DATE(YEAR($D11),MONTH($D11),1),J$5<=$E11)),'Phased Budget'!L11,""))) | K11: =IF($B11="","",IF(K$5<=Projects!$C$2,IF(OR(IF($D11="",FALSE(),AND(K$5>=DATE(YEAR($D11),MONTH($D11),1),K$5<=$E11)),N('WIP Log'!I11)<>0),N('WIP Log'!I11),""),IF(IF($D11="",FALSE(),AND(K$5>=DATE(YEAR($D11),MONTH($D11),1),K$5<=$E11)),'Phased Budget'!M11,""))) | L11: =IF($B11="","",IF(L$5<=Projects!$C$2,IF(OR(IF($D11="",FALSE(),AND(L$5>=DATE(YEAR($D11),MONTH($D11),1),L$5<=$E11)),N('WIP Log'!J11)<>0),N('WIP Log'!J11),""),IF(IF($D11="",FALSE(),AND(L$5>=DATE(YEAR($D11),MONTH($D11),1),L$5<=$E11)),'Phased Budget'!N11,""))) | M11: =IF($B11="","",IF(M$5<=Projects!$C$2,IF(OR(IF($D11="",FALSE(),AND(M$5>=DATE(YEAR($D11),MONTH($D11),1),M$5<=$E11)),N('WIP Log'!K11)<>0),N('WIP Log'!K11),""),IF(IF($D11="",FALSE(),AND(M$5>=DATE(YEAR($D11),MONTH($D11),1),M$5<=$E11)),'Phased Budget'!O11,""))) | ... AO11: =IF($B11="","",IF(AO$5<=Projects!$C$2,IF(OR(IF($D11="",FALSE(),AND(AO$5>=DATE(YEAR($D11),MONTH($D11),1),AO$5<=$E11)),N('WIP Log'!AM11)<>0),N('WIP Log'!AM11),""),IF(IF($D11="",FALSE(),AND(AO$5>=DATE(YEAR($D11),MONTH($D11),1),AO$5<=$E11)),'Phased Budget'!AQ11,"")))
A12: 7 | B12: =IF(Projects!B12="","",Projects!B12) | C12: =IF(Projects!C12="","",Projects!C12) | D12: =IF(Projects!D12="","",Projects!D12) | E12: =IF(Projects!F12="","",Projects!F12) | F12: =IF($B12="","",IF(F$5<=Projects!$C$2,IF(OR(IF($D12="",FALSE(),AND(F$5>=DATE(YEAR($D12),MONTH($D12),1),F$5<=$E12)),N('WIP Log'!D12)<>0),N('WIP Log'!D12),""),IF(IF($D12="",FALSE(),AND(F$5>=DATE(YEAR($D12),MONTH($D12),1),F$5<=$E12)),'Phased Budget'!H12,""))) | G12: =IF($B12="","",IF(G$5<=Projects!$C$2,IF(OR(IF($D12="",FALSE(),AND(G$5>=DATE(YEAR($D12),MONTH($D12),1),G$5<=$E12)),N('WIP Log'!E12)<>0),N('WIP Log'!E12),""),IF(IF($D12="",FALSE(),AND(G$5>=DATE(YEAR($D12),MONTH($D12),1),G$5<=$E12)),'Phased Budget'!I12,""))) | H12: =IF($B12="","",IF(H$5<=Projects!$C$2,IF(OR(IF($D12="",FALSE(),AND(H$5>=DATE(YEAR($D12),MONTH($D12),1),H$5<=$E12)),N('WIP Log'!F12)<>0),N('WIP Log'!F12),""),IF(IF($D12="",FALSE(),AND(H$5>=DATE(YEAR($D12),MONTH($D12),1),H$5<=$E12)),'Phased Budget'!J12,""))) | I12: =IF($B12="","",IF(I$5<=Projects!$C$2,IF(OR(IF($D12="",FALSE(),AND(I$5>=DATE(YEAR($D12),MONTH($D12),1),I$5<=$E12)),N('WIP Log'!G12)<>0),N('WIP Log'!G12),""),IF(IF($D12="",FALSE(),AND(I$5>=DATE(YEAR($D12),MONTH($D12),1),I$5<=$E12)),'Phased Budget'!K12,""))) | J12: =IF($B12="","",IF(J$5<=Projects!$C$2,IF(OR(IF($D12="",FALSE(),AND(J$5>=DATE(YEAR($D12),MONTH($D12),1),J$5<=$E12)),N('WIP Log'!H12)<>0),N('WIP Log'!H12),""),IF(IF($D12="",FALSE(),AND(J$5>=DATE(YEAR($D12),MONTH($D12),1),J$5<=$E12)),'Phased Budget'!L12,""))) | K12: =IF($B12="","",IF(K$5<=Projects!$C$2,IF(OR(IF($D12="",FALSE(),AND(K$5>=DATE(YEAR($D12),MONTH($D12),1),K$5<=$E12)),N('WIP Log'!I12)<>0),N('WIP Log'!I12),""),IF(IF($D12="",FALSE(),AND(K$5>=DATE(YEAR($D12),MONTH($D12),1),K$5<=$E12)),'Phased Budget'!M12,""))) | L12: =IF($B12="","",IF(L$5<=Projects!$C$2,IF(OR(IF($D12="",FALSE(),AND(L$5>=DATE(YEAR($D12),MONTH($D12),1),L$5<=$E12)),N('WIP Log'!J12)<>0),N('WIP Log'!J12),""),IF(IF($D12="",FALSE(),AND(L$5>=DATE(YEAR($D12),MONTH($D12),1),L$5<=$E12)),'Phased Budget'!N12,""))) | M12: =IF($B12="","",IF(M$5<=Projects!$C$2,IF(OR(IF($D12="",FALSE(),AND(M$5>=DATE(YEAR($D12),MONTH($D12),1),M$5<=$E12)),N('WIP Log'!K12)<>0),N('WIP Log'!K12),""),IF(IF($D12="",FALSE(),AND(M$5>=DATE(YEAR($D12),MONTH($D12),1),M$5<=$E12)),'Phased Budget'!O12,""))) | ... AO12: =IF($B12="","",IF(AO$5<=Projects!$C$2,IF(OR(IF($D12="",FALSE(),AND(AO$5>=DATE(YEAR($D12),MONTH($D12),1),AO$5<=$E12)),N('WIP Log'!AM12)<>0),N('WIP Log'!AM12),""),IF(IF($D12="",FALSE(),AND(AO$5>=DATE(YEAR($D12),MONTH($D12),1),AO$5<=$E12)),'Phased Budget'!AQ12,"")))
A13: 8 | B13: =IF(Projects!B13="","",Projects!B13) | C13: =IF(Projects!C13="","",Projects!C13) | D13: =IF(Projects!D13="","",Projects!D13) | E13: =IF(Projects!F13="","",Projects!F13) | F13: =IF($B13="","",IF(F$5<=Projects!$C$2,IF(OR(IF($D13="",FALSE(),AND(F$5>=DATE(YEAR($D13),MONTH($D13),1),F$5<=$E13)),N('WIP Log'!D13)<>0),N('WIP Log'!D13),""),IF(IF($D13="",FALSE(),AND(F$5>=DATE(YEAR($D13),MONTH($D13),1),F$5<=$E13)),'Phased Budget'!H13,""))) | G13: =IF($B13="","",IF(G$5<=Projects!$C$2,IF(OR(IF($D13="",FALSE(),AND(G$5>=DATE(YEAR($D13),MONTH($D13),1),G$5<=$E13)),N('WIP Log'!E13)<>0),N('WIP Log'!E13),""),IF(IF($D13="",FALSE(),AND(G$5>=DATE(YEAR($D13),MONTH($D13),1),G$5<=$E13)),'Phased Budget'!I13,""))) | H13: =IF($B13="","",IF(H$5<=Projects!$C$2,IF(OR(IF($D13="",FALSE(),AND(H$5>=DATE(YEAR($D13),MONTH($D13),1),H$5<=$E13)),N('WIP Log'!F13)<>0),N('WIP Log'!F13),""),IF(IF($D13="",FALSE(),AND(H$5>=DATE(YEAR($D13),MONTH($D13),1),H$5<=$E13)),'Phased Budget'!J13,""))) | I13: =IF($B13="","",IF(I$5<=Projects!$C$2,IF(OR(IF($D13="",FALSE(),AND(I$5>=DATE(YEAR($D13),MONTH($D13),1),I$5<=$E13)),N('WIP Log'!G13)<>0),N('WIP Log'!G13),""),IF(IF($D13="",FALSE(),AND(I$5>=DATE(YEAR($D13),MONTH($D13),1),I$5<=$E13)),'Phased Budget'!K13,""))) | J13: =IF($B13="","",IF(J$5<=Projects!$C$2,IF(OR(IF($D13="",FALSE(),AND(J$5>=DATE(YEAR($D13),MONTH($D13),1),J$5<=$E13)),N('WIP Log'!H13)<>0),N('WIP Log'!H13),""),IF(IF($D13="",FALSE(),AND(J$5>=DATE(YEAR($D13),MONTH($D13),1),J$5<=$E13)),'Phased Budget'!L13,""))) | K13: =IF($B13="","",IF(K$5<=Projects!$C$2,IF(OR(IF($D13="",FALSE(),AND(K$5>=DATE(YEAR($D13),MONTH($D13),1),K$5<=$E13)),N('WIP Log'!I13)<>0),N('WIP Log'!I13),""),IF(IF($D13="",FALSE(),AND(K$5>=DATE(YEAR($D13),MONTH($D13),1),K$5<=$E13)),'Phased Budget'!M13,""))) | L13: =IF($B13="","",IF(L$5<=Projects!$C$2,IF(OR(IF($D13="",FALSE(),AND(L$5>=DATE(YEAR($D13),MONTH($D13),1),L$5<=$E13)),N('WIP Log'!J13)<>0),N('WIP Log'!J13),""),IF(IF($D13="",FALSE(),AND(L$5>=DATE(YEAR($D13),MONTH($D13),1),L$5<=$E13)),'Phased Budget'!N13,""))) | M13: =IF($B13="","",IF(M$5<=Projects!$C$2,IF(OR(IF($D13="",FALSE(),AND(M$5>=DATE(YEAR($D13),MONTH($D13),1),M$5<=$E13)),N('WIP Log'!K13)<>0),N('WIP Log'!K13),""),IF(IF($D13="",FALSE(),AND(M$5>=DATE(YEAR($D13),MONTH($D13),1),M$5<=$E13)),'Phased Budget'!O13,""))) | ... AO13: =IF($B13="","",IF(AO$5<=Projects!$C$2,IF(OR(IF($D13="",FALSE(),AND(AO$5>=DATE(YEAR($D13),MONTH($D13),1),AO$5<=$E13)),N('WIP Log'!AM13)<>0),N('WIP Log'!AM13),""),IF(IF($D13="",FALSE(),AND(AO$5>=DATE(YEAR($D13),MONTH($D13),1),AO$5<=$E13)),'Phased Budget'!AQ13,"")))
A14: 9 | B14: =IF(Projects!B14="","",Projects!B14) | C14: =IF(Projects!C14="","",Projects!C14) | D14: =IF(Projects!D14="","",Projects!D14) | E14: =IF(Projects!F14="","",Projects!F14) | F14: =IF($B14="","",IF(F$5<=Projects!$C$2,IF(OR(IF($D14="",FALSE(),AND(F$5>=DATE(YEAR($D14),MONTH($D14),1),F$5<=$E14)),N('WIP Log'!D14)<>0),N('WIP Log'!D14),""),IF(IF($D14="",FALSE(),AND(F$5>=DATE(YEAR($D14),MONTH($D14),1),F$5<=$E14)),'Phased Budget'!H14,""))) | G14: =IF($B14="","",IF(G$5<=Projects!$C$2,IF(OR(IF($D14="",FALSE(),AND(G$5>=DATE(YEAR($D14),MONTH($D14),1),G$5<=$E14)),N('WIP Log'!E14)<>0),N('WIP Log'!E14),""),IF(IF($D14="",FALSE(),AND(G$5>=DATE(YEAR($D14),MONTH($D14),1),G$5<=$E14)),'Phased Budget'!I14,""))) | H14: =IF($B14="","",IF(H$5<=Projects!$C$2,IF(OR(IF($D14="",FALSE(),AND(H$5>=DATE(YEAR($D14),MONTH($D14),1),H$5<=$E14)),N('WIP Log'!F14)<>0),N('WIP Log'!F14),""),IF(IF($D14="",FALSE(),AND(H$5>=DATE(YEAR($D14),MONTH($D14),1),H$5<=$E14)),'Phased Budget'!J14,""))) | I14: =IF($B14="","",IF(I$5<=Projects!$C$2,IF(OR(IF($D14="",FALSE(),AND(I$5>=DATE(YEAR($D14),MONTH($D14),1),I$5<=$E14)),N('WIP Log'!G14)<>0),N('WIP Log'!G14),""),IF(IF($D14="",FALSE(),AND(I$5>=DATE(YEAR($D14),MONTH($D14),1),I$5<=$E14)),'Phased Budget'!K14,""))) | J14: =IF($B14="","",IF(J$5<=Projects!$C$2,IF(OR(IF($D14="",FALSE(),AND(J$5>=DATE(YEAR($D14),MONTH($D14),1),J$5<=$E14)),N('WIP Log'!H14)<>0),N('WIP Log'!H14),""),IF(IF($D14="",FALSE(),AND(J$5>=DATE(YEAR($D14),MONTH($D14),1),J$5<=$E14)),'Phased Budget'!L14,""))) | K14: =IF($B14="","",IF(K$5<=Projects!$C$2,IF(OR(IF($D14="",FALSE(),AND(K$5>=DATE(YEAR($D14),MONTH($D14),1),K$5<=$E14)),N('WIP Log'!I14)<>0),N('WIP Log'!I14),""),IF(IF($D14="",FALSE(),AND(K$5>=DATE(YEAR($D14),MONTH($D14),1),K$5<=$E14)),'Phased Budget'!M14,""))) | L14: =IF($B14="","",IF(L$5<=Projects!$C$2,IF(OR(IF($D14="",FALSE(),AND(L$5>=DATE(YEAR($D14),MONTH($D14),1),L$5<=$E14)),N('WIP Log'!J14)<>0),N('WIP Log'!J14),""),IF(IF($D14="",FALSE(),AND(L$5>=DATE(YEAR($D14),MONTH($D14),1),L$5<=$E14)),'Phased Budget'!N14,""))) | M14: =IF($B14="","",IF(M$5<=Projects!$C$2,IF(OR(IF($D14="",FALSE(),AND(M$5>=DATE(YEAR($D14),MONTH($D14),1),M$5<=$E14)),N('WIP Log'!K14)<>0),N('WIP Log'!K14),""),IF(IF($D14="",FALSE(),AND(M$5>=DATE(YEAR($D14),MONTH($D14),1),M$5<=$E14)),'Phased Budget'!O14,""))) | ... AO14: =IF($B14="","",IF(AO$5<=Projects!$C$2,IF(OR(IF($D14="",FALSE(),AND(AO$5>=DATE(YEAR($D14),MONTH($D14),1),AO$5<=$E14)),N('WIP Log'!AM14)<>0),N('WIP Log'!AM14),""),IF(IF($D14="",FALSE(),AND(AO$5>=DATE(YEAR($D14),MONTH($D14),1),AO$5<=$E14)),'Phased Budget'!AQ14,"")))
A15: 10 | B15: =IF(Projects!B15="","",Projects!B15) | C15: =IF(Projects!C15="","",Projects!C15) | D15: =IF(Projects!D15="","",Projects!D15) | E15: =IF(Projects!F15="","",Projects!F15) | F15: =IF($B15="","",IF(F$5<=Projects!$C$2,IF(OR(IF($D15="",FALSE(),AND(F$5>=DATE(YEAR($D15),MONTH($D15),1),F$5<=$E15)),N('WIP Log'!D15)<>0),N('WIP Log'!D15),""),IF(IF($D15="",FALSE(),AND(F$5>=DATE(YEAR($D15),MONTH($D15),1),F$5<=$E15)),'Phased Budget'!H15,""))) | G15: =IF($B15="","",IF(G$5<=Projects!$C$2,IF(OR(IF($D15="",FALSE(),AND(G$5>=DATE(YEAR($D15),MONTH($D15),1),G$5<=$E15)),N('WIP Log'!E15)<>0),N('WIP Log'!E15),""),IF(IF($D15="",FALSE(),AND(G$5>=DATE(YEAR($D15),MONTH($D15),1),G$5<=$E15)),'Phased Budget'!I15,""))) | H15: =IF($B15="","",IF(H$5<=Projects!$C$2,IF(OR(IF($D15="",FALSE(),AND(H$5>=DATE(YEAR($D15),MONTH($D15),1),H$5<=$E15)),N('WIP Log'!F15)<>0),N('WIP Log'!F15),""),IF(IF($D15="",FALSE(),AND(H$5>=DATE(YEAR($D15),MONTH($D15),1),H$5<=$E15)),'Phased Budget'!J15,""))) | I15: =IF($B15="","",IF(I$5<=Projects!$C$2,IF(OR(IF($D15="",FALSE(),AND(I$5>=DATE(YEAR($D15),MONTH($D15),1),I$5<=$E15)),N('WIP Log'!G15)<>0),N('WIP Log'!G15),""),IF(IF($D15="",FALSE(),AND(I$5>=DATE(YEAR($D15),MONTH($D15),1),I$5<=$E15)),'Phased Budget'!K15,""))) | J15: =IF($B15="","",IF(J$5<=Projects!$C$2,IF(OR(IF($D15="",FALSE(),AND(J$5>=DATE(YEAR($D15),MONTH($D15),1),J$5<=$E15)),N('WIP Log'!H15)<>0),N('WIP Log'!H15),""),IF(IF($D15="",FALSE(),AND(J$5>=DATE(YEAR($D15),MONTH($D15),1),J$5<=$E15)),'Phased Budget'!L15,""))) | K15: =IF($B15="","",IF(K$5<=Projects!$C$2,IF(OR(IF($D15="",FALSE(),AND(K$5>=DATE(YEAR($D15),MONTH($D15),1),K$5<=$E15)),N('WIP Log'!I15)<>0),N('WIP Log'!I15),""),IF(IF($D15="",FALSE(),AND(K$5>=DATE(YEAR($D15),MONTH($D15),1),K$5<=$E15)),'Phased Budget'!M15,""))) | L15: =IF($B15="","",IF(L$5<=Projects!$C$2,IF(OR(IF($D15="",FALSE(),AND(L$5>=DATE(YEAR($D15),MONTH($D15),1),L$5<=$E15)),N('WIP Log'!J15)<>0),N('WIP Log'!J15),""),IF(IF($D15="",FALSE(),AND(L$5>=DATE(YEAR($D15),MONTH($D15),1),L$5<=$E15)),'Phased Budget'!N15,""))) | M15: =IF($B15="","",IF(M$5<=Projects!$C$2,IF(OR(IF($D15="",FALSE(),AND(M$5>=DATE(YEAR($D15),MONTH($D15),1),M$5<=$E15)),N('WIP Log'!K15)<>0),N('WIP Log'!K15),""),IF(IF($D15="",FALSE(),AND(M$5>=DATE(YEAR($D15),MONTH($D15),1),M$5<=$E15)),'Phased Budget'!O15,""))) | ... AO15: =IF($B15="","",IF(AO$5<=Projects!$C$2,IF(OR(IF($D15="",FALSE(),AND(AO$5>=DATE(YEAR($D15),MONTH($D15),1),AO$5<=$E15)),N('WIP Log'!AM15)<>0),N('WIP Log'!AM15),""),IF(IF($D15="",FALSE(),AND(AO$5>=DATE(YEAR($D15),MONTH($D15),1),AO$5<=$E15)),'Phased Budget'!AQ15,"")))
A16: 11 | B16: =IF(Projects!B16="","",Projects!B16) | C16: =IF(Projects!C16="","",Projects!C16) | D16: =IF(Projects!D16="","",Projects!D16) | E16: =IF(Projects!F16="","",Projects!F16) | F16: =IF($B16="","",IF(F$5<=Projects!$C$2,IF(OR(IF($D16="",FALSE(),AND(F$5>=DATE(YEAR($D16),MONTH($D16),1),F$5<=$E16)),N('WIP Log'!D16)<>0),N('WIP Log'!D16),""),IF(IF($D16="",FALSE(),AND(F$5>=DATE(YEAR($D16),MONTH($D16),1),F$5<=$E16)),'Phased Budget'!H16,""))) | G16: =IF($B16="","",IF(G$5<=Projects!$C$2,IF(OR(IF($D16="",FALSE(),AND(G$5>=DATE(YEAR($D16),MONTH($D16),1),G$5<=$E16)),N('WIP Log'!E16)<>0),N('WIP Log'!E16),""),IF(IF($D16="",FALSE(),AND(G$5>=DATE(YEAR($D16),MONTH($D16),1),G$5<=$E16)),'Phased Budget'!I16,""))) | H16: =IF($B16="","",IF(H$5<=Projects!$C$2,IF(OR(IF($D16="",FALSE(),AND(H$5>=DATE(YEAR($D16),MONTH($D16),1),H$5<=$E16)),N('WIP Log'!F16)<>0),N('WIP Log'!F16),""),IF(IF($D16="",FALSE(),AND(H$5>=DATE(YEAR($D16),MONTH($D16),1),H$5<=$E16)),'Phased Budget'!J16,""))) | I16: =IF($B16="","",IF(I$5<=Projects!$C$2,IF(OR(IF($D16="",FALSE(),AND(I$5>=DATE(YEAR($D16),MONTH($D16),1),I$5<=$E16)),N('WIP Log'!G16)<>0),N('WIP Log'!G16),""),IF(IF($D16="",FALSE(),AND(I$5>=DATE(YEAR($D16),MONTH($D16),1),I$5<=$E16)),'Phased Budget'!K16,""))) | J16: =IF($B16="","",IF(J$5<=Projects!$C$2,IF(OR(IF($D16="",FALSE(),AND(J$5>=DATE(YEAR($D16),MONTH($D16),1),J$5<=$E16)),N('WIP Log'!H16)<>0),N('WIP Log'!H16),""),IF(IF($D16="",FALSE(),AND(J$5>=DATE(YEAR($D16),MONTH($D16),1),J$5<=$E16)),'Phased Budget'!L16,""))) | K16: =IF($B16="","",IF(K$5<=Projects!$C$2,IF(OR(IF($D16="",FALSE(),AND(K$5>=DATE(YEAR($D16),MONTH($D16),1),K$5<=$E16)),N('WIP Log'!I16)<>0),N('WIP Log'!I16),""),IF(IF($D16="",FALSE(),AND(K$5>=DATE(YEAR($D16),MONTH($D16),1),K$5<=$E16)),'Phased Budget'!M16,""))) | L16: =IF($B16="","",IF(L$5<=Projects!$C$2,IF(OR(IF($D16="",FALSE(),AND(L$5>=DATE(YEAR($D16),MONTH($D16),1),L$5<=$E16)),N('WIP Log'!J16)<>0),N('WIP Log'!J16),""),IF(IF($D16="",FALSE(),AND(L$5>=DATE(YEAR($D16),MONTH($D16),1),L$5<=$E16)),'Phased Budget'!N16,""))) | M16: =IF($B16="","",IF(M$5<=Projects!$C$2,IF(OR(IF($D16="",FALSE(),AND(M$5>=DATE(YEAR($D16),MONTH($D16),1),M$5<=$E16)),N('WIP Log'!K16)<>0),N('WIP Log'!K16),""),IF(IF($D16="",FALSE(),AND(M$5>=DATE(YEAR($D16),MONTH($D16),1),M$5<=$E16)),'Phased Budget'!O16,""))) | ... AO16: =IF($B16="","",IF(AO$5<=Projects!$C$2,IF(OR(IF($D16="",FALSE(),AND(AO$5>=DATE(YEAR($D16),MONTH($D16),1),AO$5<=$E16)),N('WIP Log'!AM16)<>0),N('WIP Log'!AM16),""),IF(IF($D16="",FALSE(),AND(AO$5>=DATE(YEAR($D16),MONTH($D16),1),AO$5<=$E16)),'Phased Budget'!AQ16,"")))
A17: 12 | B17: =IF(Projects!B17="","",Projects!B17) | C17: =IF(Projects!C17="","",Projects!C17) | D17: =IF(Projects!D17="","",Projects!D17) | E17: =IF(Projects!F17="","",Projects!F17) | F17: =IF($B17="","",IF(F$5<=Projects!$C$2,IF(OR(IF($D17="",FALSE(),AND(F$5>=DATE(YEAR($D17),MONTH($D17),1),F$5<=$E17)),N('WIP Log'!D17)<>0),N('WIP Log'!D17),""),IF(IF($D17="",FALSE(),AND(F$5>=DATE(YEAR($D17),MONTH($D17),1),F$5<=$E17)),'Phased Budget'!H17,""))) | G17: =IF($B17="","",IF(G$5<=Projects!$C$2,IF(OR(IF($D17="",FALSE(),AND(G$5>=DATE(YEAR($D17),MONTH($D17),1),G$5<=$E17)),N('WIP Log'!E17)<>0),N('WIP Log'!E17),""),IF(IF($D17="",FALSE(),AND(G$5>=DATE(YEAR($D17),MONTH($D17),1),G$5<=$E17)),'Phased Budget'!I17,""))) | H17: =IF($B17="","",IF(H$5<=Projects!$C$2,IF(OR(IF($D17="",FALSE(),AND(H$5>=DATE(YEAR($D17),MONTH($D17),1),H$5<=$E17)),N('WIP Log'!F17)<>0),N('WIP Log'!F17),""),IF(IF($D17="",FALSE(),AND(H$5>=DATE(YEAR($D17),MONTH($D17),1),H$5<=$E17)),'Phased Budget'!J17,""))) | I17: =IF($B17="","",IF(I$5<=Projects!$C$2,IF(OR(IF($D17="",FALSE(),AND(I$5>=DATE(YEAR($D17),MONTH($D17),1),I$5<=$E17)),N('WIP Log'!G17)<>0),N('WIP Log'!G17),""),IF(IF($D17="",FALSE(),AND(I$5>=DATE(YEAR($D17),MONTH($D17),1),I$5<=$E17)),'Phased Budget'!K17,""))) | J17: =IF($B17="","",IF(J$5<=Projects!$C$2,IF(OR(IF($D17="",FALSE(),AND(J$5>=DATE(YEAR($D17),MONTH($D17),1),J$5<=$E17)),N('WIP Log'!H17)<>0),N('WIP Log'!H17),""),IF(IF($D17="",FALSE(),AND(J$5>=DATE(YEAR($D17),MONTH($D17),1),J$5<=$E17)),'Phased Budget'!L17,""))) | K17: =IF($B17="","",IF(K$5<=Projects!$C$2,IF(OR(IF($D17="",FALSE(),AND(K$5>=DATE(YEAR($D17),MONTH($D17),1),K$5<=$E17)),N('WIP Log'!I17)<>0),N('WIP Log'!I17),""),IF(IF($D17="",FALSE(),AND(K$5>=DATE(YEAR($D17),MONTH($D17),1),K$5<=$E17)),'Phased Budget'!M17,""))) | L17: =IF($B17="","",IF(L$5<=Projects!$C$2,IF(OR(IF($D17="",FALSE(),AND(L$5>=DATE(YEAR($D17),MONTH($D17),1),L$5<=$E17)),N('WIP Log'!J17)<>0),N('WIP Log'!J17),""),IF(IF($D17="",FALSE(),AND(L$5>=DATE(YEAR($D17),MONTH($D17),1),L$5<=$E17)),'Phased Budget'!N17,""))) | M17: =IF($B17="","",IF(M$5<=Projects!$C$2,IF(OR(IF($D17="",FALSE(),AND(M$5>=DATE(YEAR($D17),MONTH($D17),1),M$5<=$E17)),N('WIP Log'!K17)<>0),N('WIP Log'!K17),""),IF(IF($D17="",FALSE(),AND(M$5>=DATE(YEAR($D17),MONTH($D17),1),M$5<=$E17)),'Phased Budget'!O17,""))) | ... AO17: =IF($B17="","",IF(AO$5<=Projects!$C$2,IF(OR(IF($D17="",FALSE(),AND(AO$5>=DATE(YEAR($D17),MONTH($D17),1),AO$5<=$E17)),N('WIP Log'!AM17)<>0),N('WIP Log'!AM17),""),IF(IF($D17="",FALSE(),AND(AO$5>=DATE(YEAR($D17),MONTH($D17),1),AO$5<=$E17)),'Phased Budget'!AQ17,"")))
... A55: 50 | B55: =IF(Projects!B55="","",Projects!B55) | C55: =IF(Projects!C55="","",Projects!C55) | D55: =IF(Projects!D55="","",Projects!D55) | E55: =IF(Projects!F55="","",Projects!F55) | F55: =IF($B55="","",IF(F$5<=Projects!$C$2,IF(OR(IF($D55="",FALSE(),AND(F$5>=DATE(YEAR($D55),MONTH($D55),1),F$5<=$E55)),N('WIP Log'!D55)<>0),N('WIP Log'!D55),""),IF(IF($D55="",FALSE(),AND(F$5>=DATE(YEAR($D55),MONTH($D55),1),F$5<=$E55)),'Phased Budget'!H55,""))) | G55: =IF($B55="","",IF(G$5<=Projects!$C$2,IF(OR(IF($D55="",FALSE(),AND(G$5>=DATE(YEAR($D55),MONTH($D55),1),G$5<=$E55)),N('WIP Log'!E55)<>0),N('WIP Log'!E55),""),IF(IF($D55="",FALSE(),AND(G$5>=DATE(YEAR($D55),MONTH($D55),1),G$5<=$E55)),'Phased Budget'!I55,""))) | H55: =IF($B55="","",IF(H$5<=Projects!$C$2,IF(OR(IF($D55="",FALSE(),AND(H$5>=DATE(YEAR($D55),MONTH($D55),1),H$5<=$E55)),N('WIP Log'!F55)<>0),N('WIP Log'!F55),""),IF(IF($D55="",FALSE(),AND(H$5>=DATE(YEAR($D55),MONTH($D55),1),H$5<=$E55)),'Phased Budget'!J55,""))) | I55: =IF($B55="","",IF(I$5<=Projects!$C$2,IF(OR(IF($D55="",FALSE(),AND(I$5>=DATE(YEAR($D55),MONTH($D55),1),I$5<=$E55)),N('WIP Log'!G55)<>0),N('WIP Log'!G55),""),IF(IF($D55="",FALSE(),AND(I$5>=DATE(YEAR($D55),MONTH($D55),1),I$5<=$E55)),'Phased Budget'!K55,""))) | J55: =IF($B55="","",IF(J$5<=Projects!$C$2,IF(OR(IF($D55="",FALSE(),AND(J$5>=DATE(YEAR($D55),MONTH($D55),1),J$5<=$E55)),N('WIP Log'!H55)<>0),N('WIP Log'!H55),""),IF(IF($D55="",FALSE(),AND(J$5>=DATE(YEAR($D55),MONTH($D55),1),J$5<=$E55)),'Phased Budget'!L55,""))) | K55: =IF($B55="","",IF(K$5<=Projects!$C$2,IF(OR(IF($D55="",FALSE(),AND(K$5>=DATE(YEAR($D55),MONTH($D55),1),K$5<=$E55)),N('WIP Log'!I55)<>0),N('WIP Log'!I55),""),IF(IF($D55="",FALSE(),AND(K$5>=DATE(YEAR($D55),MONTH($D55),1),K$5<=$E55)),'Phased Budget'!M55,""))) | L55: =IF($B55="","",IF(L$5<=Projects!$C$2,IF(OR(IF($D55="",FALSE(),AND(L$5>=DATE(YEAR($D55),MONTH($D55),1),L$5<=$E55)),N('WIP Log'!J55)<>0),N('WIP Log'!J55),""),IF(IF($D55="",FALSE(),AND(L$5>=DATE(YEAR($D55),MONTH($D55),1),L$5<=$E55)),'Phased Budget'!N55,""))) | M55: =IF($B55="","",IF(M$5<=Projects!$C$2,IF(OR(IF($D55="",FALSE(),AND(M$5>=DATE(YEAR($D55),MONTH($D55),1),M$5<=$E55)),N('WIP Log'!K55)<>0),N('WIP Log'!K55),""),IF(IF($D55="",FALSE(),AND(M$5>=DATE(YEAR($D55),MONTH($D55),1),M$5<=$E55)),'Phased Budget'!O55,""))) | ... AO55: =IF($B55="","",IF(AO$5<=Projects!$C$2,IF(OR(IF($D55="",FALSE(),AND(AO$5>=DATE(YEAR($D55),MONTH($D55),1),AO$5<=$E55)),N('WIP Log'!AM55)<>0),N('WIP Log'!AM55),""),IF(IF($D55="",FALSE(),AND(AO$5>=DATE(YEAR($D55),MONTH($D55),1),AO$5<=$E55)),'Phased Budget'!AQ55,"")))

Sheet Aggregator
A1: Aggregator
A3: Σ WIP actuals (≤ Current Month) + Σ Phased Budgeted (after it) per month, against TRM. Enter TRM in the yellow column.
A5: Month | B5: Year | C5: Σ WIP (actual) | D5: Σ Phased Budgeted | E5: Total (WIP + Phased) | F5: TRM (input) | G5: Variance (Total − TRM) | I5: Annual (calendar year)
A6: ='WIP Log'!D5 -> 46023 | B6: =YEAR(A6) -> 2026 | C6: =IF(A6<=Projects!$C$2,'WIP Log'!D57,0) -> 0 | D6: ='Phased Budget'!H57 -> 0 | E6: =C6+D6 -> 0 | G6: =IF(F6="","",E6-F6) | I6: Year | J6: Σ WIP (actual) | K6: Σ Phased Budget | L6: WIP + Phased Budget | M6: TRM | N6: Variance
A7: ='WIP Log'!E5 -> 46054 | B7: =YEAR(A7) -> 2026 | C7: =IF(A7<=Projects!$C$2,'WIP Log'!E57,0) -> 0 | D7: ='Phased Budget'!I57 -> 0 | E7: =C7+D7 -> 0 | G7: =IF(F7="","",E7-F7) | I7: =YEAR(Projects!$C$3)+0 -> 2026 | J7: =SUMIFS(C$6:C$41,$B$6:$B$41,$I7) -> 1000 | K7: =SUMIFS(D$6:D$41,$B$6:$B$41,$I7) -> 4500 | L7: =J7+K7 -> 5500 | M7: =SUMIFS(F$6:F$41,$B$6:$B$41,$I7) -> 0 | N7: =L7-M7 -> 5500
A8: ='WIP Log'!F5 -> 46082 | B8: =YEAR(A8) -> 2026 | C8: =IF(A8<=Projects!$C$2,'WIP Log'!F57,0) -> 0 | D8: ='Phased Budget'!J57 -> 0 | E8: =C8+D8 -> 0 | G8: =IF(F8="","",E8-F8) | I8: =YEAR(Projects!$C$3)+1 -> 2027 | J8: =SUMIFS(C$6:C$41,$B$6:$B$41,$I8) -> 0 | K8: =SUMIFS(D$6:D$41,$B$6:$B$41,$I8) -> 4500 | L8: =J8+K8 -> 4500 | M8: =SUMIFS(F$6:F$41,$B$6:$B$41,$I8) -> 0 | N8: =L8-M8 -> 4500
A9: ='WIP Log'!G5 -> 46113 | B9: =YEAR(A9) -> 2026 | C9: =IF(A9<=Projects!$C$2,'WIP Log'!G57,0) -> 0 | D9: ='Phased Budget'!K57 -> 0 | E9: =C9+D9 -> 0 | G9: =IF(F9="","",E9-F9) | I9: =YEAR(Projects!$C$3)+2 -> 2028 | J9: =SUMIFS(C$6:C$41,$B$6:$B$41,$I9) -> 0 | K9: =SUMIFS(D$6:D$41,$B$6:$B$41,$I9) -> 0 | L9: =J9+K9 -> 0 | M9: =SUMIFS(F$6:F$41,$B$6:$B$41,$I9) -> 0 | N9: =L9-M9 -> 0
A10: ='WIP Log'!H5 -> 46143 | B10: =YEAR(A10) -> 2026 | C10: =IF(A10<=Projects!$C$2,'WIP Log'!H57,0) -> 0 | D10: ='Phased Budget'!L57 -> 0 | E10: =C10+D10 -> 0 | G10: =IF(F10="","",E10-F10) | I10: Total | J10: =SUM(J7:J9) -> 1000 | K10: =SUM(K7:K9) -> 9000 | L10: =SUM(L7:L9) -> 10000 | M10: =SUM(M7:M9) -> 0 | N10: =SUM(N7:N9) -> 10000
A11: ='WIP Log'!I5 -> 46174 | B11: =YEAR(A11) -> 2026 | C11: =IF(A11<=Projects!$C$2,'WIP Log'!I57,0) -> 0 | D11: ='Phased Budget'!M57 -> 0 | E11: =C11+D11 -> 0 | G11: =IF(F11="","",E11-F11)
A12: ='WIP Log'!J5 -> 46204 | B12: =YEAR(A12) -> 2026 | C12: =IF(A12<=Projects!$C$2,'WIP Log'!J57,0) -> 0 | D12: ='Phased Budget'!N57 -> 0 | E12: =C12+D12 -> 0 | G12: =IF(F12="","",E12-F12) | I12: Reconciliation
A13: ='WIP Log'!K5 -> 46235 | B13: =YEAR(A13) -> 2026 | C13: =IF(A13<=Projects!$C$2,'WIP Log'!K57,0) -> 0 | D13: ='Phased Budget'!O57 -> 0 | E13: =C13+D13 -> 0 | G13: =IF(F13="","",E13-F13) | I13: Σ Contracted Budget | L13: =Projects!G57 -> 10000
A14: ='WIP Log'!L5 -> 46266 | B14: =YEAR(A14) -> 2026 | C14: =IF(A14<=Projects!$C$2,'WIP Log'!L57,0) -> 0 | D14: ='Phased Budget'!P57 -> 0 | E14: =C14+D14 -> 0 | G14: =IF(F14="","",E14-F14) | I14: Σ WIP to date (all projects) | L14: =Projects!H57 -> 1000
A15: ='WIP Log'!M5 -> 46296 | B15: =YEAR(A15) -> 2026 | C15: =IF(A15<=Projects!$C$2,'WIP Log'!M57,0) -> 1000 | D15: ='Phased Budget'!Q57 -> 0 | E15: =C15+D15 -> 1000 | G15: =IF(F15="","",E15-F15) | I15: Σ Phased Budgeted (on timeline) | L15: =D42 -> 9000
A16: ='WIP Log'!N5 -> 46327 | B16: =YEAR(A16) -> 2026 | C16: =IF(A16<=Projects!$C$2,'WIP Log'!N57,0) -> 0 | D16: ='Phased Budget'!R57 -> 2250 | E16: =C16+D16 -> 2250 | G16: =IF(F16="","",E16-F16) | I16: Difference (unphased / off-timeline) | L16: =L13-L14-L15 -> 0 | M16: =IF(ABS(L16)<0.005,"✓ fully phased","Check Projects → Status") -> ✓ fully phased
A17: ='WIP Log'!O5 -> 46357 | B17: =YEAR(A17) -> 2026 | C17: =IF(A17<=Projects!$C$2,'WIP Log'!O57,0) -> 0 | D17: ='Phased Budget'!S57 -> 2250 | E17: =C17+D17 -> 2250 | G17: =IF(F17="","",E17-F17)
A18: ='WIP Log'!P5 -> 46388 | B18: =YEAR(A18) -> 2027 | C18: =IF(A18<=Projects!$C$2,'WIP Log'!P57,0) -> 0 | D18: ='Phased Budget'!T57 -> 2250 | E18: =C18+D18 -> 2250 | G18: =IF(F18="","",E18-F18)
A19: ='WIP Log'!Q5 -> 46419 | B19: =YEAR(A19) -> 2027 | C19: =IF(A19<=Projects!$C$2,'WIP Log'!Q57,0) -> 0 | D19: ='Phased Budget'!U57 -> 2250 | E19: =C19+D19 -> 2250 | G19: =IF(F19="","",E19-F19)
A20: ='WIP Log'!R5 -> 46447 | B20: =YEAR(A20) -> 2027 | C20: =IF(A20<=Projects!$C$2,'WIP Log'!R57,0) -> 0 | D20: ='Phased Budget'!V57 -> 0 | E20: =C20+D20 -> 0 | G20: =IF(F20="","",E20-F20)
A21: ='WIP Log'!S5 -> 46478 | B21: =YEAR(A21) -> 2027 | C21: =IF(A21<=Projects!$C$2,'WIP Log'!S57,0) -> 0 | D21: ='Phased Budget'!W57 -> 0 | E21: =C21+D21 -> 0 | G21: =IF(F21="","",E21-F21)
A22: ='WIP Log'!T5 -> 46508 | B22: =YEAR(A22) -> 2027 | C22: =IF(A22<=Projects!$C$2,'WIP Log'!T57,0) -> 0 | D22: ='Phased Budget'!X57 -> 0 | E22: =C22+D22 -> 0 | G22: =IF(F22="","",E22-F22)
A23: ='WIP Log'!U5 -> 46539 | B23: =YEAR(A23) -> 2027 | C23: =IF(A23<=Projects!$C$2,'WIP Log'!U57,0) -> 0 | D23: ='Phased Budget'!Y57 -> 0 | E23: =C23+D23 -> 0 | G23: =IF(F23="","",E23-F23)
A24: ='WIP Log'!V5 -> 46569 | B24: =YEAR(A24) -> 2027 | C24: =IF(A24<=Projects!$C$2,'WIP Log'!V57,0) -> 0 | D24: ='Phased Budget'!Z57 -> 0 | E24: =C24+D24 -> 0 | G24: =IF(F24="","",E24-F24)
A25: ='WIP Log'!W5 -> 46600 | B25: =YEAR(A25) -> 2027 | C25: =IF(A25<=Projects!$C$2,'WIP Log'!W57,0) -> 0 | D25: ='Phased Budget'!AA57 -> 0 | E25: =C25+D25 -> 0 | G25: =IF(F25="","",E25-F25)
A26: ='WIP Log'!X5 -> 46631 | B26: =YEAR(A26) -> 2027 | C26: =IF(A26<=Projects!$C$2,'WIP Log'!X57,0) -> 0 | D26: ='Phased Budget'!AB57 -> 0 | E26: =C26+D26 -> 0 | G26: =IF(F26="","",E26-F26)
A27: ='WIP Log'!Y5 -> 46661 | B27: =YEAR(A27) -> 2027 | C27: =IF(A27<=Projects!$C$2,'WIP Log'!Y57,0) -> 0 | D27: ='Phased Budget'!AC57 -> 0 | E27: =C27+D27 -> 0 | G27: =IF(F27="","",E27-F27)
A28: ='WIP Log'!Z5 -> 46692 | B28: =YEAR(A28) -> 2027 | C28: =IF(A28<=Projects!$C$2,'WIP Log'!Z57,0) -> 0 | D28: ='Phased Budget'!AD57 -> 0 | E28: =C28+D28 -> 0 | G28: =IF(F28="","",E28-F28)
A29: ='WIP Log'!AA5 -> 46722 | B29: =YEAR(A29) -> 2027 | C29: =IF(A29<=Projects!$C$2,'WIP Log'!AA57,0) -> 0 | D29: ='Phased Budget'!AE57 -> 0 | E29: =C29+D29 -> 0 | G29: =IF(F29="","",E29-F29)
A30: ='WIP Log'!AB5 -> 46753 | B30: =YEAR(A30) -> 2028 | C30: =IF(A30<=Projects!$C$2,'WIP Log'!AB57,0) -> 0 | D30: ='Phased Budget'!AF57 -> 0 | E30: =C30+D30 -> 0 | G30: =IF(F30="","",E30-F30)
A31: ='WIP Log'!AC5 -> 46784 | B31: =YEAR(A31) -> 2028 | C31: =IF(A31<=Projects!$C$2,'WIP Log'!AC57,0) -> 0 | D31: ='Phased Budget'!AG57 -> 0 | E31: =C31+D31 -> 0 | G31: =IF(F31="","",E31-F31)
A32: ='WIP Log'!AD5 -> 46813 | B32: =YEAR(A32) -> 2028 | C32: =IF(A32<=Projects!$C$2,'WIP Log'!AD57,0) -> 0 | D32: ='Phased Budget'!AH57 -> 0 | E32: =C32+D32 -> 0 | G32: =IF(F32="","",E32-F32)
A33: ='WIP Log'!AE5 -> 46844 | B33: =YEAR(A33) -> 2028 | C33: =IF(A33<=Projects!$C$2,'WIP Log'!AE57,0) -> 0 | D33: ='Phased Budget'!AI57 -> 0 | E33: =C33+D33 -> 0 | G33: =IF(F33="","",E33-F33)
A34: ='WIP Log'!AF5 -> 46874 | B34: =YEAR(A34) -> 2028 | C34: =IF(A34<=Projects!$C$2,'WIP Log'!AF57,0) -> 0 | D34: ='Phased Budget'!AJ57 -> 0 | E34: =C34+D34 -> 0 | G34: =IF(F34="","",E34-F34)
A35: ='WIP Log'!AG5 -> 46905 | B35: =YEAR(A35) -> 2028 | C35: =IF(A35<=Projects!$C$2,'WIP Log'!AG57,0) -> 0 | D35: ='Phased Budget'!AK57 -> 0 | E35: =C35+D35 -> 0 | G35: =IF(F35="","",E35-F35)
A36: ='WIP Log'!AH5 -> 46935 | B36: =YEAR(A36) -> 2028 | C36: =IF(A36<=Projects!$C$2,'WIP Log'!AH57,0) -> 0 | D36: ='Phased Budget'!AL57 -> 0 | E36: =C36+D36 -> 0 | G36: =IF(F36="","",E36-F36)
A37: ='WIP Log'!AI5 -> 46966 | B37: =YEAR(A37) -> 2028 | C37: =IF(A37<=Projects!$C$2,'WIP Log'!AI57,0) -> 0 | D37: ='Phased Budget'!AM57 -> 0 | E37: =C37+D37 -> 0 | G37: =IF(F37="","",E37-F37)
A38: ='WIP Log'!AJ5 -> 46997 | B38: =YEAR(A38) -> 2028 | C38: =IF(A38<=Projects!$C$2,'WIP Log'!AJ57,0) -> 0 | D38: ='Phased Budget'!AN57 -> 0 | E38: =C38+D38 -> 0 | G38: =IF(F38="","",E38-F38)
A39: ='WIP Log'!AK5 -> 47027 | B39: =YEAR(A39) -> 2028 | C39: =IF(A39<=Projects!$C$2,'WIP Log'!AK57,0) -> 0 | D39: ='Phased Budget'!AO57 -> 0 | E39: =C39+D39 -> 0 | G39: =IF(F39="","",E39-F39)
A40: ='WIP Log'!AL5 -> 47058 | B40: =YEAR(A40) -> 2028 | C40: =IF(A40<=Projects!$C$2,'WIP Log'!AL57,0) -> 0 | D40: ='Phased Budget'!AP57 -> 0 | E40: =C40+D40 -> 0 | G40: =IF(F40="","",E40-F40)
A41: ='WIP Log'!AM5 -> 47088 | B41: =YEAR(A41) -> 2028 | C41: =IF(A41<=Projects!$C$2,'WIP Log'!AM57,0) -> 0 | D41: ='Phased Budget'!AQ57 -> 0 | E41: =C41+D41 -> 0 | G41: =IF(F41="","",E41-F41)
A42: TOTAL | C42: =SUM(C6:C41) -> 1000 | D42: =SUM(D6:D41) -> 9000 | E42: =SUM(E6:E41) -> 10000 | F42: =SUM(F6:F41) -> 0 | G42: =SUM(G6:G41) -> 0

Sheet Phased Budget
A1: Phased Budgeted – calculation grid (no inputs)
A3: Budgeted × weight(k) ÷ Σ remaining weights, for project months after the Current Month only.
A5: # | B5: Project Name | C5: Starting Month | D5: Duration | E5: Budgeted | F5: Σ remaining weights | G5: Equal weights? | H5: ='WIP Log'!D5 -> 46023 | I5: ='WIP Log'!E5 -> 46054 | J5: ='WIP Log'!F5 -> 46082 | K5: ='WIP Log'!G5 -> 46113 | L5: ='WIP Log'!H5 -> 46143 | M5: ='WIP Log'!I5 -> 46174 | N5: ='WIP Log'!J5 -> 46204 | O5: ='WIP Log'!K5 -> 46235 | ... AQ5: ='WIP Log'!AM5 -> 47088
A6: 1 | B6: =IF(Projects!B6="","",Projects!B6) -> Example Project (slide) | C6: =IF(Projects!D6="","",Projects!D6) -> 46296 | D6: =IF(Projects!E6="","",Projects!E6) -> 5 | E6: =IF(Projects!B6="",0,N(Projects!I6)) -> 9000 | F6: =Phasing!G6 -> 8 | G6: =Phasing!D6=0 -> FALSE | H6: =IF(OR($C6="",$D6="",$F6=0),0,IF(OR(H$5<=Projects!$C$2,((YEAR(H$5)-YEAR($C6))*12+MONTH(H$5)-MONTH($C6)+1)<1,((YEAR(H$5)-YEAR($C6))*12+MONTH(H$5)-MONTH($C6)+1)>$D6),0,$E6*IF($G6,1,N(INDEX(Phasing!$I6:$AF6,((YEAR(H$5)-YEAR($C6))*12+MONTH(H$5)-MONTH($C6)+1))))/$F6)) -> 0 | I6: =IF(OR($C6="",$D6="",$F6=0),0,IF(OR(I$5<=Projects!$C$2,((YEAR(I$5)-YEAR($C6))*12+MONTH(I$5)-MONTH($C6)+1)<1,((YEAR(I$5)-YEAR($C6))*12+MONTH(I$5)-MONTH($C6)+1)>$D6),0,$E6*IF($G6,1,N(INDEX(Phasing!$I6:$AF6,((YEAR(I$5)-YEAR($C6))*12+MONTH(I$5)-MONTH($C6)+1))))/$F6)) -> 0 | J6: =IF(OR($C6="",$D6="",$F6=0),0,IF(OR(J$5<=Projects!$C$2,((YEAR(J$5)-YEAR($C6))*12+MONTH(J$5)-MONTH($C6)+1)<1,((YEAR(J$5)-YEAR($C6))*12+MONTH(J$5)-MONTH($C6)+1)>$D6),0,$E6*IF($G6,1,N(INDEX(Phasing!$I6:$AF6,((YEAR(J$5)-YEAR($C6))*12+MONTH(J$5)-MONTH($C6)+1))))/$F6)) -> 0 | K6: =IF(OR($C6="",$D6="",$F6=0),0,IF(OR(K$5<=Projects!$C$2,((YEAR(K$5)-YEAR($C6))*12+MONTH(K$5)-MONTH($C6)+1)<1,((YEAR(K$5)-YEAR($C6))*12+MONTH(K$5)-MONTH($C6)+1)>$D6),0,$E6*IF($G6,1,N(INDEX(Phasing!$I6:$AF6,((YEAR(K$5)-YEAR($C6))*12+MONTH(K$5)-MONTH($C6)+1))))/$F6)) -> 0 | L6: =IF(OR($C6="",$D6="",$F6=0),0,IF(OR(L$5<=Projects!$C$2,((YEAR(L$5)-YEAR($C6))*12+MONTH(L$5)-MONTH($C6)+1)<1,((YEAR(L$5)-YEAR($C6))*12+MONTH(L$5)-MONTH($C6)+1)>$D6),0,$E6*IF($G6,1,N(INDEX(Phasing!$I6:$AF6,((YEAR(L$5)-YEAR($C6))*12+MONTH(L$5)-MONTH($C6)+1))))/$F6)) -> 0 | M6: =IF(OR($C6="",$D6="",$F6=0),0,IF(OR(M$5<=Projects!$C$2,((YEAR(M$5)-YEAR($C6))*12+MONTH(M$5)-MONTH($C6)+1)<1,((YEAR(M$5)-YEAR($C6))*12+MONTH(M$5)-MONTH($C6)+1)>$D6),0,$E6*IF($G6,1,N(INDEX(Phasing!$I6:$AF6,((YEAR(M$5)-YEAR($C6))*12+MONTH(M$5)-MONTH($C6)+1))))/$F6)) -> 0 | N6: =IF(OR($C6="",$D6="",$F6=0),0,IF(OR(N$5<=Projects!$C$2,((YEAR(N$5)-YEAR($C6))*12+MONTH(N$5)-MONTH($C6)+1)<1,((YEAR(N$5)-YEAR($C6))*12+MONTH(N$5)-MONTH($C6)+1)>$D6),0,$E6*IF($G6,1,N(INDEX(Phasing!$I6:$AF6,((YEAR(N$5)-YEAR($C6))*12+MONTH(N$5)-MONTH($C6)+1))))/$F6)) -> 0 | O6: =IF(OR($C6="",$D6="",$F6=0),0,IF(OR(O$5<=Projects!$C$2,((YEAR(O$5)-YEAR($C6))*12+MONTH(O$5)-MONTH($C6)+1)<1,((YEAR(O$5)-YEAR($C6))*12+MONTH(O$5)-MONTH($C6)+1)>$D6),0,$E6*IF($G6,1,N(INDEX(Phasing!$I6:$AF6,((YEAR(O$5)-YEAR($C6))*12+MONTH(O$5)-MONTH($C6)+1))))/$F6)) -> 0 | ... AQ6: =IF(OR($C6="",$D6="",$F6=0),0,IF(OR(AQ$5<=Projects!$C$2,((YEAR(AQ$5)-YEAR($C6))*12+MONTH(AQ$5)-MONTH($C6)+1)<1,((YEAR(AQ$5)-YEAR($C6))*12+MONTH(AQ$5)-MONTH($C6)+1)>$D6),0,$E6*IF($G6,1,N(INDEX(Phasing!$I6:$AF6,((YEAR(AQ$5)-YEAR($C6))*12+MONTH(AQ$5)-MONTH($C6)+1))))/$F6)) -> 0
A7: 2 | B7: =IF(Projects!B7="","",Projects!B7) | C7: =IF(Projects!D7="","",Projects!D7) | D7: =IF(Projects!E7="","",Projects!E7) | E7: =IF(Projects!B7="",0,N(Projects!I7)) -> 0 | F7: =Phasing!G7 -> 0 | G7: =Phasing!D7=0 -> TRUE | H7: =IF(OR($C7="",$D7="",$F7=0),0,IF(OR(H$5<=Projects!$C$2,((YEAR(H$5)-YEAR($C7))*12+MONTH(H$5)-MONTH($C7)+1)<1,((YEAR(H$5)-YEAR($C7))*12+MONTH(H$5)-MONTH($C7)+1)>$D7),0,$E7*IF($G7,1,N(INDEX(Phasing!$I7:$AF7,((YEAR(H$5)-YEAR($C7))*12+MONTH(H$5)-MONTH($C7)+1))))/$F7)) -> 0 | I7: =IF(OR($C7="",$D7="",$F7=0),0,IF(OR(I$5<=Projects!$C$2,((YEAR(I$5)-YEAR($C7))*12+MONTH(I$5)-MONTH($C7)+1)<1,((YEAR(I$5)-YEAR($C7))*12+MONTH(I$5)-MONTH($C7)+1)>$D7),0,$E7*IF($G7,1,N(INDEX(Phasing!$I7:$AF7,((YEAR(I$5)-YEAR($C7))*12+MONTH(I$5)-MONTH($C7)+1))))/$F7)) -> 0 | J7: =IF(OR($C7="",$D7="",$F7=0),0,IF(OR(J$5<=Projects!$C$2,((YEAR(J$5)-YEAR($C7))*12+MONTH(J$5)-MONTH($C7)+1)<1,((YEAR(J$5)-YEAR($C7))*12+MONTH(J$5)-MONTH($C7)+1)>$D7),0,$E7*IF($G7,1,N(INDEX(Phasing!$I7:$AF7,((YEAR(J$5)-YEAR($C7))*12+MONTH(J$5)-MONTH($C7)+1))))/$F7)) -> 0 | K7: =IF(OR($C7="",$D7="",$F7=0),0,IF(OR(K$5<=Projects!$C$2,((YEAR(K$5)-YEAR($C7))*12+MONTH(K$5)-MONTH($C7)+1)<1,((YEAR(K$5)-YEAR($C7))*12+MONTH(K$5)-MONTH($C7)+1)>$D7),0,$E7*IF($G7,1,N(INDEX(Phasing!$I7:$AF7,((YEAR(K$5)-YEAR($C7))*12+MONTH(K$5)-MONTH($C7)+1))))/$F7)) -> 0 | L7: =IF(OR($C7="",$D7="",$F7=0),0,IF(OR(L$5<=Projects!$C$2,((YEAR(L$5)-YEAR($C7))*12+MONTH(L$5)-MONTH($C7)+1)<1,((YEAR(L$5)-YEAR($C7))*12+MONTH(L$5)-MONTH($C7)+1)>$D7),0,$E7*IF($G7,1,N(INDEX(Phasing!$I7:$AF7,((YEAR(L$5)-YEAR($C7))*12+MONTH(L$5)-MONTH($C7)+1))))/$F7)) -> 0 | M7: =IF(OR($C7="",$D7="",$F7=0),0,IF(OR(M$5<=Projects!$C$2,((YEAR(M$5)-YEAR($C7))*12+MONTH(M$5)-MONTH($C7)+1)<1,((YEAR(M$5)-YEAR($C7))*12+MONTH(M$5)-MONTH($C7)+1)>$D7),0,$E7*IF($G7,1,N(INDEX(Phasing!$I7:$AF7,((YEAR(M$5)-YEAR($C7))*12+MONTH(M$5)-MONTH($C7)+1))))/$F7)) -> 0 | N7: =IF(OR($C7="",$D7="",$F7=0),0,IF(OR(N$5<=Projects!$C$2,((YEAR(N$5)-YEAR($C7))*12+MONTH(N$5)-MONTH($C7)+1)<1,((YEAR(N$5)-YEAR($C7))*12+MONTH(N$5)-MONTH($C7)+1)>$D7),0,$E7*IF($G7,1,N(INDEX(Phasing!$I7:$AF7,((YEAR(N$5)-YEAR($C7))*12+MONTH(N$5)-MONTH($C7)+1))))/$F7)) -> 0 | O7: =IF(OR($C7="",$D7="",$F7=0),0,IF(OR(O$5<=Projects!$C$2,((YEAR(O$5)-YEAR($C7))*12+MONTH(O$5)-MONTH($C7)+1)<1,((YEAR(O$5)-YEAR($C7))*12+MONTH(O$5)-MONTH($C7)+1)>$D7),0,$E7*IF($G7,1,N(INDEX(Phasing!$I7:$AF7,((YEAR(O$5)-YEAR($C7))*12+MONTH(O$5)-MONTH($C7)+1))))/$F7)) -> 0 | ... AQ7: =IF(OR($C7="",$D7="",$F7=0),0,IF(OR(AQ$5<=Projects!$C$2,((YEAR(AQ$5)-YEAR($C7))*12+MONTH(AQ$5)-MONTH($C7)+1)<1,((YEAR(AQ$5)-YEAR($C7))*12+MONTH(AQ$5)-MONTH($C7)+1)>$D7),0,$E7*IF($G7,1,N(INDEX(Phasing!$I7:$AF7,((YEAR(AQ$5)-YEAR($C7))*12+MONTH(AQ$5)-MONTH($C7)+1))))/$F7)) -> 0
A8: 3 | B8: =IF(Projects!B8="","",Projects!B8) | C8: =IF(Projects!D8="","",Projects!D8) | D8: =IF(Projects!E8="","",Projects!E8) | E8: =IF(Projects!B8="",0,N(Projects!I8)) -> 0 | F8: =Phasing!G8 -> 0 | G8: =Phasing!D8=0 -> TRUE | H8: =IF(OR($C8="",$D8="",$F8=0),0,IF(OR(H$5<=Projects!$C$2,((YEAR(H$5)-YEAR($C8))*12+MONTH(H$5)-MONTH($C8)+1)<1,((YEAR(H$5)-YEAR($C8))*12+MONTH(H$5)-MONTH($C8)+1)>$D8),0,$E8*IF($G8,1,N(INDEX(Phasing!$I8:$AF8,((YEAR(H$5)-YEAR($C8))*12+MONTH(H$5)-MONTH($C8)+1))))/$F8)) -> 0 | I8: =IF(OR($C8="",$D8="",$F8=0),0,IF(OR(I$5<=Projects!$C$2,((YEAR(I$5)-YEAR($C8))*12+MONTH(I$5)-MONTH($C8)+1)<1,((YEAR(I$5)-YEAR($C8))*12+MONTH(I$5)-MONTH($C8)+1)>$D8),0,$E8*IF($G8,1,N(INDEX(Phasing!$I8:$AF8,((YEAR(I$5)-YEAR($C8))*12+MONTH(I$5)-MONTH($C8)+1))))/$F8)) -> 0 | J8: =IF(OR($C8="",$D8="",$F8=0),0,IF(OR(J$5<=Projects!$C$2,((YEAR(J$5)-YEAR($C8))*12+MONTH(J$5)-MONTH($C8)+1)<1,((YEAR(J$5)-YEAR($C8))*12+MONTH(J$5)-MONTH($C8)+1)>$D8),0,$E8*IF($G8,1,N(INDEX(Phasing!$I8:$AF8,((YEAR(J$5)-YEAR($C8))*12+MONTH(J$5)-MONTH($C8)+1))))/$F8)) -> 0 | K8: =IF(OR($C8="",$D8="",$F8=0),0,IF(OR(K$5<=Projects!$C$2,((YEAR(K$5)-YEAR($C8))*12+MONTH(K$5)-MONTH($C8)+1)<1,((YEAR(K$5)-YEAR($C8))*12+MONTH(K$5)-MONTH($C8)+1)>$D8),0,$E8*IF($G8,1,N(INDEX(Phasing!$I8:$AF8,((YEAR(K$5)-YEAR($C8))*12+MONTH(K$5)-MONTH($C8)+1))))/$F8)) -> 0 | L8: =IF(OR($C8="",$D8="",$F8=0),0,IF(OR(L$5<=Projects!$C$2,((YEAR(L$5)-YEAR($C8))*12+MONTH(L$5)-MONTH($C8)+1)<1,((YEAR(L$5)-YEAR($C8))*12+MONTH(L$5)-MONTH($C8)+1)>$D8),0,$E8*IF($G8,1,N(INDEX(Phasing!$I8:$AF8,((YEAR(L$5)-YEAR($C8))*12+MONTH(L$5)-MONTH($C8)+1))))/$F8)) -> 0 | M8: =IF(OR($C8="",$D8="",$F8=0),0,IF(OR(M$5<=Projects!$C$2,((YEAR(M$5)-YEAR($C8))*12+MONTH(M$5)-MONTH($C8)+1)<1,((YEAR(M$5)-YEAR($C8))*12+MONTH(M$5)-MONTH($C8)+1)>$D8),0,$E8*IF($G8,1,N(INDEX(Phasing!$I8:$AF8,((YEAR(M$5)-YEAR($C8))*12+MONTH(M$5)-MONTH($C8)+1))))/$F8)) -> 0 | N8: =IF(OR($C8="",$D8="",$F8=0),0,IF(OR(N$5<=Projects!$C$2,((YEAR(N$5)-YEAR($C8))*12+MONTH(N$5)-MONTH($C8)+1)<1,((YEAR(N$5)-YEAR($C8))*12+MONTH(N$5)-MONTH($C8)+1)>$D8),0,$E8*IF($G8,1,N(INDEX(Phasing!$I8:$AF8,((YEAR(N$5)-YEAR($C8))*12+MONTH(N$5)-MONTH($C8)+1))))/$F8)) -> 0 | O8: =IF(OR($C8="",$D8="",$F8=0),0,IF(OR(O$5<=Projects!$C$2,((YEAR(O$5)-YEAR($C8))*12+MONTH(O$5)-MONTH($C8)+1)<1,((YEAR(O$5)-YEAR($C8))*12+MONTH(O$5)-MONTH($C8)+1)>$D8),0,$E8*IF($G8,1,N(INDEX(Phasing!$I8:$AF8,((YEAR(O$5)-YEAR($C8))*12+MONTH(O$5)-MONTH($C8)+1))))/$F8)) -> 0 | ... AQ8: =IF(OR($C8="",$D8="",$F8=0),0,IF(OR(AQ$5<=Projects!$C$2,((YEAR(AQ$5)-YEAR($C8))*12+MONTH(AQ$5)-MONTH($C8)+1)<1,((YEAR(AQ$5)-YEAR($C8))*12+MONTH(AQ$5)-MONTH($C8)+1)>$D8),0,$E8*IF($G8,1,N(INDEX(Phasing!$I8:$AF8,((YEAR(AQ$5)-YEAR($C8))*12+MONTH(AQ$5)-MONTH($C8)+1))))/$F8)) -> 0
A9: 4 | B9: =IF(Projects!B9="","",Projects!B9) | C9: =IF(Projects!D9="","",Projects!D9) | D9: =IF(Projects!E9="","",Projects!E9) | E9: =IF(Projects!B9="",0,N(Projects!I9)) -> 0 | F9: =Phasing!G9 -> 0 | G9: =Phasing!D9=0 -> TRUE | H9: =IF(OR($C9="",$D9="",$F9=0),0,IF(OR(H$5<=Projects!$C$2,((YEAR(H$5)-YEAR($C9))*12+MONTH(H$5)-MONTH($C9)+1)<1,((YEAR(H$5)-YEAR($C9))*12+MONTH(H$5)-MONTH($C9)+1)>$D9),0,$E9*IF($G9,1,N(INDEX(Phasing!$I9:$AF9,((YEAR(H$5)-YEAR($C9))*12+MONTH(H$5)-MONTH($C9)+1))))/$F9)) -> 0 | I9: =IF(OR($C9="",$D9="",$F9=0),0,IF(OR(I$5<=Projects!$C$2,((YEAR(I$5)-YEAR($C9))*12+MONTH(I$5)-MONTH($C9)+1)<1,((YEAR(I$5)-YEAR($C9))*12+MONTH(I$5)-MONTH($C9)+1)>$D9),0,$E9*IF($G9,1,N(INDEX(Phasing!$I9:$AF9,((YEAR(I$5)-YEAR($C9))*12+MONTH(I$5)-MONTH($C9)+1))))/$F9)) -> 0 | J9: =IF(OR($C9="",$D9="",$F9=0),0,IF(OR(J$5<=Projects!$C$2,((YEAR(J$5)-YEAR($C9))*12+MONTH(J$5)-MONTH($C9)+1)<1,((YEAR(J$5)-YEAR($C9))*12+MONTH(J$5)-MONTH($C9)+1)>$D9),0,$E9*IF($G9,1,N(INDEX(Phasing!$I9:$AF9,((YEAR(J$5)-YEAR($C9))*12+MONTH(J$5)-MONTH($C9)+1))))/$F9)) -> 0 | K9: =IF(OR($C9="",$D9="",$F9=0),0,IF(OR(K$5<=Projects!$C$2,((YEAR(K$5)-YEAR($C9))*12+MONTH(K$5)-MONTH($C9)+1)<1,((YEAR(K$5)-YEAR($C9))*12+MONTH(K$5)-MONTH($C9)+1)>$D9),0,$E9*IF($G9,1,N(INDEX(Phasing!$I9:$AF9,((YEAR(K$5)-YEAR($C9))*12+MONTH(K$5)-MONTH($C9)+1))))/$F9)) -> 0 | L9: =IF(OR($C9="",$D9="",$F9=0),0,IF(OR(L$5<=Projects!$C$2,((YEAR(L$5)-YEAR($C9))*12+MONTH(L$5)-MONTH($C9)+1)<1,((YEAR(L$5)-YEAR($C9))*12+MONTH(L$5)-MONTH($C9)+1)>$D9),0,$E9*IF($G9,1,N(INDEX(Phasing!$I9:$AF9,((YEAR(L$5)-YEAR($C9))*12+MONTH(L$5)-MONTH($C9)+1))))/$F9)) -> 0 | M9: =IF(OR($C9="",$D9="",$F9=0),0,IF(OR(M$5<=Projects!$C$2,((YEAR(M$5)-YEAR($C9))*12+MONTH(M$5)-MONTH($C9)+1)<1,((YEAR(M$5)-YEAR($C9))*12+MONTH(M$5)-MONTH($C9)+1)>$D9),0,$E9*IF($G9,1,N(INDEX(Phasing!$I9:$AF9,((YEAR(M$5)-YEAR($C9))*12+MONTH(M$5)-MONTH($C9)+1))))/$F9)) -> 0 | N9: =IF(OR($C9="",$D9="",$F9=0),0,IF(OR(N$5<=Projects!$C$2,((YEAR(N$5)-YEAR($C9))*12+MONTH(N$5)-MONTH($C9)+1)<1,((YEAR(N$5)-YEAR($C9))*12+MONTH(N$5)-MONTH($C9)+1)>$D9),0,$E9*IF($G9,1,N(INDEX(Phasing!$I9:$AF9,((YEAR(N$5)-YEAR($C9))*12+MONTH(N$5)-MONTH($C9)+1))))/$F9)) -> 0 | O9: =IF(OR($C9="",$D9="",$F9=0),0,IF(OR(O$5<=Projects!$C$2,((YEAR(O$5)-YEAR($C9))*12+MONTH(O$5)-MONTH($C9)+1)<1,((YEAR(O$5)-YEAR($C9))*12+MONTH(O$5)-MONTH($C9)+1)>$D9),0,$E9*IF($G9,1,N(INDEX(Phasing!$I9:$AF9,((YEAR(O$5)-YEAR($C9))*12+MONTH(O$5)-MONTH($C9)+1))))/$F9)) -> 0 | ... AQ9: =IF(OR($C9="",$D9="",$F9=0),0,IF(OR(AQ$5<=Projects!$C$2,((YEAR(AQ$5)-YEAR($C9))*12+MONTH(AQ$5)-MONTH($C9)+1)<1,((YEAR(AQ$5)-YEAR($C9))*12+MONTH(AQ$5)-MONTH($C9)+1)>$D9),0,$E9*IF($G9,1,N(INDEX(Phasing!$I9:$AF9,((YEAR(AQ$5)-YEAR($C9))*12+MONTH(AQ$5)-MONTH($C9)+1))))/$F9)) -> 0
A10: 5 | B10: =IF(Projects!B10="","",Projects!B10) | C10: =IF(Projects!D10="","",Projects!D10) | D10: =IF(Projects!E10="","",Projects!E10) | E10: =IF(Projects!B10="",0,N(Projects!I10)) -> 0 | F10: =Phasing!G10 -> 0 | G10: =Phasing!D10=0 -> TRUE | H10: =IF(OR($C10="",$D10="",$F10=0),0,IF(OR(H$5<=Projects!$C$2,((YEAR(H$5)-YEAR($C10))*12+MONTH(H$5)-MONTH($C10)+1)<1,((YEAR(H$5)-YEAR($C10))*12+MONTH(H$5)-MONTH($C10)+1)>$D10),0,$E10*IF($G10,1,N(INDEX(Phasing!$I10:$AF10,((YEAR(H$5)-YEAR($C10))*12+MONTH(H$5)-MONTH($C10)+1))))/$F10)) -> 0 | I10: =IF(OR($C10="",$D10="",$F10=0),0,IF(OR(I$5<=Projects!$C$2,((YEAR(I$5)-YEAR($C10))*12+MONTH(I$5)-MONTH($C10)+1)<1,((YEAR(I$5)-YEAR($C10))*12+MONTH(I$5)-MONTH($C10)+1)>$D10),0,$E10*IF($G10,1,N(INDEX(Phasing!$I10:$AF10,((YEAR(I$5)-YEAR($C10))*12+MONTH(I$5)-MONTH($C10)+1))))/$F10)) -> 0 | J10: =IF(OR($C10="",$D10="",$F10=0),0,IF(OR(J$5<=Projects!$C$2,((YEAR(J$5)-YEAR($C10))*12+MONTH(J$5)-MONTH($C10)+1)<1,((YEAR(J$5)-YEAR($C10))*12+MONTH(J$5)-MONTH($C10)+1)>$D10),0,$E10*IF($G10,1,N(INDEX(Phasing!$I10:$AF10,((YEAR(J$5)-YEAR($C10))*12+MONTH(J$5)-MONTH($C10)+1))))/$F10)) -> 0 | K10: =IF(OR($C10="",$D10="",$F10=0),0,IF(OR(K$5<=Projects!$C$2,((YEAR(K$5)-YEAR($C10))*12+MONTH(K$5)-MONTH($C10)+1)<1,((YEAR(K$5)-YEAR($C10))*12+MONTH(K$5)-MONTH($C10)+1)>$D10),0,$E10*IF($G10,1,N(INDEX(Phasing!$I10:$AF10,((YEAR(K$5)-YEAR($C10))*12+MONTH(K$5)-MONTH($C10)+1))))/$F10)) -> 0 | L10: =IF(OR($C10="",$D10="",$F10=0),0,IF(OR(L$5<=Projects!$C$2,((YEAR(L$5)-YEAR($C10))*12+MONTH(L$5)-MONTH($C10)+1)<1,((YEAR(L$5)-YEAR($C10))*12+MONTH(L$5)-MONTH($C10)+1)>$D10),0,$E10*IF($G10,1,N(INDEX(Phasing!$I10:$AF10,((YEAR(L$5)-YEAR($C10))*12+MONTH(L$5)-MONTH($C10)+1))))/$F10)) -> 0 | M10: =IF(OR($C10="",$D10="",$F10=0),0,IF(OR(M$5<=Projects!$C$2,((YEAR(M$5)-YEAR($C10))*12+MONTH(M$5)-MONTH($C10)+1)<1,((YEAR(M$5)-YEAR($C10))*12+MONTH(M$5)-MONTH($C10)+1)>$D10),0,$E10*IF($G10,1,N(INDEX(Phasing!$I10:$AF10,((YEAR(M$5)-YEAR($C10))*12+MONTH(M$5)-MONTH($C10)+1))))/$F10)) -> 0 | N10: =IF(OR($C10="",$D10="",$F10=0),0,IF(OR(N$5<=Projects!$C$2,((YEAR(N$5)-YEAR($C10))*12+MONTH(N$5)-MONTH($C10)+1)<1,((YEAR(N$5)-YEAR($C10))*12+MONTH(N$5)-MONTH($C10)+1)>$D10),0,$E10*IF($G10,1,N(INDEX(Phasing!$I10:$AF10,((YEAR(N$5)-YEAR($C10))*12+MONTH(N$5)-MONTH($C10)+1))))/$F10)) -> 0 | O10: =IF(OR($C10="",$D10="",$F10=0),0,IF(OR(O$5<=Projects!$C$2,((YEAR(O$5)-YEAR($C10))*12+MONTH(O$5)-MONTH($C10)+1)<1,((YEAR(O$5)-YEAR($C10))*12+MONTH(O$5)-MONTH($C10)+1)>$D10),0,$E10*IF($G10,1,N(INDEX(Phasing!$I10:$AF10,((YEAR(O$5)-YEAR($C10))*12+MONTH(O$5)-MONTH($C10)+1))))/$F10)) -> 0 | ... AQ10: =IF(OR($C10="",$D10="",$F10=0),0,IF(OR(AQ$5<=Projects!$C$2,((YEAR(AQ$5)-YEAR($C10))*12+MONTH(AQ$5)-MONTH($C10)+1)<1,((YEAR(AQ$5)-YEAR($C10))*12+MONTH(AQ$5)-MONTH($C10)+1)>$D10),0,$E10*IF($G10,1,N(INDEX(Phasing!$I10:$AF10,((YEAR(AQ$5)-YEAR($C10))*12+MONTH(AQ$5)-MONTH($C10)+1))))/$F10)) -> 0
A11: 6 | B11: =IF(Projects!B11="","",Projects!B11) | C11: =IF(Projects!D11="","",Projects!D11) | D11: =IF(Projects!E11="","",Projects!E11) | E11: =IF(Projects!B11="",0,N(Projects!I11)) -> 0 | F11: =Phasing!G11 -> 0 | G11: =Phasing!D11=0 -> TRUE | H11: =IF(OR($C11="",$D11="",$F11=0),0,IF(OR(H$5<=Projects!$C$2,((YEAR(H$5)-YEAR($C11))*12+MONTH(H$5)-MONTH($C11)+1)<1,((YEAR(H$5)-YEAR($C11))*12+MONTH(H$5)-MONTH($C11)+1)>$D11),0,$E11*IF($G11,1,N(INDEX(Phasing!$I11:$AF11,((YEAR(H$5)-YEAR($C11))*12+MONTH(H$5)-MONTH($C11)+1))))/$F11)) -> 0 | I11: =IF(OR($C11="",$D11="",$F11=0),0,IF(OR(I$5<=Projects!$C$2,((YEAR(I$5)-YEAR($C11))*12+MONTH(I$5)-MONTH($C11)+1)<1,((YEAR(I$5)-YEAR($C11))*12+MONTH(I$5)-MONTH($C11)+1)>$D11),0,$E11*IF($G11,1,N(INDEX(Phasing!$I11:$AF11,((YEAR(I$5)-YEAR($C11))*12+MONTH(I$5)-MONTH($C11)+1))))/$F11)) -> 0 | J11: =IF(OR($C11="",$D11="",$F11=0),0,IF(OR(J$5<=Projects!$C$2,((YEAR(J$5)-YEAR($C11))*12+MONTH(J$5)-MONTH($C11)+1)<1,((YEAR(J$5)-YEAR($C11))*12+MONTH(J$5)-MONTH($C11)+1)>$D11),0,$E11*IF($G11,1,N(INDEX(Phasing!$I11:$AF11,((YEAR(J$5)-YEAR($C11))*12+MONTH(J$5)-MONTH($C11)+1))))/$F11)) -> 0 | K11: =IF(OR($C11="",$D11="",$F11=0),0,IF(OR(K$5<=Projects!$C$2,((YEAR(K$5)-YEAR($C11))*12+MONTH(K$5)-MONTH($C11)+1)<1,((YEAR(K$5)-YEAR($C11))*12+MONTH(K$5)-MONTH($C11)+1)>$D11),0,$E11*IF($G11,1,N(INDEX(Phasing!$I11:$AF11,((YEAR(K$5)-YEAR($C11))*12+MONTH(K$5)-MONTH($C11)+1))))/$F11)) -> 0 | L11: =IF(OR($C11="",$D11="",$F11=0),0,IF(OR(L$5<=Projects!$C$2,((YEAR(L$5)-YEAR($C11))*12+MONTH(L$5)-MONTH($C11)+1)<1,((YEAR(L$5)-YEAR($C11))*12+MONTH(L$5)-MONTH($C11)+1)>$D11),0,$E11*IF($G11,1,N(INDEX(Phasing!$I11:$AF11,((YEAR(L$5)-YEAR($C11))*12+MONTH(L$5)-MONTH($C11)+1))))/$F11)) -> 0 | M11: =IF(OR($C11="",$D11="",$F11=0),0,IF(OR(M$5<=Projects!$C$2,((YEAR(M$5)-YEAR($C11))*12+MONTH(M$5)-MONTH($C11)+1)<1,((YEAR(M$5)-YEAR($C11))*12+MONTH(M$5)-MONTH($C11)+1)>$D11),0,$E11*IF($G11,1,N(INDEX(Phasing!$I11:$AF11,((YEAR(M$5)-YEAR($C11))*12+MONTH(M$5)-MONTH($C11)+1))))/$F11)) -> 0 | N11: =IF(OR($C11="",$D11="",$F11=0),0,IF(OR(N$5<=Projects!$C$2,((YEAR(N$5)-YEAR($C11))*12+MONTH(N$5)-MONTH($C11)+1)<1,((YEAR(N$5)-YEAR($C11))*12+MONTH(N$5)-MONTH($C11)+1)>$D11),0,$E11*IF($G11,1,N(INDEX(Phasing!$I11:$AF11,((YEAR(N$5)-YEAR($C11))*12+MONTH(N$5)-MONTH($C11)+1))))/$F11)) -> 0 | O11: =IF(OR($C11="",$D11="",$F11=0),0,IF(OR(O$5<=Projects!$C$2,((YEAR(O$5)-YEAR($C11))*12+MONTH(O$5)-MONTH($C11)+1)<1,((YEAR(O$5)-YEAR($C11))*12+MONTH(O$5)-MONTH($C11)+1)>$D11),0,$E11*IF($G11,1,N(INDEX(Phasing!$I11:$AF11,((YEAR(O$5)-YEAR($C11))*12+MONTH(O$5)-MONTH($C11)+1))))/$F11)) -> 0 | ... AQ11: =IF(OR($C11="",$D11="",$F11=0),0,IF(OR(AQ$5<=Projects!$C$2,((YEAR(AQ$5)-YEAR($C11))*12+MONTH(AQ$5)-MONTH($C11)+1)<1,((YEAR(AQ$5)-YEAR($C11))*12+MONTH(AQ$5)-MONTH($C11)+1)>$D11),0,$E11*IF($G11,1,N(INDEX(Phasing!$I11:$AF11,((YEAR(AQ$5)-YEAR($C11))*12+MONTH(AQ$5)-MONTH($C11)+1))))/$F11)) -> 0
A12: 7 | B12: =IF(Projects!B12="","",Projects!B12) | C12: =IF(Projects!D12="","",Projects!D12) | D12: =IF(Projects!E12="","",Projects!E12) | E12: =IF(Projects!B12="",0,N(Projects!I12)) -> 0 | F12: =Phasing!G12 -> 0 | G12: =Phasing!D12=0 -> TRUE | H12: =IF(OR($C12="",$D12="",$F12=0),0,IF(OR(H$5<=Projects!$C$2,((YEAR(H$5)-YEAR($C12))*12+MONTH(H$5)-MONTH($C12)+1)<1,((YEAR(H$5)-YEAR($C12))*12+MONTH(H$5)-MONTH($C12)+1)>$D12),0,$E12*IF($G12,1,N(INDEX(Phasing!$I12:$AF12,((YEAR(H$5)-YEAR($C12))*12+MONTH(H$5)-MONTH($C12)+1))))/$F12)) -> 0 | I12: =IF(OR($C12="",$D12="",$F12=0),0,IF(OR(I$5<=Projects!$C$2,((YEAR(I$5)-YEAR($C12))*12+MONTH(I$5)-MONTH($C12)+1)<1,((YEAR(I$5)-YEAR($C12))*12+MONTH(I$5)-MONTH($C12)+1)>$D12),0,$E12*IF($G12,1,N(INDEX(Phasing!$I12:$AF12,((YEAR(I$5)-YEAR($C12))*12+MONTH(I$5)-MONTH($C12)+1))))/$F12)) -> 0 | J12: =IF(OR($C12="",$D12="",$F12=0),0,IF(OR(J$5<=Projects!$C$2,((YEAR(J$5)-YEAR($C12))*12+MONTH(J$5)-MONTH($C12)+1)<1,((YEAR(J$5)-YEAR($C12))*12+MONTH(J$5)-MONTH($C12)+1)>$D12),0,$E12*IF($G12,1,N(INDEX(Phasing!$I12:$AF12,((YEAR(J$5)-YEAR($C12))*12+MONTH(J$5)-MONTH($C12)+1))))/$F12)) -> 0 | K12: =IF(OR($C12="",$D12="",$F12=0),0,IF(OR(K$5<=Projects!$C$2,((YEAR(K$5)-YEAR($C12))*12+MONTH(K$5)-MONTH($C12)+1)<1,((YEAR(K$5)-YEAR($C12))*12+MONTH(K$5)-MONTH($C12)+1)>$D12),0,$E12*IF($G12,1,N(INDEX(Phasing!$I12:$AF12,((YEAR(K$5)-YEAR($C12))*12+MONTH(K$5)-MONTH($C12)+1))))/$F12)) -> 0 | L12: =IF(OR($C12="",$D12="",$F12=0),0,IF(OR(L$5<=Projects!$C$2,((YEAR(L$5)-YEAR($C12))*12+MONTH(L$5)-MONTH($C12)+1)<1,((YEAR(L$5)-YEAR($C12))*12+MONTH(L$5)-MONTH($C12)+1)>$D12),0,$E12*IF($G12,1,N(INDEX(Phasing!$I12:$AF12,((YEAR(L$5)-YEAR($C12))*12+MONTH(L$5)-MONTH($C12)+1))))/$F12)) -> 0 | M12: =IF(OR($C12="",$D12="",$F12=0),0,IF(OR(M$5<=Projects!$C$2,((YEAR(M$5)-YEAR($C12))*12+MONTH(M$5)-MONTH($C12)+1)<1,((YEAR(M$5)-YEAR($C12))*12+MONTH(M$5)-MONTH($C12)+1)>$D12),0,$E12*IF($G12,1,N(INDEX(Phasing!$I12:$AF12,((YEAR(M$5)-YEAR($C12))*12+MONTH(M$5)-MONTH($C12)+1))))/$F12)) -> 0 | N12: =IF(OR($C12="",$D12="",$F12=0),0,IF(OR(N$5<=Projects!$C$2,((YEAR(N$5)-YEAR($C12))*12+MONTH(N$5)-MONTH($C12)+1)<1,((YEAR(N$5)-YEAR($C12))*12+MONTH(N$5)-MONTH($C12)+1)>$D12),0,$E12*IF($G12,1,N(INDEX(Phasing!$I12:$AF12,((YEAR(N$5)-YEAR($C12))*12+MONTH(N$5)-MONTH($C12)+1))))/$F12)) -> 0 | O12: =IF(OR($C12="",$D12="",$F12=0),0,IF(OR(O$5<=Projects!$C$2,((YEAR(O$5)-YEAR($C12))*12+MONTH(O$5)-MONTH($C12)+1)<1,((YEAR(O$5)-YEAR($C12))*12+MONTH(O$5)-MONTH($C12)+1)>$D12),0,$E12*IF($G12,1,N(INDEX(Phasing!$I12:$AF12,((YEAR(O$5)-YEAR($C12))*12+MONTH(O$5)-MONTH($C12)+1))))/$F12)) -> 0 | ... AQ12: =IF(OR($C12="",$D12="",$F12=0),0,IF(OR(AQ$5<=Projects!$C$2,((YEAR(AQ$5)-YEAR($C12))*12+MONTH(AQ$5)-MONTH($C12)+1)<1,((YEAR(AQ$5)-YEAR($C12))*12+MONTH(AQ$5)-MONTH($C12)+1)>$D12),0,$E12*IF($G12,1,N(INDEX(Phasing!$I12:$AF12,((YEAR(AQ$5)-YEAR($C12))*12+MONTH(AQ$5)-MONTH($C12)+1))))/$F12)) -> 0
A13: 8 | B13: =IF(Projects!B13="","",Projects!B13) | C13: =IF(Projects!D13="","",Projects!D13) | D13: =IF(Projects!E13="","",Projects!E13) | E13: =IF(Projects!B13="",0,N(Projects!I13)) -> 0 | F13: =Phasing!G13 -> 0 | G13: =Phasing!D13=0 -> TRUE | H13: =IF(OR($C13="",$D13="",$F13=0),0,IF(OR(H$5<=Projects!$C$2,((YEAR(H$5)-YEAR($C13))*12+MONTH(H$5)-MONTH($C13)+1)<1,((YEAR(H$5)-YEAR($C13))*12+MONTH(H$5)-MONTH($C13)+1)>$D13),0,$E13*IF($G13,1,N(INDEX(Phasing!$I13:$AF13,((YEAR(H$5)-YEAR($C13))*12+MONTH(H$5)-MONTH($C13)+1))))/$F13)) -> 0 | I13: =IF(OR($C13="",$D13="",$F13=0),0,IF(OR(I$5<=Projects!$C$2,((YEAR(I$5)-YEAR($C13))*12+MONTH(I$5)-MONTH($C13)+1)<1,((YEAR(I$5)-YEAR($C13))*12+MONTH(I$5)-MONTH($C13)+1)>$D13),0,$E13*IF($G13,1,N(INDEX(Phasing!$I13:$AF13,((YEAR(I$5)-YEAR($C13))*12+MONTH(I$5)-MONTH($C13)+1))))/$F13)) -> 0 | J13: =IF(OR($C13="",$D13="",$F13=0),0,IF(OR(J$5<=Projects!$C$2,((YEAR(J$5)-YEAR($C13))*12+MONTH(J$5)-MONTH($C13)+1)<1,((YEAR(J$5)-YEAR($C13))*12+MONTH(J$5)-MONTH($C13)+1)>$D13),0,$E13*IF($G13,1,N(INDEX(Phasing!$I13:$AF13,((YEAR(J$5)-YEAR($C13))*12+MONTH(J$5)-MONTH($C13)+1))))/$F13)) -> 0 | K13: =IF(OR($C13="",$D13="",$F13=0),0,IF(OR(K$5<=Projects!$C$2,((YEAR(K$5)-YEAR($C13))*12+MONTH(K$5)-MONTH($C13)+1)<1,((YEAR(K$5)-YEAR($C13))*12+MONTH(K$5)-MONTH($C13)+1)>$D13),0,$E13*IF($G13,1,N(INDEX(Phasing!$I13:$AF13,((YEAR(K$5)-YEAR($C13))*12+MONTH(K$5)-MONTH($C13)+1))))/$F13)) -> 0 | L13: =IF(OR($C13="",$D13="",$F13=0),0,IF(OR(L$5<=Projects!$C$2,((YEAR(L$5)-YEAR($C13))*12+MONTH(L$5)-MONTH($C13)+1)<1,((YEAR(L$5)-YEAR($C13))*12+MONTH(L$5)-MONTH($C13)+1)>$D13),0,$E13*IF($G13,1,N(INDEX(Phasing!$I13:$AF13,((YEAR(L$5)-YEAR($C13))*12+MONTH(L$5)-MONTH($C13)+1))))/$F13)) -> 0 | M13: =IF(OR($C13="",$D13="",$F13=0),0,IF(OR(M$5<=Projects!$C$2,((YEAR(M$5)-YEAR($C13))*12+MONTH(M$5)-MONTH($C13)+1)<1,((YEAR(M$5)-YEAR($C13))*12+MONTH(M$5)-MONTH($C13)+1)>$D13),0,$E13*IF($G13,1,N(INDEX(Phasing!$I13:$AF13,((YEAR(M$5)-YEAR($C13))*12+MONTH(M$5)-MONTH($C13)+1))))/$F13)) -> 0 | N13: =IF(OR($C13="",$D13="",$F13=0),0,IF(OR(N$5<=Projects!$C$2,((YEAR(N$5)-YEAR($C13))*12+MONTH(N$5)-MONTH($C13)+1)<1,((YEAR(N$5)-YEAR($C13))*12+MONTH(N$5)-MONTH($C13)+1)>$D13),0,$E13*IF($G13,1,N(INDEX(Phasing!$I13:$AF13,((YEAR(N$5)-YEAR($C13))*12+MONTH(N$5)-MONTH($C13)+1))))/$F13)) -> 0 | O13: =IF(OR($C13="",$D13="",$F13=0),0,IF(OR(O$5<=Projects!$C$2,((YEAR(O$5)-YEAR($C13))*12+MONTH(O$5)-MONTH($C13)+1)<1,((YEAR(O$5)-YEAR($C13))*12+MONTH(O$5)-MONTH($C13)+1)>$D13),0,$E13*IF($G13,1,N(INDEX(Phasing!$I13:$AF13,((YEAR(O$5)-YEAR($C13))*12+MONTH(O$5)-MONTH($C13)+1))))/$F13)) -> 0 | ... AQ13: =IF(OR($C13="",$D13="",$F13=0),0,IF(OR(AQ$5<=Projects!$C$2,((YEAR(AQ$5)-YEAR($C13))*12+MONTH(AQ$5)-MONTH($C13)+1)<1,((YEAR(AQ$5)-YEAR($C13))*12+MONTH(AQ$5)-MONTH($C13)+1)>$D13),0,$E13*IF($G13,1,N(INDEX(Phasing!$I13:$AF13,((YEAR(AQ$5)-YEAR($C13))*12+MONTH(AQ$5)-MONTH($C13)+1))))/$F13)) -> 0
A14: 9 | B14: =IF(Projects!B14="","",Projects!B14) | C14: =IF(Projects!D14="","",Projects!D14) | D14: =IF(Projects!E14="","",Projects!E14) | E14: =IF(Projects!B14="",0,N(Projects!I14)) -> 0 | F14: =Phasing!G14 -> 0 | G14: =Phasing!D14=0 -> TRUE | H14: =IF(OR($C14="",$D14="",$F14=0),0,IF(OR(H$5<=Projects!$C$2,((YEAR(H$5)-YEAR($C14))*12+MONTH(H$5)-MONTH($C14)+1)<1,((YEAR(H$5)-YEAR($C14))*12+MONTH(H$5)-MONTH($C14)+1)>$D14),0,$E14*IF($G14,1,N(INDEX(Phasing!$I14:$AF14,((YEAR(H$5)-YEAR($C14))*12+MONTH(H$5)-MONTH($C14)+1))))/$F14)) -> 0 | I14: =IF(OR($C14="",$D14="",$F14=0),0,IF(OR(I$5<=Projects!$C$2,((YEAR(I$5)-YEAR($C14))*12+MONTH(I$5)-MONTH($C14)+1)<1,((YEAR(I$5)-YEAR($C14))*12+MONTH(I$5)-MONTH($C14)+1)>$D14),0,$E14*IF($G14,1,N(INDEX(Phasing!$I14:$AF14,((YEAR(I$5)-YEAR($C14))*12+MONTH(I$5)-MONTH($C14)+1))))/$F14)) -> 0 | J14: =IF(OR($C14="",$D14="",$F14=0),0,IF(OR(J$5<=Projects!$C$2,((YEAR(J$5)-YEAR($C14))*12+MONTH(J$5)-MONTH($C14)+1)<1,((YEAR(J$5)-YEAR($C14))*12+MONTH(J$5)-MONTH($C14)+1)>$D14),0,$E14*IF($G14,1,N(INDEX(Phasing!$I14:$AF14,((YEAR(J$5)-YEAR($C14))*12+MONTH(J$5)-MONTH($C14)+1))))/$F14)) -> 0 | K14: =IF(OR($C14="",$D14="",$F14=0),0,IF(OR(K$5<=Projects!$C$2,((YEAR(K$5)-YEAR($C14))*12+MONTH(K$5)-MONTH($C14)+1)<1,((YEAR(K$5)-YEAR($C14))*12+MONTH(K$5)-MONTH($C14)+1)>$D14),0,$E14*IF($G14,1,N(INDEX(Phasing!$I14:$AF14,((YEAR(K$5)-YEAR($C14))*12+MONTH(K$5)-MONTH($C14)+1))))/$F14)) -> 0 | L14: =IF(OR($C14="",$D14="",$F14=0),0,IF(OR(L$5<=Projects!$C$2,((YEAR(L$5)-YEAR($C14))*12+MONTH(L$5)-MONTH($C14)+1)<1,((YEAR(L$5)-YEAR($C14))*12+MONTH(L$5)-MONTH($C14)+1)>$D14),0,$E14*IF($G14,1,N(INDEX(Phasing!$I14:$AF14,((YEAR(L$5)-YEAR($C14))*12+MONTH(L$5)-MONTH($C14)+1))))/$F14)) -> 0 | M14: =IF(OR($C14="",$D14="",$F14=0),0,IF(OR(M$5<=Projects!$C$2,((YEAR(M$5)-YEAR($C14))*12+MONTH(M$5)-MONTH($C14)+1)<1,((YEAR(M$5)-YEAR($C14))*12+MONTH(M$5)-MONTH($C14)+1)>$D14),0,$E14*IF($G14,1,N(INDEX(Phasing!$I14:$AF14,((YEAR(M$5)-YEAR($C14))*12+MONTH(M$5)-MONTH($C14)+1))))/$F14)) -> 0 | N14: =IF(OR($C14="",$D14="",$F14=0),0,IF(OR(N$5<=Projects!$C$2,((YEAR(N$5)-YEAR($C14))*12+MONTH(N$5)-MONTH($C14)+1)<1,((YEAR(N$5)-YEAR($C14))*12+MONTH(N$5)-MONTH($C14)+1)>$D14),0,$E14*IF($G14,1,N(INDEX(Phasing!$I14:$AF14,((YEAR(N$5)-YEAR($C14))*12+MONTH(N$5)-MONTH($C14)+1))))/$F14)) -> 0 | O14: =IF(OR($C14="",$D14="",$F14=0),0,IF(OR(O$5<=Projects!$C$2,((YEAR(O$5)-YEAR($C14))*12+MONTH(O$5)-MONTH($C14)+1)<1,((YEAR(O$5)-YEAR($C14))*12+MONTH(O$5)-MONTH($C14)+1)>$D14),0,$E14*IF($G14,1,N(INDEX(Phasing!$I14:$AF14,((YEAR(O$5)-YEAR($C14))*12+MONTH(O$5)-MONTH($C14)+1))))/$F14)) -> 0 | ... AQ14: =IF(OR($C14="",$D14="",$F14=0),0,IF(OR(AQ$5<=Projects!$C$2,((YEAR(AQ$5)-YEAR($C14))*12+MONTH(AQ$5)-MONTH($C14)+1)<1,((YEAR(AQ$5)-YEAR($C14))*12+MONTH(AQ$5)-MONTH($C14)+1)>$D14),0,$E14*IF($G14,1,N(INDEX(Phasing!$I14:$AF14,((YEAR(AQ$5)-YEAR($C14))*12+MONTH(AQ$5)-MONTH($C14)+1))))/$F14)) -> 0
A15: 10 | B15: =IF(Projects!B15="","",Projects!B15) | C15: =IF(Projects!D15="","",Projects!D15) | D15: =IF(Projects!E15="","",Projects!E15) | E15: =IF(Projects!B15="",0,N(Projects!I15)) -> 0 | F15: =Phasing!G15 -> 0 | G15: =Phasing!D15=0 -> TRUE | H15: =IF(OR($C15="",$D15="",$F15=0),0,IF(OR(H$5<=Projects!$C$2,((YEAR(H$5)-YEAR($C15))*12+MONTH(H$5)-MONTH($C15)+1)<1,((YEAR(H$5)-YEAR($C15))*12+MONTH(H$5)-MONTH($C15)+1)>$D15),0,$E15*IF($G15,1,N(INDEX(Phasing!$I15:$AF15,((YEAR(H$5)-YEAR($C15))*12+MONTH(H$5)-MONTH($C15)+1))))/$F15)) -> 0 | I15: =IF(OR($C15="",$D15="",$F15=0),0,IF(OR(I$5<=Projects!$C$2,((YEAR(I$5)-YEAR($C15))*12+MONTH(I$5)-MONTH($C15)+1)<1,((YEAR(I$5)-YEAR($C15))*12+MONTH(I$5)-MONTH($C15)+1)>$D15),0,$E15*IF($G15,1,N(INDEX(Phasing!$I15:$AF15,((YEAR(I$5)-YEAR($C15))*12+MONTH(I$5)-MONTH($C15)+1))))/$F15)) -> 0 | J15: =IF(OR($C15="",$D15="",$F15=0),0,IF(OR(J$5<=Projects!$C$2,((YEAR(J$5)-YEAR($C15))*12+MONTH(J$5)-MONTH($C15)+1)<1,((YEAR(J$5)-YEAR($C15))*12+MONTH(J$5)-MONTH($C15)+1)>$D15),0,$E15*IF($G15,1,N(INDEX(Phasing!$I15:$AF15,((YEAR(J$5)-YEAR($C15))*12+MONTH(J$5)-MONTH($C15)+1))))/$F15)) -> 0 | K15: =IF(OR($C15="",$D15="",$F15=0),0,IF(OR(K$5<=Projects!$C$2,((YEAR(K$5)-YEAR($C15))*12+MONTH(K$5)-MONTH($C15)+1)<1,((YEAR(K$5)-YEAR($C15))*12+MONTH(K$5)-MONTH($C15)+1)>$D15),0,$E15*IF($G15,1,N(INDEX(Phasing!$I15:$AF15,((YEAR(K$5)-YEAR($C15))*12+MONTH(K$5)-MONTH($C15)+1))))/$F15)) -> 0 | L15: =IF(OR($C15="",$D15="",$F15=0),0,IF(OR(L$5<=Projects!$C$2,((YEAR(L$5)-YEAR($C15))*12+MONTH(L$5)-MONTH($C15)+1)<1,((YEAR(L$5)-YEAR($C15))*12+MONTH(L$5)-MONTH($C15)+1)>$D15),0,$E15*IF($G15,1,N(INDEX(Phasing!$I15:$AF15,((YEAR(L$5)-YEAR($C15))*12+MONTH(L$5)-MONTH($C15)+1))))/$F15)) -> 0 | M15: =IF(OR($C15="",$D15="",$F15=0),0,IF(OR(M$5<=Projects!$C$2,((YEAR(M$5)-YEAR($C15))*12+MONTH(M$5)-MONTH($C15)+1)<1,((YEAR(M$5)-YEAR($C15))*12+MONTH(M$5)-MONTH($C15)+1)>$D15),0,$E15*IF($G15,1,N(INDEX(Phasing!$I15:$AF15,((YEAR(M$5)-YEAR($C15))*12+MONTH(M$5)-MONTH($C15)+1))))/$F15)) -> 0 | N15: =IF(OR($C15="",$D15="",$F15=0),0,IF(OR(N$5<=Projects!$C$2,((YEAR(N$5)-YEAR($C15))*12+MONTH(N$5)-MONTH($C15)+1)<1,((YEAR(N$5)-YEAR($C15))*12+MONTH(N$5)-MONTH($C15)+1)>$D15),0,$E15*IF($G15,1,N(INDEX(Phasing!$I15:$AF15,((YEAR(N$5)-YEAR($C15))*12+MONTH(N$5)-MONTH($C15)+1))))/$F15)) -> 0 | O15: =IF(OR($C15="",$D15="",$F15=0),0,IF(OR(O$5<=Projects!$C$2,((YEAR(O$5)-YEAR($C15))*12+MONTH(O$5)-MONTH($C15)+1)<1,((YEAR(O$5)-YEAR($C15))*12+MONTH(O$5)-MONTH($C15)+1)>$D15),0,$E15*IF($G15,1,N(INDEX(Phasing!$I15:$AF15,((YEAR(O$5)-YEAR($C15))*12+MONTH(O$5)-MONTH($C15)+1))))/$F15)) -> 0 | ... AQ15: =IF(OR($C15="",$D15="",$F15=0),0,IF(OR(AQ$5<=Projects!$C$2,((YEAR(AQ$5)-YEAR($C15))*12+MONTH(AQ$5)-MONTH($C15)+1)<1,((YEAR(AQ$5)-YEAR($C15))*12+MONTH(AQ$5)-MONTH($C15)+1)>$D15),0,$E15*IF($G15,1,N(INDEX(Phasing!$I15:$AF15,((YEAR(AQ$5)-YEAR($C15))*12+MONTH(AQ$5)-MONTH($C15)+1))))/$F15)) -> 0
A16: 11 | B16: =IF(Projects!B16="","",Projects!B16) | C16: =IF(Projects!D16="","",Projects!D16) | D16: =IF(Projects!E16="","",Projects!E16) | E16: =IF(Projects!B16="",0,N(Projects!I16)) -> 0 | F16: =Phasing!G16 -> 0 | G16: =Phasing!D16=0 -> TRUE | H16: =IF(OR($C16="",$D16="",$F16=0),0,IF(OR(H$5<=Projects!$C$2,((YEAR(H$5)-YEAR($C16))*12+MONTH(H$5)-MONTH($C16)+1)<1,((YEAR(H$5)-YEAR($C16))*12+MONTH(H$5)-MONTH($C16)+1)>$D16),0,$E16*IF($G16,1,N(INDEX(Phasing!$I16:$AF16,((YEAR(H$5)-YEAR($C16))*12+MONTH(H$5)-MONTH($C16)+1))))/$F16)) -> 0 | I16: =IF(OR($C16="",$D16="",$F16=0),0,IF(OR(I$5<=Projects!$C$2,((YEAR(I$5)-YEAR($C16))*12+MONTH(I$5)-MONTH($C16)+1)<1,((YEAR(I$5)-YEAR($C16))*12+MONTH(I$5)-MONTH($C16)+1)>$D16),0,$E16*IF($G16,1,N(INDEX(Phasing!$I16:$AF16,((YEAR(I$5)-YEAR($C16))*12+MONTH(I$5)-MONTH($C16)+1))))/$F16)) -> 0 | J16: =IF(OR($C16="",$D16="",$F16=0),0,IF(OR(J$5<=Projects!$C$2,((YEAR(J$5)-YEAR($C16))*12+MONTH(J$5)-MONTH($C16)+1)<1,((YEAR(J$5)-YEAR($C16))*12+MONTH(J$5)-MONTH($C16)+1)>$D16),0,$E16*IF($G16,1,N(INDEX(Phasing!$I16:$AF16,((YEAR(J$5)-YEAR($C16))*12+MONTH(J$5)-MONTH($C16)+1))))/$F16)) -> 0 | K16: =IF(OR($C16="",$D16="",$F16=0),0,IF(OR(K$5<=Projects!$C$2,((YEAR(K$5)-YEAR($C16))*12+MONTH(K$5)-MONTH($C16)+1)<1,((YEAR(K$5)-YEAR($C16))*12+MONTH(K$5)-MONTH($C16)+1)>$D16),0,$E16*IF($G16,1,N(INDEX(Phasing!$I16:$AF16,((YEAR(K$5)-YEAR($C16))*12+MONTH(K$5)-MONTH($C16)+1))))/$F16)) -> 0 | L16: =IF(OR($C16="",$D16="",$F16=0),0,IF(OR(L$5<=Projects!$C$2,((YEAR(L$5)-YEAR($C16))*12+MONTH(L$5)-MONTH($C16)+1)<1,((YEAR(L$5)-YEAR($C16))*12+MONTH(L$5)-MONTH($C16)+1)>$D16),0,$E16*IF($G16,1,N(INDEX(Phasing!$I16:$AF16,((YEAR(L$5)-YEAR($C16))*12+MONTH(L$5)-MONTH($C16)+1))))/$F16)) -> 0 | M16: =IF(OR($C16="",$D16="",$F16=0),0,IF(OR(M$5<=Projects!$C$2,((YEAR(M$5)-YEAR($C16))*12+MONTH(M$5)-MONTH($C16)+1)<1,((YEAR(M$5)-YEAR($C16))*12+MONTH(M$5)-MONTH($C16)+1)>$D16),0,$E16*IF($G16,1,N(INDEX(Phasing!$I16:$AF16,((YEAR(M$5)-YEAR($C16))*12+MONTH(M$5)-MONTH($C16)+1))))/$F16)) -> 0 | N16: =IF(OR($C16="",$D16="",$F16=0),0,IF(OR(N$5<=Projects!$C$2,((YEAR(N$5)-YEAR($C16))*12+MONTH(N$5)-MONTH($C16)+1)<1,((YEAR(N$5)-YEAR($C16))*12+MONTH(N$5)-MONTH($C16)+1)>$D16),0,$E16*IF($G16,1,N(INDEX(Phasing!$I16:$AF16,((YEAR(N$5)-YEAR($C16))*12+MONTH(N$5)-MONTH($C16)+1))))/$F16)) -> 0 | O16: =IF(OR($C16="",$D16="",$F16=0),0,IF(OR(O$5<=Projects!$C$2,((YEAR(O$5)-YEAR($C16))*12+MONTH(O$5)-MONTH($C16)+1)<1,((YEAR(O$5)-YEAR($C16))*12+MONTH(O$5)-MONTH($C16)+1)>$D16),0,$E16*IF($G16,1,N(INDEX(Phasing!$I16:$AF16,((YEAR(O$5)-YEAR($C16))*12+MONTH(O$5)-MONTH($C16)+1))))/$F16)) -> 0 | ... AQ16: =IF(OR($C16="",$D16="",$F16=0),0,IF(OR(AQ$5<=Projects!$C$2,((YEAR(AQ$5)-YEAR($C16))*12+MONTH(AQ$5)-MONTH($C16)+1)<1,((YEAR(AQ$5)-YEAR($C16))*12+MONTH(AQ$5)-MONTH($C16)+1)>$D16),0,$E16*IF($G16,1,N(INDEX(Phasing!$I16:$AF16,((YEAR(AQ$5)-YEAR($C16))*12+MONTH(AQ$5)-MONTH($C16)+1))))/$F16)) -> 0
A17: 12 | B17: =IF(Projects!B17="","",Projects!B17) | C17: =IF(Projects!D17="","",Projects!D17) | D17: =IF(Projects!E17="","",Projects!E17) | E17: =IF(Projects!B17="",0,N(Projects!I17)) -> 0 | F17: =Phasing!G17 -> 0 | G17: =Phasing!D17=0 -> TRUE | H17: =IF(OR($C17="",$D17="",$F17=0),0,IF(OR(H$5<=Projects!$C$2,((YEAR(H$5)-YEAR($C17))*12+MONTH(H$5)-MONTH($C17)+1)<1,((YEAR(H$5)-YEAR($C17))*12+MONTH(H$5)-MONTH($C17)+1)>$D17),0,$E17*IF($G17,1,N(INDEX(Phasing!$I17:$AF17,((YEAR(H$5)-YEAR($C17))*12+MONTH(H$5)-MONTH($C17)+1))))/$F17)) -> 0 | I17: =IF(OR($C17="",$D17="",$F17=0),0,IF(OR(I$5<=Projects!$C$2,((YEAR(I$5)-YEAR($C17))*12+MONTH(I$5)-MONTH($C17)+1)<1,((YEAR(I$5)-YEAR($C17))*12+MONTH(I$5)-MONTH($C17)+1)>$D17),0,$E17*IF($G17,1,N(INDEX(Phasing!$I17:$AF17,((YEAR(I$5)-YEAR($C17))*12+MONTH(I$5)-MONTH($C17)+1))))/$F17)) -> 0 | J17: =IF(OR($C17="",$D17="",$F17=0),0,IF(OR(J$5<=Projects!$C$2,((YEAR(J$5)-YEAR($C17))*12+MONTH(J$5)-MONTH($C17)+1)<1,((YEAR(J$5)-YEAR($C17))*12+MONTH(J$5)-MONTH($C17)+1)>$D17),0,$E17*IF($G17,1,N(INDEX(Phasing!$I17:$AF17,((YEAR(J$5)-YEAR($C17))*12+MONTH(J$5)-MONTH($C17)+1))))/$F17)) -> 0 | K17: =IF(OR($C17="",$D17="",$F17=0),0,IF(OR(K$5<=Projects!$C$2,((YEAR(K$5)-YEAR($C17))*12+MONTH(K$5)-MONTH($C17)+1)<1,((YEAR(K$5)-YEAR($C17))*12+MONTH(K$5)-MONTH($C17)+1)>$D17),0,$E17*IF($G17,1,N(INDEX(Phasing!$I17:$AF17,((YEAR(K$5)-YEAR($C17))*12+MONTH(K$5)-MONTH($C17)+1))))/$F17)) -> 0 | L17: =IF(OR($C17="",$D17="",$F17=0),0,IF(OR(L$5<=Projects!$C$2,((YEAR(L$5)-YEAR($C17))*12+MONTH(L$5)-MONTH($C17)+1)<1,((YEAR(L$5)-YEAR($C17))*12+MONTH(L$5)-MONTH($C17)+1)>$D17),0,$E17*IF($G17,1,N(INDEX(Phasing!$I17:$AF17,((YEAR(L$5)-YEAR($C17))*12+MONTH(L$5)-MONTH($C17)+1))))/$F17)) -> 0 | M17: =IF(OR($C17="",$D17="",$F17=0),0,IF(OR(M$5<=Projects!$C$2,((YEAR(M$5)-YEAR($C17))*12+MONTH(M$5)-MONTH($C17)+1)<1,((YEAR(M$5)-YEAR($C17))*12+MONTH(M$5)-MONTH($C17)+1)>$D17),0,$E17*IF($G17,1,N(INDEX(Phasing!$I17:$AF17,((YEAR(M$5)-YEAR($C17))*12+MONTH(M$5)-MONTH($C17)+1))))/$F17)) -> 0 | N17: =IF(OR($C17="",$D17="",$F17=0),0,IF(OR(N$5<=Projects!$C$2,((YEAR(N$5)-YEAR($C17))*12+MONTH(N$5)-MONTH($C17)+1)<1,((YEAR(N$5)-YEAR($C17))*12+MONTH(N$5)-MONTH($C17)+1)>$D17),0,$E17*IF($G17,1,N(INDEX(Phasing!$I17:$AF17,((YEAR(N$5)-YEAR($C17))*12+MONTH(N$5)-MONTH($C17)+1))))/$F17)) -> 0 | O17: =IF(OR($C17="",$D17="",$F17=0),0,IF(OR(O$5<=Projects!$C$2,((YEAR(O$5)-YEAR($C17))*12+MONTH(O$5)-MONTH($C17)+1)<1,((YEAR(O$5)-YEAR($C17))*12+MONTH(O$5)-MONTH($C17)+1)>$D17),0,$E17*IF($G17,1,N(INDEX(Phasing!$I17:$AF17,((YEAR(O$5)-YEAR($C17))*12+MONTH(O$5)-MONTH($C17)+1))))/$F17)) -> 0 | ... AQ17: =IF(OR($C17="",$D17="",$F17=0),0,IF(OR(AQ$5<=Projects!$C$2,((YEAR(AQ$5)-YEAR($C17))*12+MONTH(AQ$5)-MONTH($C17)+1)<1,((YEAR(AQ$5)-YEAR($C17))*12+MONTH(AQ$5)-MONTH($C17)+1)>$D17),0,$E17*IF($G17,1,N(INDEX(Phasing!$I17:$AF17,((YEAR(AQ$5)-YEAR($C17))*12+MONTH(AQ$5)-MONTH($C17)+1))))/$F17)) -> 0
... A55: 50 | B55: =IF(Projects!B55="","",Projects!B55) | C55: =IF(Projects!D55="","",Projects!D55) | D55: =IF(Projects!E55="","",Projects!E55) | E55: =IF(Projects!B55="",0,N(Projects!I55)) -> 0 | F55: =Phasing!G55 -> 0 | G55: =Phasing!D55=0 -> TRUE | H55: =IF(OR($C55="",$D55="",$F55=0),0,IF(OR(H$5<=Projects!$C$2,((YEAR(H$5)-YEAR($C55))*12+MONTH(H$5)-MONTH($C55)+1)<1,((YEAR(H$5)-YEAR($C55))*12+MONTH(H$5)-MONTH($C55)+1)>$D55),0,$E55*IF($G55,1,N(INDEX(Phasing!$I55:$AF55,((YEAR(H$5)-YEAR($C55))*12+MONTH(H$5)-MONTH($C55)+1))))/$F55)) -> 0 | I55: =IF(OR($C55="",$D55="",$F55=0),0,IF(OR(I$5<=Projects!$C$2,((YEAR(I$5)-YEAR($C55))*12+MONTH(I$5)-MONTH($C55)+1)<1,((YEAR(I$5)-YEAR($C55))*12+MONTH(I$5)-MONTH($C55)+1)>$D55),0,$E55*IF($G55,1,N(INDEX(Phasing!$I55:$AF55,((YEAR(I$5)-YEAR($C55))*12+MONTH(I$5)-MONTH($C55)+1))))/$F55)) -> 0 | J55: =IF(OR($C55="",$D55="",$F55=0),0,IF(OR(J$5<=Projects!$C$2,((YEAR(J$5)-YEAR($C55))*12+MONTH(J$5)-MONTH($C55)+1)<1,((YEAR(J$5)-YEAR($C55))*12+MONTH(J$5)-MONTH($C55)+1)>$D55),0,$E55*IF($G55,1,N(INDEX(Phasing!$I55:$AF55,((YEAR(J$5)-YEAR($C55))*12+MONTH(J$5)-MONTH($C55)+1))))/$F55)) -> 0 | K55: =IF(OR($C55="",$D55="",$F55=0),0,IF(OR(K$5<=Projects!$C$2,((YEAR(K$5)-YEAR($C55))*12+MONTH(K$5)-MONTH($C55)+1)<1,((YEAR(K$5)-YEAR($C55))*12+MONTH(K$5)-MONTH($C55)+1)>$D55),0,$E55*IF($G55,1,N(INDEX(Phasing!$I55:$AF55,((YEAR(K$5)-YEAR($C55))*12+MONTH(K$5)-MONTH($C55)+1))))/$F55)) -> 0 | L55: =IF(OR($C55="",$D55="",$F55=0),0,IF(OR(L$5<=Projects!$C$2,((YEAR(L$5)-YEAR($C55))*12+MONTH(L$5)-MONTH($C55)+1)<1,((YEAR(L$5)-YEAR($C55))*12+MONTH(L$5)-MONTH($C55)+1)>$D55),0,$E55*IF($G55,1,N(INDEX(Phasing!$I55:$AF55,((YEAR(L$5)-YEAR($C55))*12+MONTH(L$5)-MONTH($C55)+1))))/$F55)) -> 0 | M55: =IF(OR($C55="",$D55="",$F55=0),0,IF(OR(M$5<=Projects!$C$2,((YEAR(M$5)-YEAR($C55))*12+MONTH(M$5)-MONTH($C55)+1)<1,((YEAR(M$5)-YEAR($C55))*12+MONTH(M$5)-MONTH($C55)+1)>$D55),0,$E55*IF($G55,1,N(INDEX(Phasing!$I55:$AF55,((YEAR(M$5)-YEAR($C55))*12+MONTH(M$5)-MONTH($C55)+1))))/$F55)) -> 0 | N55: =IF(OR($C55="",$D55="",$F55=0),0,IF(OR(N$5<=Projects!$C$2,((YEAR(N$5)-YEAR($C55))*12+MONTH(N$5)-MONTH($C55)+1)<1,((YEAR(N$5)-YEAR($C55))*12+MONTH(N$5)-MONTH($C55)+1)>$D55),0,$E55*IF($G55,1,N(INDEX(Phasing!$I55:$AF55,((YEAR(N$5)-YEAR($C55))*12+MONTH(N$5)-MONTH($C55)+1))))/$F55)) -> 0 | O55: =IF(OR($C55="",$D55="",$F55=0),0,IF(OR(O$5<=Projects!$C$2,((YEAR(O$5)-YEAR($C55))*12+MONTH(O$5)-MONTH($C55)+1)<1,((YEAR(O$5)-YEAR($C55))*12+MONTH(O$5)-MONTH($C55)+1)>$D55),0,$E55*IF($G55,1,N(INDEX(Phasing!$I55:$AF55,((YEAR(O$5)-YEAR($C55))*12+MONTH(O$5)-MONTH($C55)+1))))/$F55)) -> 0 | ... AQ55: =IF(OR($C55="",$D55="",$F55=0),0,IF(OR(AQ$5<=Projects!$C$2,((YEAR(AQ$5)-YEAR($C55))*12+MONTH(AQ$5)-MONTH($C55)+1)<1,((YEAR(AQ$5)-YEAR($C55))*12+MONTH(AQ$5)-MONTH($C55)+1)>$D55),0,$E55*IF($G55,1,N(INDEX(Phasing!$I55:$AF55,((YEAR(AQ$5)-YEAR($C55))*12+MONTH(AQ$5)-MONTH($C55)+1))))/$F55)) -> 0
B57: TOTAL | E57: =SUM(E6:E55) -> 9000 | H57: =SUM(H6:H55) -> 0 | I57: =SUM(I6:I55) -> 0 | J57: =SUM(J6:J55) -> 0 | K57: =SUM(K6:K55) -> 0 | L57: =SUM(L6:L55) -> 0 | M57: =SUM(M6:M55) -> 0 | N57: =SUM(N6:N55) -> 0 | O57: =SUM(O6:O55) -> 0 | ... AQ57: =SUM(AQ6:AQ55) -> 0
